Workbook
Name \B: #REF!
Name \B: #REF!
Name \B: #REF!
Name \B: #REF!
Name \B: #REF!
Name \B: #REF!
Name \B: #REF!
Name \B: #REF!
Name \B: #REF!
Name \B: #REF!
Name \B: #REF!
Name \B: #REF!
Name \B: #REF!
Name \B: #REF!
Name \B: #REF!
Name \B: #REF!
Name \B: #REF!
Name \B: #REF!
Name \B: #REF!
Name \B: #REF!
Name \B: #REF!
Name \B: #REF!
Name \B: #REF!
Name \B: #REF!
Name \B: #REF!
Name \B: #REF!
Name \B: #REF!
Name \B: #REF!
Name \B: #REF!
Name \B: #REF!
Name \B: #REF!
Name \B: #REF!
Name \B: #REF!
Name \B: #REF!
Name \B: #REF!
Name \B: #REF!
Name \B: #REF!
Name \B: #REF!
Name \B: #REF!
Name \B: #REF!
Name \B: #REF!
Name \B: #REF!
Name \B: #REF!
Name \B: #REF!
Name \B: #REF!
Name \B: #REF!
Name \B: #REF!
Name \B: #REF!
Name \B: #REF!
Name \B: #REF!
Name \C: #REF!
Name \C: #REF!
Name \C: #REF!
Name \C: #REF!
Name \C: #REF!
Name \C: #REF!
Name \C: #REF!
Name \C: #REF!
Name \C: #REF!
Name \C: #REF!

Sheet Tapioca Starch Price_1
A2: Date | B2: Domestic Price | C2: Date | D2: FOB Bangkok | E2: FOB Hochiminh-Lowest price | F2: FOB Hochiminh-Highest price
A4: 42745 | B4: 11.2 | C4: 42745 | D4: 340
A5: 42752 | B5: 11.2 | C5: 42752 | D5: 340
A6: 42759 | B6: 11 | C6: 42759 | D6: 340
A7: 42766 | B7: 11 | C7: 42766 | D7: 340
A8: 42773 | B8: 11 | C8: 42773 | D8: 340
A9: 42780 | B9: 11 | C9: 42780 | D9: 340
A10: 42787 | B10: 11 | C10: 42787 | D10: 340
A11: 42794 | B11: 11 | C11: 42794 | D11: 340
A12: 42801 | B12: 11.2 | C12: 42801 | D12: 345
A13: 42808 | B13: 11.2 | C13: 42808 | D13: 345
A14: 42815 | B14: 11.2 | C14: 42815 | D14: 345
A15: 42822 | B15: 11.2 | C15: 42822 | D15: 345
... A262: 44558 | B262: 15.1 | C262: 44558 | D262: 490
A263: 44565 | B263: 15.1 | C263: 44565 | D263: 490 | E263: 520 | F263: 540
A264: 44572 | B264: 15.1 | C264: 44572 | D264: 490
A265: 44579 | B265: 15.1 | C265: 44579 | D265: 490
A266: 44586 | B266: 15.1 | C266: 44586 | D266: 490
A267: 44593 | B267: 15.1 | C267: 44593 | D267: 490
A268: 44600 | B268: 15.1 | C268: 44600 | D268: 490
A269: 44607 | B269: 15.1 | C269: 44607 | D269: 495
A270: 44614 | B270: 15.1 | C270: 44614 | D270: 495
A271: 44621 | B271: 15.1 | C271: 44621 | D271: 495
A272: 44628 | B272: 15.15 | C272: 44628 | D272: 495
A273: 44635 | B273: 15.2 | C273: 44635 | D273: 495
A274: 44642 | B274: 15.25 | C274: 44642 | D274: 495
A275: 44649 | B275: 15.35 | C275: 44649 | D275: 495
A276: 44656 | B276: 15.5 | C276: 44656 | D276: 500 | E276: 530 | F276: 560
A277: 44663 | B277: 15.6 | C277: 44663 | D277: 500
A278: 44670 | B278: 15.65 | C278: 44670 | D278: 505
A279: 44677 | B279: 16.1 | C279: 44677 | D279: 510
A280: 44684 | B280: 16.5 | C280: 44684 | D280: 515
A281: 44691 | B281: 16.8 | C281: 44691 | D281: 520
A282: 44698 | B282: 17 | C282: 44698 | D282: 525
A283: 44705 | B283: 17.3 | C283: 44705 | D283: 535
A284: 44712 | B284: 17.35 | C284: 44712 | D284: 540
A285: 44719 | B285: 17.4 | C285: 44719 | D285: 540
A286: 44726 | B286: 17.5 | C286: 44726 | D286: 540
A287: 44733 | B287: 17.5 | C287: 44733 | D287: 540
A288: 44740 | B288: 17.5 | C288: 44740 | D288: 540
A289: 44747 | B289: 17.5 | C289: 44747 | D289: 535 | E289: 540 | F289: 580
A290: 44754 | B290: 17.5 | C290: 44754 | D290: 530
A291: 44761 | B291: 17.5 | C291: 44761 | D291: 525
A292: 44768 | B292: 17.4 | C292: 44768 | D292: 520
A293: 44775 | B293: 17.3 | C293: 44775 | D293: 520
A294: 44782 | B294: 17.2 | C294: 44782 | D294: 520
A295: 44789 | B295: 17.2 | C295: 44789 | D295: 520
A296: 44796 | B296: 17.2 | C296: 44796 | D296: 520
A297: 44803 | B297: 17.2 | C297: 44803 | D297: 515
A298: 44810 | B298: 17.1 | C298: 44810 | D298: 510
A299: 44817 | B299: 17.1 | C299: 44817 | D299: 510
A300: 44824 | B300: 17.1 | C300: 44824 | D300: 510
A301: 44831 | B301: 17 | C301: 44831 | D301: 500
A302: 44838 | B302: 17 | C302: 44838 | D302: 500 | E302: 550 | F302: 590
A303: 44845 | B303: 17 | C303: 44845 | D303: 500
A304: 44852 | B304: 16.9 | C304: 44852 | D304: 495
A305: 44859 | B305: 16.9 | C305: 44859 | D305: 495
A306: 44866 | B306: 16.85 | C306: 44866 | D306: 490
A307: 44873 | B307: 16.8 | C307: 44873 | D307: 485
A308: 44880 | B308: 16.75 | C308: 44880 | D308: 485
A309: 44887 | B309: 16.75 | C309: 44887 | D309: 485
A310: 44894 | B310: 16.75 | C310: 44894 | D310: 490
A311: 44901 | B311: 16.7 | C311: 44901 | D311: 495
A312: 44908 | B312: 16.7 | C312: 44908 | D312: 495
A313: 44915 | B313: 16.6 | C313: 44915 | D313: 495
A314: 44922 | B314: 16.5 | C314: 44922 | D314: 495
A315: 44929 | B315: 16.5 | C315: 44929 | D315: 495 | E315: 560 | F315: 580
A316: 44936 | B316: 16.5 | C316: 44936 | D316: 495
A317: 44943 | B317: 16.5 | C317: 44943 | D317: 500
A318: 44950 | B318: 16.5 | C318: 44950 | D318: 510
A319: 44957 | B319: 16.6 | C319: 44957 | D319: 520
A320: 44964 | B320: 16.7 | C320: 44964 | D320: 525
A321: 44971 | B321: 16.9 | C321: 44971 | D321: 525
A322: 44978 | B322: 17.1 | C322: 44978 | D322: 525
A323: 44985 | B323: 17.15 | C323: 44985 | D323: 525
A324: 44992 | B324: 17.4 | C324: 44992 | D324: 530
A325: 44999 | B325: 17.5 | C325: 44999 | D325: 535
A326: 45006 | B326: 17.7 | C326: 45006 | D326: 545
A327: 45013 | B327: 17.8 | C327: 45013 | D327: 550
A328: 45020 | B328: 17.8 | C328: 45020 | D328: 550 | E328: 570 | F328: 590
A329: 45027 | B329: 17.8 | C329: 45027 | D329: 550
A330: 45034 | B330: 18 | C330: 45034 | D330: 550
A331: 45041 | B331: 18.2 | C331: 45041 | D331: 555
A332: 45048 | B332: 18.3 | C332: 45048 | D332: 560
A333: 45055 | B333: 18.3 | C333: 45055 | D333: 560
A334: 45062 | B334: 18.4 | C334: 45062 | D334: 570
A335: 45069 | B335: 18.4 | C335: 45069 | D335: 570
A336: 45076 | B336: 18.4 | C336: 45076 | D336: 570
A337: 45083 | B337: 18.4 | C337: 45083 | D337: 570
A338: 45090 | B338: 18.4 | C338: 45090 | D338: 570
A339: 45097 | B339: 18.4 | C339: 45097 | D339: 570
A340: 45104 | B340: 18.5 | C340: 45104 | D340: 570
A341: 45111 | B341: 18.5 | C341: 45111 | D341: 570 | E341: 560 | F341: 590
A342: 45118 | B342: 18.5 | C342: 45118 | D342: 570
A343: 45125 | B343: 18.5 | C343: 45125 | D343: 570
A344: 45132 | B344: 18.5 | C344: 45132 | D344: 570
A345: 45146 | B345: 18.5 | C345: 45146 | D345: 570
A346: 45153 | B346: 18.5 | C346: 45153 | D346: 570
A347: 45160 | B347: 18.5 | C347: 45160 | D347: 570
A348: 45167 | B348: 18.5 | C348: 45167 | D348: 570
...

Sheet Tapioca Production_1
B2: Thailand Tapioca Production
B3: Crop Year | C3: Yield | D3: Crop Year | E3: Plant Area | F3: Production
B4: (October-September) | C4: (Ton/Rai) | D4: (October-September) | E4: (Rai) | F4: (Ton)
B5: 2005/2006 | C5: 3.375 | D5: 2005/2006 | E5: 6692537 | F5: 22584402
B6: 2006/2007 | C6: 3.668 | D6: 2006/2007 | E6: 7201243 | F6: 26411233
B7: 2007/2008 | C7: 3.401 | D7: 2007/2008 | E7: 7397098 | F7: 25155797
B8: 2008/2009 | C8: 3.628 | D8: 2008/2009 | E8: 8292146 | F8: 30088024
B9: 2009/2010 | C9: 3.013 | D9: 2009/2010 | E9: 7302839 | F9: 22005740
B10: 2010/2011 | C10: 3.088 | D10: 2010/2011 | E10: 7096173 | F10: 21912416
B11: 2011/2012 | C11: 3.362 | D11: 2011/2012 | E11: 7911323 | F11: 26601090
B12: 2012/2013 | C12: 3.474 | D12: 2012/2013 | E12: 8138953 | F12: 28275565
B13: 2013/2014 | C13: 3.492 | D13: 2013/2014 | E13: 8656942 | F13: 30227542
B14: 2014/2015 | C14: 3.864 | D14: 2014/2015 | E14: 8697948 | F14: 33610487
B15: 2015/2016 | C15: 3.426 | D15: 2015/2016 | E15: 8919803 | F15: 30557857
B16: 2016/2017 | C16: 3.472 | D16: 2016/2017 | E16: 8910021 | F16: 30935529
... B24: 2024/2025 | C24: 2.958 | D24: 2024/2025 | E24: 8445471 | F24: 24983311
B25: 2025/2026 | D25: 2025/2026 | F25: 18000000
B26: 2026/2076 | D26: 2026/2027

Sheet Tapioca Chip Price_1
A2: Date | B2: (THB/kg) | C2: TH @Srichang Port (USD/MT) | D2: VN to China (USD/MT) | E2: VN to Korea (USD/MT)
A3: 44927 | B3: 8.75 | C3: 269
A4: 44958 | B4: 9 | C4: 275
A5: 44986 | B5: 9.18 | C5: 273
A6: 45017 | B6: 9.38 | C6: 270
A7: 45047 | B7: 9.55 | C7: 266
A8: 45078 | B8: 9.45 | C8: 263
A9: 45108 | B9: 9.35 | C9: 265
A10: 45139 | B10: 9.6 | C10: 273
A11: 45170 | B11: 9.75 | C11: 280
A12: 45200 | B12: 9.68 | C12: 283
A13: 45231 | B13: 9.8 | C13: 278
A14: 45261 | B14: 9.7 | C14: 269
... A26: 45627 | B26: 6.5 | C26: 190
A27: 45658
A28: 45689
A29: 45717
A30: 45748 | B30: 5.45 | C30: 185
A31: 45755 | B31: 5.48 | C31: 185
A32: 45764 | B32: 5.48 | C32: 185
A33: 45769 | B33: 5.53 | C33: 185
A34: 45771 | B34: 5.53 | C34: 185
A35: 45776 | B35: 5.53 | C35: 185
A36: 45785 | B36: 5.58 | C36: 185
A37: 45792 | B37: 5.63 | C37: 192.5
A38: 45797 | B38: 5.63 | C38: 192.5
A39: 45804 | B39: 5.63 | C39: 197.5
A40: 45813 | B40: 5.88 | C40: 197.5
A41: 45818 | B41: 5.88 | C41: 205
... A68: 46007 | B68: 6.13 | C68: 212.5
A69: 46014 | B69: 6.28 | C69: 212.5 | D69: 235 | E69: 290
A70: 46028 | B70: 6.28 | C70: 217.5 | D70: 240 | E70: 295
A71: 46035 | B71: 6.18 | C71: 217.5 | D71: 240 | E71: 295
A72: 46042 | B72: 6.18 | C72: 217.5 | D72: 240 | E72: 295
A73: 46049 | B73: 6.18 | C73: 217.5 | D73: 240 | E73: 295
A74: 46056 | B74: 6.18 | C74: 217.5 | D74: 240 | E74: 295
A75: 46063 | B75: 6.45 | C75: 222.5 | D75: 240 | E75: 295
A76: 46070 | B76: 6.5 | C76: 227.5 | D76: 240 | E76: 295
A77: 46077 | B77: 6.5 | C77: 227.5 | D77: 240 | E77: 295
A78: 46086 | B78: 6.6 | C78: 235 | D78: 250 | E78: 305
A79: 46091 | B79: 6.68 | C79: 245 | D79: 250 | E79: 305
A80: 46098 | B80: 6.9 | C80: 245 | D80: 250 | E80: 305
... A82: 46112 | B82: 7.65 | C82: 255 | D82: 255 | E82: 310
A83: 46119 | B83: =(7.75+7.8)/2 -> 7.775 | C83: 255 | D83: 260 | E83: 315
A84: 46121 | B84: =(7.75+7.8)/2 -> 7.775 | C84: =(255+265)/2 -> 260 | D84: 260 | E84: 315
A85: 46133 | B85: =(7.75+8)/2 -> 7.875 | C85: =(255+265)/2 -> 260 | D85: 260 | E85: 315
A86: 46140 | B86: =(7.6+8)/2 -> 7.8 | C86: =(255+265)/2 -> 260 | D86: 265 | E86: 320
A87: 46149 | B87: =(7.6+8)/2 -> 7.8 | C87: =(255+265)/2 -> 260 | D87: 265 | E87: 320
A88: 46154 | B88: 7.8 | C88: 260 | D88: 265 | E88: 320
A89: 46161 | B89: 7.75 | C89: 260 | D89: 265 | E89: 320
A90: 46168 | B90: 7.75 | C90: 260 | D90: 265 | E90: 320
A91: 46178 | B91: 7.75 | C91: 260 | D91: 265 | E91: 320
A92: 46182 | B92: 7.75 | C92: 260 | D92: 265 | E92: 320

Sheet Ethanol Price_1
B2: Ethanol (THB./Liter)
B3: Month | C3: THB./Liter
B4: 43101 | C4: 24.57
B5: 43132 | C5: 24.45
B6: 43160 | C6: 24.44
B7: 43191 | C7: 23.59
B8: 43221 | C8: 23.59
B9: 43252 | C9: 23.59
B10: 43282 | C10: 23.4
B11: 43313 | C11: 23.4
B12: 43344 | C12: 23.4
B13: 43374 | C13: 23.31
B14: 43405 | C14: 23.31
B15: 43435 | C15: 23.31
... B27: 43800 | C27: 22.04
B28: 43831 | C28: =AVERAGE(C16:C27) -> 22.0725
B29: 43862 | C29: 22.61
B30: 43891 | C30: 22.61
B31: 43922 | C31: 22.61
B32: 43952 | C32: 23.28
B33: 43983 | C33: 23.28
B34: 44013 | C34: 23.28
B35: 44044 | C35: 23.16
B36: 44075 | C36: 23.16
B37: 44105 | C37: 23.16
B38: 44136 | C38: 23.8
B39: 44166 | C39: 23.8
B40: 44197 | C40: 24.83
... B70: 45474 | C70: 30.52
B71: 45505
B72: 45536
B73: 45566
B74: 45597
B75: 45627
B76: 45658
B77: 45689
B78: 45717
B79: 45748 | C79: 19.38
B80: 45778 | C80: 19.37
B81: 45809 | C81: 19.39
B82: 45839 | C82: 18.34
B83: 45870 | C83: 18.33
B84: 45901 | C84: 18.33
B85: 45931 | C85: 19.81
B86: 45962 | C86: 19.8
B87: 45992 | C87: 19.8
B88: 46023 | C88: 20.83
B89: 46054 | C89: 20.82
B90: 46082 | C90: 20.82
... B93: 46174 | C93: 21.98
B95: Diff Dec-25 | C95: =C91-C87 -> 1.61 | E95: ***In 2022, Thailand capped diesel prices at 30–35 baht/liter using the Oil Fuel Fund to cushion the impact of soaring global oil prices from the Russia-Ukraine crisis.
C96: =C95/C87 -> 0.081313131 | E96: ***According to the Ministry of Energy’s policy, ethanol prices will no longer be disclosed starting from August 2024 onwards.
E97: ***Reference TTTa_Price has been used since April 2025.

Sheet Dry Pulp Monthly price_1
B2: Market dry pulp price
A3: Jan'24 | B3: 4.6
A4: Feb'24 | B4: 4.2041667
A5: Mar'24 | B5: 3.7980769
A6: Apr'24 | B6: 3.24
A7: May'24 | B7: 3.2
A8: Jun'24 | B8: 3.2
A9: Jul'24 | B9: 3.2
A10: Aug'24 | B10: 3.2
A11: Sep'24 | B11: 3.0153846
A12: Oct'24 | B12: 2.6653846
A13: Nov'24 | B13: 2.4230769
A14: Dec'24 | B14: 2.3125
... A31: May'26 | B31: 5.5

Sheet Dry Pulp Daily price_1
A1: Date | B1: Start | C1: End | D1: Average | F1: https://www.nettathai.org/2012-02-06-06-49-09.html
A2: 44501 | B2: =4.5 -> 4.5 | D2: =AVERAGE(B2:C2) -> 4.5
A3: 44503 | B3: =4.5 -> 4.5 | D3: =AVERAGE(B3:C3) -> 4.5
A4: 44505 | B4: =4.5 -> 4.5 | D4: =AVERAGE(B4:C4) -> 4.5
A5: 44508 | B5: =4.5 -> 4.5 | D5: =AVERAGE(B5:C5) -> 4.5
A6: 44510 | B6: =4.5 -> 4.5 | D6: =AVERAGE(B6:C6) -> 4.5
A7: 44512 | B7: =4.5 -> 4.5 | D7: =AVERAGE(B7:C7) -> 4.5
A8: 44515 | B8: 4.5 | C8: 4.6 | D8: =AVERAGE(B8:C8) -> 4.55
A9: 44517 | B9: 4.5 | C9: 4.6 | D9: =AVERAGE(B9:C9) -> 4.55
A10: 44519 | B10: 4.5 | C10: 4.6 | D10: =AVERAGE(B10:C10) -> 4.55
A11: 44522 | B11: 4.5 | C11: 4.6 | D11: =AVERAGE(B11:C11) -> 4.55
A12: 44524 | B12: 4.5 | C12: 4.6 | D12: =AVERAGE(B12:C12) -> 4.55
A13: 44526 | B13: 4.5 | C13: 4.6 | D13: =AVERAGE(B13:C13) -> 4.55
A14: 44529 | B14: 4.5 | C14: 4.6 | D14: =AVERAGE(B14:C14) -> 4.55
A15: 44531 | B15: 4.6 | D15: =AVERAGE(B15:C15) -> 4.6
A16: 44533 | B16: 4.6 | D16: =AVERAGE(B16:C16) -> 4.6
A17: 44536 | B17: 4.5 | C17: 4.6 | D17: =AVERAGE(B17:C17) -> 4.55
A18: 44538 | B18: 4.5 | C18: 4.6 | D18: =AVERAGE(B18:C18) -> 4.55
A19: 44540 | B19: 4.5 | C19: 4.6 | D19: =AVERAGE(B19:C19) -> 4.55
A20: 44543 | B20: 4.5 | C20: 4.6 | D20: =AVERAGE(B20:C20) -> 4.55
A21: 44545 | B21: 4.5 | C21: 4.6 | D21: =AVERAGE(B21:C21) -> 4.55
A22: 44547 | B22: 4.5 | C22: 4.6 | D22: =AVERAGE(B22:C22) -> 4.55
A23: 44550 | B23: 4.5 | C23: 4.6 | D23: =AVERAGE(B23:C23) -> 4.55
A24: 44552 | B24: 4.5 | C24: 4.6 | D24: =AVERAGE(B24:C24) -> 4.55
A25: 44554 | B25: 4.5 | C25: 4.6 | D25: =AVERAGE(B25:C25) -> 4.55
A26: 44557 | B26: 4.5 | C26: 4.6 | D26: =AVERAGE(B26:C26) -> 4.55
A27: 44559 | B27: 4.6 | D27: =AVERAGE(B27:C27) -> 4.6
A28: 5/12022 | B28: 4.5 | C28: 4.6 | D28: =AVERAGE(B28:C28) -> 4.55
A29: 44568 | B29: 4.5 | C29: 4.6 | D29: =AVERAGE(B29:C29) -> 4.55
A30: 44571 | B30: 4.5 | C30: 4.6 | D30: =AVERAGE(B30:C30) -> 4.55
A31: 44573 | B31: 4.5 | C31: 4.6 | D31: =AVERAGE(B31:C31) -> 4.55
A32: 44575 | B32: 4.5 | C32: 4.6 | D32: =AVERAGE(B32:C32) -> 4.55
A33: 44578 | B33: 4.5 | C33: 4.6 | D33: =AVERAGE(B33:C33) -> 4.55
A34: 44580 | B34: 4.5 | C34: 4.6 | D34: =AVERAGE(B34:C34) -> 4.55
A35: 44582 | B35: 4.5 | C35: 4.6 | D35: =AVERAGE(B35:C35) -> 4.55
A36: 44585 | B36: 4.6 | D36: =AVERAGE(B36:C36) -> 4.6
A37: 44587 | B37: 4.6 | C37: 4.8 | D37: =AVERAGE(B37:C37) -> 4.7
A38: 44589 | B38: 4.6 | C38: 4.8 | D38: =AVERAGE(B38:C38) -> 4.7
A39: 44592 | B39: 4.5 | C39: 4.6 | D39: =AVERAGE(B39:C39) -> 4.55
A40: 44594 | B40: 4.5 | C40: 4.6 | D40: =AVERAGE(B40:C40) -> 4.55
A41: 44596 | B41: 4.5 | C41: 4.6 | D41: =AVERAGE(B41:C41) -> 4.55
A42: 44599 | B42: 4.5 | C42: 4.6 | D42: =AVERAGE(B42:C42) -> 4.55
A43: 44601 | B43: 4.6 | D43: =AVERAGE(B43:C43) -> 4.6
A44: 44603 | B44: 4.6 | D44: =AVERAGE(B44:C44) -> 4.6
A45: 44606 | B45: 4.6 | C45: 4.7 | D45: =AVERAGE(B45:C45) -> 4.65
A46: 44610 | B46: 4.6 | C46: 4.7 | D46: =AVERAGE(B46:C46) -> 4.65
A47: 44613 | B47: 4.6 | C47: 4.7 | D47: =AVERAGE(B47:C47) -> 4.65
A48: 44615 | B48: 4.6 | C48: 4.7 | D48: =AVERAGE(B48:C48) -> 4.65
A49: 44617 | B49: 4.6 | C49: 4.7 | D49: =AVERAGE(B49:C49) -> 4.65
A50: 44620 | B50: 4.6 | C50: 4.7 | D50: =AVERAGE(B50:C50) -> 4.65
A51: 44622 | B51: 4.6 | C51: 4.7 | D51: =AVERAGE(B51:C51) -> 4.65
A52: 44624 | B52: 4.6 | C52: 4.7 | D52: =AVERAGE(B52:C52) -> 4.65
A53: 44627 | B53: 4.6 | C53: 4.8 | D53: =AVERAGE(B53:C53) -> 4.7
A54: 44629 | B54: 4.6 | C54: 4.8 | D54: =AVERAGE(B54:C54) -> 4.7
A55: 44631 | B55: 4.6 | C55: 4.8 | D55: =AVERAGE(B55:C55) -> 4.7
A56: 44634 | B56: 4.6 | C56: 4.8 | D56: =AVERAGE(B56:C56) -> 4.7
... A71: 44676 | B71: 4.9 | C71: 5 | D71: =AVERAGE(B71:C71) -> 4.95
A72: 44678 | B72: 5 | D72: =AVERAGE(B72:C72) -> 5
A73: 44680 | B73: 5 | C73: 5.1 | D73: =AVERAGE(B73:C73) -> 5.05
A74: 44684 | B74: 5.1 | C74: 5.2 | D74: =AVERAGE(B74:C74) -> 5.15
A75: 44686 | B75: 5.1 | C75: 5.2 | D75: =AVERAGE(B75:C75) -> 5.15
A76: 44687 | B76: 5.1 | C76: 5.2 | D76: =AVERAGE(B76:C76) -> 5.15
A77: 44690 | B77: 5.2 | C77: 5.3 | D77: =AVERAGE(B77:C77) -> 5.25
A78: 44692 | B78: 5.2 | C78: 5.3 | D78: =AVERAGE(B78:C78) -> 5.25
A79: 44694 | B79: 5.2 | C79: 5.3 | D79: =AVERAGE(B79:C79) -> 5.25
A80: 44699 | B80: 5.2 | C80: 5.3 | D80: =AVERAGE(B80:C80) -> 5.25
A81: 44701 | B81: 5.2 | C81: 5.3 | D81: =AVERAGE(B81:C81) -> 5.25
A82: 44704 | B82: 5.2 | C82: 5.3 | D82: =AVERAGE(B82:C82) -> 5.25
A83: 44706 | B83: 5.2 | C83: 5.3 | D83: =AVERAGE(B83:C83) -> 5.25
A84: 44708 | B84: 5.2 | C84: 5.3 | D84: =AVERAGE(B84:C84) -> 5.25
... A112: 44778 | B112: 5.5 | C112: 5.6 | D112: =AVERAGE(B112:C112) -> 5.55
A113: 44781 | B113: 5.5 | D113: =AVERAGE(B113:C113) -> 5.5
A114: 44783 | B114: 5.5 | D114: =AVERAGE(B114:C114) -> 5.5
A115: 44788 | B115: 5.5 | D115: =AVERAGE(B115:C115) -> 5.5
A116: 44790 | B116: 5.5 | D116: =AVERAGE(B116:C116) -> 5.5
A117: 44792 | B117: 5.5 | D117: =AVERAGE(B117:C117) -> 5.5
A118: 44795 | B118: 5.5 | D118: =AVERAGE(B118:C118) -> 5.5
A119: 44797 | B119: 5.5 | D119: =AVERAGE(B119:C119) -> 5.5
A120: 44799 | B120: 5.5 | D120: =AVERAGE(B120:C120) -> 5.5
A121: 44802 | B121: 5.5 | D121: =AVERAGE(B121:C121) -> 5.5
A122: 44806 | B122: 5.5 | D122: =AVERAGE(B122:C122) -> 5.5
A123: 44809 | B123: 5.5 | D123: =AVERAGE(B123:C123) -> 5.5
A124: 44811 | B124: 5.5 | D124: =AVERAGE(B124:C124) -> 5.5
... A140: 44855 | B140: 5.5 | D140: =AVERAGE(B140:C140) -> 5.5
A141: 44860 | B141: 5.4 | C141: 5.5 | D141: =AVERAGE(B141:C141) -> 5.45
A142: 44865 | B142: 5.4 | C142: 5.5 | D142: =AVERAGE(B142:C142) -> 5.45
A143: 44867 | B143: 5.4 | C143: 5.5 | D143: =AVERAGE(B143:C143) -> 5.45
A144: 44869 | B144: 5.4 | C144: 5.5 | D144: =AVERAGE(B144:C144) -> 5.45
A145: 44872 | B145: 5.4 | C145: 5.5 | D145: =AVERAGE(B145:C145) -> 5.45
A146: 44874 | B146: 5.4 | C146: 5.5 | D146: =AVERAGE(B146:C146) -> 5.45
A147: 44876 | B147: 5.4 | C147: 5.5 | D147: =AVERAGE(B147:C147) -> 5.45
A148: 44879 | B148: 5.4 | C148: 5.5 | D148: =AVERAGE(B148:C148) -> 5.45
A149: 44881 | B149: 5.4 | C149: 5.5 | D149: =AVERAGE(B149:C149) -> 5.45
A150: 44883 | B150: 5.4 | C150: 5.5 | D150: =AVERAGE(B150:C150) -> 5.45
A151: 44886 | B151: 5.4 | C151: 5.5 | D151: =AVERAGE(B151:C151) -> 5.45
A152: 44888 | B152: 5.4 | C152: 5.5 | D152: =AVERAGE(B152:C152) -> 5.45
... A241: 45142 | B241: 5.8 | C241: 5.9 | D241: =AVERAGE(B241:C241) -> 5.85
A242: 45145 | B242: 5.8 | D242: =AVERAGE(B242:C242) -> 5.8
A243: 45147 | B243: 5.8 | C243: 5.9 | D243: =AVERAGE(B243:C243) -> 5.85
A244: 45149 | B244: 5.8 | D244: =AVERAGE(B244:C244) -> 5.8
...

Sheet LE02026 cost LV11022026_Origi
A1: LE02026 Cost projection E1 (LV:11/2/2026)
A3: SK plant | B3: Jan | C3: Feb | D3: Mar | E3: Apr | F3: May | G3: Jun | H3: Jul | I3: Aug | J3: Sep | K3: Oct | L3: Nov | M3: Dec | N3: Total/Avg.
A5: Day operation | B5: 27 | C5: 28 | D5: 31 | E5: 24 | F5: 31 | G5: 30 | H5: 30 | I5: 31 | J5: 30 | K5: 31 | L5: 30 | M5: 26 | N5: =SUM(B5:M5) -> 349
A6: Grinding/day without waxy | B6: =B7/B5 -> 1088.8185 | C6: =C7/C5 -> 1401.25 | D6: =D7/D5 -> 1551.6129 | E6: =E7/E5 -> 1252.0833 | F6: =F7/F5 -> 1538.7097 | G6: =G7/G5 -> 1410 | H6: =H7/H5 -> 1393.3333 | I6: =I7/I5 -> 1345.1613 | ... N6: =N7/N5 -> 1337.0576
A7: Grinding/month , tons | B7: 29398.1 | C7: 39235 | D7: 48100 | E7: 30050 | F7: 47700 | G7: 42300 | H7: 41800 | I7: 41700 | J7: 39700 | K7: 38700 | L7: 37350 | M7: 30600 | N7: =SUM(B7:M7) -> 466633.1
A9: Roots purchased/month , tons | B9: 29954.31 | C9: 41200 | D9: 48100 | E9: 30050 | F9: 47700 | G9: 42300 | H9: 41800 | I9: 41700 | J9: 39700 | K9: 38700 | L9: 37350 | M9: 30600 | N9: =SUM(B9:M9) -> 469154.31
A10: Starch content , % | B10: 27.073368 | C10: 27.256311 | D10: ='[60]SK MAP - Mar 2026 (2)'!G13 -> 25.742204 | E10: ='[60]SK MAP - Apr 2026 (2)'!G13 -> 22 | F10: ='[60]SK MAP - May 2026 (2)'!G13 -> 20.43501 | G10: ='[60]SK MAP - Jun 2026 (2)'!G13 -> 20.858156 | H10: ='[60]SK MAP - Jul 2026 (2)'!G13 -> 21.5 | I10: ='[60]SK MAP - Aug 2026 (2)'!G13 -> 22.977698 | J10: ='[60]SK MAP - Sep 26 (2)'!G13 -> 23.924433 | K10: ='[60]SK MAP - Oct 26 (2)'!G13 -> 24.503876 | L10: ='[60]SK MAP - Nov 26 (2)'!G13 -> 25.989759 | M10: ='[60]SK MAP - Dec 26 (2)'!G13 -> 26.745098 | N10: =N14/(N9*1000)*100 -> 23.945984
A11: Price , THB/kg. | B11: 2.8182197 | C11: 2.8494175 | D11: ='[60]SK MAP - Mar 2026 (2)'!H13 -> 2.9097713 | E11: ='[60]SK MAP - Apr 2026 (2)'!H13 -> 2.9020799 | F11: ='[60]SK MAP - May 2026 (2)'!H13 -> 2.8197589 | G11: ='[60]SK MAP - Jun 2026 (2)'!H13 -> 2.8361702 | H11: ='[60]SK MAP - Jul 2026 (2)'!H13 -> 2.781244 | I11: ='[60]SK MAP - Aug 2026 (2)'!H13 -> 2.8942446 | J11: ='[60]SK MAP - Sep 26 (2)'!H13 -> 2.9433249 | K11: ='[60]SK MAP - Oct 26 (2)'!H13 -> 2.9290698 | L11: ='[60]SK MAP - Nov 26 (2)'!H13 -> 3.0487952 | M11: ='[60]SK MAP - Dec 26 (2)'!H13 -> 3.0852941 | N11: =N15/(N9*1000) -> 2.8964613 | R11: Actual 2025
A12: PPDS , THB/kg. | B12: =B11/B10*100 -> 10.409564 | C12: =C11/C10*100 -> 10.454157 | D12: =D11/D10*100 -> 11.303505 | E12: =E11/E10*100 -> 13.191272 | F12: =F11/F10*100 -> 13.798666 | G12: =G11/G10*100 -> 13.597416 | H12: =H11/H10*100 -> 12.936019 | I12: =I11/I10*100 -> 12.595886 | ... N12: =N11/N10*100 -> 12.095813 | P12: =#REF! -> #REF! | R12: =#REF! -> #REF!
A14: Weight starch , kg | B14: =((B9*1000)*B10)/100 -> 8109640.5 | C14: =((C9*1000)*C10)/100 -> 11229600 | D14: =((D9*1000)*D10)/100 -> 12382000 | E14: =((E9*1000)*E10)/100 -> 6611000 | F14: =((F9*1000)*F10)/100 -> 9747500 | G14: =((G9*1000)*G10)/100 -> 8823000 | H14: =((H9*1000)*H10)/100 -> 8987000 | I14: =((I9*1000)*I10)/100 -> 9581700 | ... M14: =((M9*1000)*M10)/100 -> 8184000 | N14: =SUM(B14:M14) -> 1.1234362e+08
A15: Amount , THB | B15: =(B9*1000)*B11 -> 84417826 | C15: =(C9*1000)*C11 -> 117396000 | D15: =(D9*1000)*D11 -> 139960000 | E15: =(E9*1000)*E11 -> 87207500 | F15: =(F9*1000)*F11 -> 134502500 | G15: =(G9*1000)*G11 -> 119970000 | H15: =(H9*1000)*H11 -> 116256000 | I15: =(I9*1000)*I11 -> 1.2069e+08 | ... M15: =(M9*1000)*M11 -> 94410000 | N15: =SUM(B15:M15) -> 1358887326
A17: Co-products prices , THB/kg
A18: Pulp (moisture 79%) | B18: 0.282 | C18: 0.254 | D18: 0.254 | E18: 0.254 | F18: 0.254 | G18: 0.254 | H18: 0.254 | I18: 0.254 | J18: 0.254 | K18: 0.254 | L18: 0.254 | M18: 0.254 | N18: =AVERAGE(B18:M18) -> 0.25633333
A19: Soil Skin | B19: 0.03 | C19: 0.03 | D19: 0.03 | E19: 0.03 | F19: 0.03 | G19: 0.03 | H19: 0.03 | I19: 0.03 | J19: 0.03 | K19: 0.03 | L19: 0.03 | M19: 0.03 | N19: =AVERAGE(B19:M19) -> 0.03
A20: Wash Skin | B20: 0.2 | C20: 0.2 | D20: 0.2 | E20: 0.2 | F20: 0.2 | G20: 0.2 | H20: 0.2 | I20: 0.2 | J20: 0.2 | K20: 0.2 | L20: 0.2 | M20: 0.2 | N20: =AVERAGE(B20:M20) -> 0.2
A21: Pulp moisture, actual | B21: 0.7875
A24: KSN plant | B24: Jan | C24: Feb | D24: Mar | E24: Apr | F24: May | G24: Jun | H24: Jul | I24: Aug | J24: Sep | K24: Oct | L24: Nov | M24: Dec | N24: Total/Avg.
A26: Day operation | B26: 28 | C26: 28 | D26: 31 | E26: 24 | F26: 31 | G26: 30 | H26: 31 | I26: 31 | J26: 30 | K26: 31 | L26: 30 | M26: 26 | N26: =SUM(B26:M26) -> 351
A27: Grinding/day without waxy | B27: =B28/B26 -> 516.30804 | C27: 600 | D27: 650 | E27: 700 | F27: 700 | G27: 700 | H27: 700 | I27: 700 | J27: 700 | K27: 700 | L27: 700 | M27: 600 | N27: =N28/N26 -> 665.54594
A28: Grinding/month , tons | B28: 14456.625 | C28: =C27*C26 -> 16800 | D28: =D27*D26 -> 20150 | E28: =E27*E26 -> 16800 | F28: =F27*F26 -> 21700 | G28: =G27*G26 -> 21000 | H28: =H27*H26 -> 21700 | I28: =I27*I26 -> 21700 | J28: =J27*J26 -> 21000 | ... M28: =M27*M26 -> 15600 | N28: =SUM(B28:M28) -> 233606.62
A30: Roots purchased/month , tons | B30: 15610.621 | C30: 16800 | D30: 20150 | E30: 16800 | F30: 21700 | G30: 21000 | H30: 21700 | I30: 21700 | J30: 21000 | K30: 21700 | L30: 21000 | M30: 15600 | N30: =SUM(B30:M30) -> 234760.62
A31: Actual starch content | B31: 27.464032 | C31: 27.333333 | D31: ='[60]KSN MAP - Mar 2026 (2)'!G13 -> 26.184615 | E31: ='[60]KSN MAP - Apr 2026 (2)'!G13 -> 23.807143 | F31: ='[60]KSN MAP - May 2026 (2)'!G13 -> 21.551429 | G31: ='[60]KSN MAP - Jun 2026 (2)'!G13 -> 21.496429 | H31: ='[60]KSN MAP - Jul 2026 (2)'!G13 -> 21.995 | I31: ='[60]KSN MAP - Aug 2026 (2)'!G13 -> 23.5 | J31: ='[60]KSN MAP - Sep 2026 (2)'!G13 -> 24.404286 | K31: ='[60]KSN MAP - Oct 2026 (2)'!G13 -> 25.2 | L31: ='[60]KSN MAP - Nov 2026 (2)'!G13 -> 25.7 | M31: ='[60]KSN MAP - Dec 2026 (2)'!G13 -> 27.5 | N31: =N35/(N30*1000)*100 -> 24.492494
A32: Actual price | B32: 2.9210987 | C32: 2.9346667 | D32: ='[60]KSN MAP - Mar 2026 (2)'!H13 -> 2.8946154 | E32: ='[60]KSN MAP - Apr 2026 (2)'!H13 -> 2.8442857 | F32: ='[60]KSN MAP - May 2026 (2)'!H13 -> 2.7264286 | G32: ='[60]KSN MAP - Jun 2026 (2)'!H13 -> 2.755 | H32: ='[60]KSN MAP - Jul 2026 (2)'!H13 -> 2.7142857 | I32: ='[60]KSN MAP - Aug 2026 (2)'!H13 -> 2.7942857 | J32: ='[60]KSN MAP - Sep 2026 (2)'!H13 -> 2.8342857 | K32: ='[60]KSN MAP - Oct 2026 (2)'!H13 -> 2.9057143 | L32: ='[60]KSN MAP - Nov 2026 (2)'!H13 -> 2.9971429 | M32: ='[60]KSN MAP - Dec 2026 (2)'!H13 -> 3.0833333 | N32: =N36/(N30*1000) -> 2.859004 | R32: =R11 -> Actual 2025
A33: PPDS | B33: 10.636088 | C33: =C32/C31*100 -> 10.736585 | D33: =D32/D31*100 -> 11.054642 | E33: =E32/E31*100 -> 11.947195 | F33: =F32/F31*100 -> 12.650802 | G33: =G32/G31*100 -> 12.816082 | H33: =H32/H31*100 -> 12.340467 | I33: =I32/I31*100 -> 11.890578 | J33: =J32/J31*100 -> 11.613885 | ... N33: =N32/N31*100 -> 11.67298 | P33: =#REF! -> #REF! | R33: =#REF! -> #REF!
A35: Weight starch , kg | B35: =((B30*1000)*B31)/100 -> 4287306 | C35: =((C30*1000)*C31)/100 -> 4592000 | D35: =((D30*1000)*D31)/100 -> 5276200 | E35: =((E30*1000)*E31)/100 -> 3999600 | F35: =((F30*1000)*F31)/100 -> 4676660 | G35: =((G30*1000)*G31)/100 -> 4514250 | H35: =((H30*1000)*H31)/100 -> 4772915 | I35: =((I30*1000)*I31)/100 -> 5099500 | ... M35: =((M30*1000)*M31)/100 -> 4290000 | N35: =SUM(B35:M35) -> 57498731
A36: Amount , THB | B36: =(B30*1000)*B32 -> 45600164 | C36: =(C30*1000)*C32 -> 49302400 | D36: =(D30*1000)*D32 -> 58326500 | E36: =(E30*1000)*E32 -> 47784000 | F36: =(F30*1000)*F32 -> 59163500 | G36: =(G30*1000)*G32 -> 57855000 | H36: =(H30*1000)*H32 -> 58900000 | I36: =(I30*1000)*I32 -> 60636000 | ... M36: =(M30*1000)*M32 -> 48100000 | N36: =SUM(B36:M36) -> 6.7118156e+08
A38: Co-products prices, THB/kg
A39: Pulp | B39: 0.134 | C39: 0.134 | D39: 0.134 | E39: 0.134 | F39: 0.134 | G39: 0.134 | H39: 0.134 | I39: 0.134 | J39: 0.134 | K39: 0.134 | L39: 0.134 | M39: 0.134 | N39: =AVERAGE(B39:M39) -> 0.134
A40: Soil Skin | B40: 0.03 | C40: 0.03 | D40: 0.03 | E40: 0.03 | F40: 0.03 | G40: 0.03 | H40: 0.03 | I40: 0.03 | J40: 0.03 | K40: 0.03 | L40: 0.03 | M40: 0.03 | N40: =AVERAGE(B40:M40) -> 0.03
A41: Wash Skin | B41: 0.12 | C41: 0.12 | D41: 0.12 | E41: 0.12 | F41: 0.12 | G41: 0.12 | H41: 0.12 | I41: 0.12 | J41: 0.12 | K41: 0.12 | L41: 0.12 | M41: 0.12 | N41: =AVERAGE(B41:M41) -> 0.12

Sheet LV02.04.2026 cost_Origi
A1: 2026 Cost projection_LV:26/3/2026 | E1: Monthly
E2: LV:26/3/2026 | F2: LV:26/3/2026 | G2: LV:26/3/2026 | H2: LV:26/3/2026 | I2: LV:26/3/2026 | J2: LV:26/3/2026 | K2: LV:26/3/2026 | L2: LV:26/3/2026 | M2: LV:26/3/2026
A3: SK plant | B3: Jan | C3: Feb | D3: Mar | E3: Apr | F3: May | G3: Jun | H3: Jul | I3: Aug | J3: Sep | K3: Oct | L3: Nov | M3: Dec | N3: Total/Avg.
A5: Day operation | B5: 27 | C5: 28 | D5: 31 | E5: 24 | F5: 31 | G5: 30 | H5: 30 | I5: 31 | J5: 31 | K5: 31 | L5: 30 | M5: 26 | N5: =SUM(B5:M5) -> 350 | P5: Plan
A6: Grinding/day without waxy | B6: =B7/B5 -> 1088.8185 | C6: 1087.38 | D6: =D7/D5 -> 1082.5681 | E6: 1450 | F6: 1450 | G6: 1400 | H6: 1400 | I6: 1400 | J6: 1300 | K6: 1200 | L6: 1200 | M6: 1200 | N6: =N7/N5 -> 1186.2355 | P6: Apr-Dec
A7: Grinding/month , tons | B7: 29398.1 | C7: 30446.73 | D7: 33559.61 | E7: 26978 | F7: 39250 | G7: 39800 | H7: 41800 | I7: 41700 | J7: 37200 | K7: 34300 | L7: 33150 | M7: 27600 | N7: =SUM(B7:M7) -> 415182.44 | P7: From Planner
A9: Roots purchased/month , tons | B9: 29954.31 | C9: 30325.58 | D9: 33527.15 | E9: ='SK MAP - Apr 2026 _ 26.03.2026'!E6 -> 29500 | F9: ='SK MAP - May 2026 _ 26.03.2026'!E6 -> 39250 | G9: ='SK MAP -June 2026 _ 26.03.2026'!E6 -> 41050 | H9: ='SK MAP -July 2026 _ 26.03.26'!E6 -> 41800 | I9: ='SK MAP -Aug 2026 _ 26.03.26'!E6 -> 41700 | J9: ='SK MAP -Sep 2026 _ 26.03.26 '!E6 -> 37200 | K9: ='SK MAP -Oct 2026 _ 26.03.26'!E6 -> 34300 | L9: ='SK MAP -Nov 2026 _ 26.03.26'!E6 -> 33150 | M9: ='SK MAP -Dec 2026 _ 26.03.26 '!E6 -> 27600 | N9: =SUM(B9:M9) -> 419357.04
A10: Starch content , % | B10: 27.073368 | C10: 26.63 | D10: 24.644387 | E10: ='SK MAP - Apr 2026 _ 26.03.2026'!E7*100 -> 21.969492 | F10: ='SK MAP - May 2026 _ 26.03.2026'!E7*100 -> 20.970382 | G10: ='SK MAP -June 2026 _ 26.03.2026'!G13 -> 21 | H10: ='SK MAP -July 2026 _ 26.03.26'!E7*100 -> 22 | I10: ='SK MAP -Aug 2026 _ 26.03.26'!E7*100 -> 22.504484 | J10: ='SK MAP -Sep 2026 _ 26.03.26 '!E7*100 -> 22.801935 | K10: ='SK MAP -Oct 2026 _ 26.03.26'!E7*100 -> 22.995773 | L10: ='SK MAP -Nov 2026 _ 26.03.26'!E7*100 -> 24 | M10: ='SK MAP -Dec 2026 _ 26.03.26 '!E7*100 -> 25 | N10: =N14/(N9*1000)*100 -> 23.270203
A11: Price , THB/kg. | B11: 2.8182197 | C11: 2.92 | D11: 2.9583502 | E11: ='SK MAP - Apr 2026 _ 26.03.2026'!E8 -> 3.0755932 | F11: ='SK MAP - May 2026 _ 26.03.2026'!E8 -> 3.1263057 | G11: ='SK MAP -June 2026 _ 26.03.2026'!H13 -> 3.0808161 | H11: ='SK MAP -July 2026 _ 26.03.26'!E8 -> 3.1277512 | I11: ='SK MAP -Aug 2026 _ 26.03.26'!E8 -> 3.1165468 | J11: ='SK MAP -Sep 2026 _ 26.03.26 '!E8 -> 3.0435484 | K11: ='SK MAP -Oct 2026 _ 26.03.26'!E8 -> 2.955102 | L11: ='SK MAP -Nov 2026 _ 26.03.26'!E8 -> 3.0776018 | M11: ='SK MAP -Dec 2026 _ 26.03.26 '!E8 -> 3.1746377 | N11: =N15/(N9*1000) -> 3.0454125 | R11: Actual 2025
A12: PPDS , THB/kg. | B12: =B11/B10*100 -> 10.409564 | C12: 10.98 | D12: 12.004154 | E12: ='SK MAP - Apr 2026 _ 26.03.2026'!E9 -> 13.999383 | F12: ='SK MAP - May 2026 _ 26.03.2026'!E9 -> 14.908196 | G12: ='SK MAP -June 2026 _ 26.03.2026'!I13 -> 14.670553 | H12: ='SK MAP -July 2026 _ 26.03.26'!E9 -> 14.217051 | I12: ='SK MAP -Aug 2026 _ 26.03.26'!E9 -> 13.848559 | J12: ='SK MAP -Sep 2026 _ 26.03.26 '!E9 -> 13.347763 | K12: ='SK MAP -Oct 2026 _ 26.03.26'!E9 -> 12.850632 | L12: ='SK MAP -Nov 2026 _ 26.03.26'!E9 -> 12.823341 | M12: ='SK MAP -Dec 2026 _ 26.03.26 '!E9 -> 12.698551 | N12: =N11/N10*100 -> 13.087176 | P12: =#REF! -> #REF! | R12: =#REF! -> #REF!
A14: Weight starch , kg | B14: =((B9*1000)*B10)/100 -> 8109640.5 | C14: 8074417.2 | D14: =((D9*1000)*D10)/100 -> 8262560.5 | E14: =((E9*1000)*E10)/100 -> 6481000 | F14: =((F9*1000)*F10)/100 -> 8230875 | G14: =((G9*1000)*G10)/100 -> 8620500 | H14: =((H9*1000)*H10)/100 -> 9196000 | I14: =((I9*1000)*I10)/100 -> 9384370 | J14: =((J9*1000)*J10)/100 -> 8482320 | K14: =((K9*1000)*K10)/100 -> 7887550 | ... M14: =((M9*1000)*M10)/100 -> 6900000 | N14: =SUM(B14:M14) -> 97585233
A15: Amount , THB | B15: =(B9*1000)*B11 -> 84417826 | C15: 88684792 | D15: =(D9*1000)*D11 -> 99185052 | E15: =(E9*1000)*E11 -> 90730000 | F15: =(F9*1000)*F11 -> 122707500 | G15: =(G9*1000)*G11 -> 126467500 | H15: =(H9*1000)*H11 -> 1.3074e+08 | I15: =(I9*1000)*I11 -> 129960000 | J15: =(J9*1000)*J11 -> 113220000 | K15: =(K9*1000)*K11 -> 1.0136e+08 | ... M15: =(M9*1000)*M11 -> 87620000 | N15: =SUM(B15:M15) -> 1.2771152e+09
A17: Co-products prices , THB/kg
A18: Pulp (moisture 79%) | B18: 0.282 | C18: 0.282 | D18: 0.36561484 | E18: 0.254 | F18: 0.254 | G18: 0.254 | H18: 0.254 | I18: 0.254 | J18: 0.254 | K18: 0.254 | L18: 0.254 | M18: 0.254 | N18: =AVERAGE(B18:M18) -> 0.2679679
A19: Soil Skin | B19: 0.03 | C19: 0.03 | D19: 0.03 | E19: 0.03 | F19: 0.03 | G19: 0.03 | H19: 0.03 | I19: 0.03 | J19: 0.03 | K19: 0.03 | L19: 0.03 | M19: 0.03 | N19: =AVERAGE(B19:M19) -> 0.03
A20: Wash Skin | B20: 0.2 | C20: 0.2 | D20: 0.24733343 | E20: 0.2 | F20: 0.2 | G20: 0.2 | H20: 0.2 | I20: 0.2 | J20: 0.2 | K20: 0.2 | L20: 0.2 | M20: 0.2 | N20: =AVERAGE(B20:M20) -> 0.20394445
A21: Pulp moisture, actual | B21: 0.7875 | C21: 0.7869 | D21: 0.78003438
A23: 2026 Cost projection_LV:2/4/2026
E24: Monthly Rev.01 | F24: LV:2/4/2026 | G24: LV:2/4/2026 | H24: LV:2/4/2026 | I24: LV:2/4/2026 | J24: LV:2/4/2026 | K24: LV:2/4/2026 | L24: LV:2/4/2026 | M24: LV:2/4/2026
A25: KSN plant | B25: Jan | C25: Feb | D25: Mar | E25: Apr | F25: May | G25: Jun | H25: Jul | I25: Aug | J25: Sep | K25: Oct | L25: Nov | M25: Dec | N25: Total/Avg.
C26: Stop 1 day | D26: Stop 2 days
A27: Day operation | B27: 28 | C27: 27 | D27: 29 | E27: 24 | F27: 31 | G27: 30 | H27: 31 | I27: 31 | J27: 30 | K27: 31 | L27: 30 | M27: 26 | N27: =SUM(B27:M27) -> 348
A28: Grinding/day without waxy | B28: =B29/B27 -> 516.30804 | C28: 519.15 | D28: =D29/D27 -> 507.18548 | E28: 700 | F28: 700 | G28: 700 | H28: 700 | I28: 700 | J28: 700 | K28: 700 | L28: 700 | M28: 600 | N28: =N29/N27 -> 647.64921
A29: Grinding/month , tons | B29: 14456.625 | C29: 14016.92 | D29: 14708.379 | E29: =E28*E27 -> 16800 | F29: =F28*F27 -> 21700 | G29: =G28*G27 -> 21000 | H29: =H28*H27 -> 21700 | I29: =I28*I27 -> 21700 | J29: =J28*J27 -> 21000 | K29: =K28*K27 -> 21700 | L29: =L28*L27 -> 21000 | M29: =M28*M27 -> 15600 | N29: =SUM(B29:M29) -> 225381.92
A31: Roots purchased/month , tons | B31: 15610.621 | C31: 14627.14 | D31: 14093.328 | E31: ='KSN MAP - Apr 2026 (2)'!E6 -> 16800 | F31: 21700 | G31: 21000 | H31: 21700 | I31: 21700 | J31: 21000 | K31: 21700 | L31: 21000 | M31: 15600 | N31: =SUM(B31:M31) -> 226531.09
A32: Actual starch content | B32: 27.464032 | C32: 27.61 | D32: 25.43097 | E32: ='KSN MAP - Apr 2026 Rev1-2.04.26'!G13 -> 23 | F32: ='KSN MAP - May 2026_02.04.26'!G13 -> 21.551429 | G32: ='KSN MAP - Jun 2026_02.04.26'!G13 -> 21.496429 | H32: ='KSN MAP - Jul 2026_02.04.26'!G13 -> 21.995 | I32: ='KSN MAP - Aug 2026_02.04.26'!G13 -> 23.5 | J32: ='KSN MAP - Sep 2026 _02.04.26'!G13 -> 24.404286 | K32: ='KSN MAP - Oct 2026_02.04.26'!G13 -> 25.2 | L32: ='KSN MAP - Nov 2026 _02.04.26'!G13 -> 25.7 | M32: ='KSN MAP - Dec 2026 _02.04.26'!G13 -> 27.5 | N32: =N36/(N31*1000)*100 -> 24.330816
A33: Actual price | B33: 2.9210987 | C33: 2.95 | D33: 2.8933837 | E33: ='KSN MAP - Apr 2026 Rev1-2.04.26'!H13 -> 3.0985714 | F33: ='KSN MAP - May 2026_02.04.26'!H13 -> 3.005 | G33: ='KSN MAP - Jun 2026_02.04.26'!H13 -> 3.0014286 | H33: ='KSN MAP - Jul 2026_02.04.26'!H13 -> 2.9785714 | I33: ='KSN MAP - Aug 2026_02.04.26'!H13 -> 3.0085714 | J33: ='KSN MAP - Sep 2026 _02.04.26'!H13 -> 2.9985714 | K33: ='KSN MAP - Oct 2026_02.04.26'!H13 -> 3.0628571 | L33: ='KSN MAP - Nov 2026 _02.04.26'!H13 -> 3.1328571 | M33: ='KSN MAP - Dec 2026 _02.04.26'!H13 -> 3.2166667 | N33: =N37/(N31*1000) -> 3.0242394 | R33: =R11 -> Actual 2025
A34: PPDS | B34: 10.636088 | C34: 10.67 | D34: 11.377402 | E34: =E33/E32*100 -> 13.47205 | F34: =F33/F32*100 -> 13.943391 | G34: =G33/G32*100 -> 13.962452 | H34: =H33/H32*100 -> 13.542039 | I34: =I33/I32*100 -> 12.802432 | J34: =J33/J32*100 -> 12.287069 | K34: =K33/K32*100 -> 12.154195 | L34: =L33/L32*100 -> 12.190106 | ... N34: =N33/N32*100 -> 12.429667 | P34: =#REF! -> #REF! | R34: =#REF! -> #REF!
A36: Weight starch , kg | B36: =((B31*1000)*B32)/100 -> 4287306 | C36: 4037862 | D36: =((D31*1000)*D32)/100 -> 3584070 | E36: =((E31*1000)*E32)/100 -> 3864000 | F36: =((F31*1000)*F32)/100 -> 4676660 | G36: =((G31*1000)*G32)/100 -> 4514250 | H36: =((H31*1000)*H32)/100 -> 4772915 | I36: =((I31*1000)*I32)/100 -> 5099500 | J36: =((J31*1000)*J32)/100 -> 5124900 | K36: =((K31*1000)*K32)/100 -> 5468400 | ... M36: =((M31*1000)*M32)/100 -> 4290000 | N36: =SUM(B36:M36) -> 55116863
A37: Amount , THB | B37: =(B31*1000)*B33 -> 45600164 | C37: 43087170 | D37: =(D31*1000)*D33 -> 40777405 | E37: =(E31*1000)*E33 -> 52056000 | F37: =(F31*1000)*F33 -> 65208500 | G37: =(G31*1000)*G33 -> 63030000 | H37: =(H31*1000)*H33 -> 64635000 | I37: =(I31*1000)*I33 -> 65286000 | J37: =(J31*1000)*J33 -> 62970000 | K37: =(K31*1000)*K33 -> 66464000 | ... M37: =(M31*1000)*M33 -> 50180000 | N37: =SUM(B37:M37) -> 6.8508424e+08
A39: Co-products prices, THB/kg
A40: Pulp | B40: 0.134 | C40: 0.134 | D40: 0.134 | E40: 0.134 | F40: 0.134 | G40: 0.134 | H40: 0.134 | I40: 0.134 | J40: 0.134 | K40: 0.134 | L40: 0.134 | M40: 0.134 | N40: =AVERAGE(B40:M40) -> 0.134
A41: Soil Skin | B41: 0.03 | C41: 0.03 | D41: 0.03 | E41: 0.03 | F41: 0.03 | G41: 0.03 | H41: 0.03 | I41: 0.03 | J41: 0.03 | K41: 0.03 | L41: 0.03 | M41: 0.03 | N41: =AVERAGE(B41:M41) -> 0.03
A42: Wash Skin | B42: 0.12 | C42: 0.12 | D42: 0.12 | E42: 0.12 | F42: 0.12 | G42: 0.12 | H42: 0.12 | I42: 0.12 | J42: 0.12 | K42: 0.12 | L42: 0.12 | M42: 0.12 | N42: =AVERAGE(B42:M42) -> 0.12

Sheet SK ST+Price+PPDS+Farmer_Origi.
B2: SK plant
B4: Starch content in root (%)
B5: Month | C5: 2026 El Niño | D5: 2025 La Niña | E5: 2024 El Niño | F5: 2023 El Niño | G5: 2022 La Niña | H5: 2021 La Niña | I5: 2020 La Niña | J5: 2019 | K5: 2018 | L5: 2017 | M5: 2016 | N5: 2015
B6: Jan | C6: 27.073368 | D6: 27.465482 | E6: 26.552126 | F6: 28.283012 | G6: 28.075819 | H6: 28.283416 | I6: 26.452771 | J6: 27.600559 | K6: 28.75 | L6: 28.48 | M6: 27.988439 | N6: 28.53
B7: Feb | C7: ='LE02026 cost LV11022026_Origi'!C10 -> 27.256311 | D7: 27.142097 | E7: 27.098026 | F7: 28.246149 | G7: 27.665692 | H7: 28.343564 | I7: 26.436967 | J7: 27.6 | K7: 28.75 | L7: 28.99 | M7: 28.524987 | N7: 28.9513
B8: Mar | C8: ='LE02026 cost LV11022026_Origi'!D10 -> 25.742204 | D8: 25.506314 | E8: 25.153572 | F8: 27.27257 | G8: 26.223927 | H8: 26.636336 | I8: 24.42815 | J8: 25.985059 | K8: 26.75 | L8: 27.941922 | M8: 27.796808 | N8: 26.68091
B9: Apr | C9: =#REF! -> #REF! | D9: 22.363459 | E9: 21.636709 | F9: 24.331309 | G9: 24.772808 | H9: 24.116969 | I9: 21.491937 | J9: 22.72 | K9: 24.85 | L9: 25.393449 | M9: 25.197741 | N9: 25.48
B10: May | C10: =#REF! -> #REF! | D10: 19.449638 | E10: 18.241591 | F10: 20.530842 | G10: 23.098356 | H10: 22.594208 | I10: 20.447716 | J10: 20.44 | K10: 23.39 | L10: 23.453555 | M10: 22.082839 | N10: 24.298698
B11: Jun | C11: =#REF! -> #REF! | D11: 20.598081 | E11: 16.633931 | F11: 20.08 | G11: 23.058919 | H11: 22.643665 | I11: 20.831887 | J11: 21.06 | K11: 23.75 | L11: 24.251453 | M11: 20.984485 | N11: 22.924381
B12: Jul | C12: =#REF! -> #REF! | D12: 23.384067 | E12: 18.040337 | F12: 22.568159 | G12: 24.122682 | H12: 23.921738 | I12: 22.260539 | J12: 22.05 | K12: 24.95 | L12: 25.399363 | M12: 22.366981 | N12: 22.238087
B13: Aug | C13: =#REF! -> #REF! | D13: 24.238562 | E13: 21.33516 | F13: 24.498753 | G13: 24.589269 | H13: 24.39491 | I13: 23.375192 | J13: 22.9 | K13: 25.87 | L13: 25.874386 | M13: 25.135475 | N13: 23.603732
B14: Sep | C14: =#REF! -> #REF! | D14: 24.537915 | E14: 23.015575 | F14: 24.04 | G14: 25.249353 | H14: 24.676516 | I14: 23.848565 | J14: 23.22 | K14: 26.47 | L14: 25.921535 | M14: 25.698979 | N14: 23.984547
B15: Oct | C15: =#REF! -> #REF! | D15: 24.001491 | E15: 23.447747 | F15: 23.844147 | G15: 25.791357 | H15: 24.768643 | I15: 24.304353 | J15: 24.51 | K15: 26.07 | L15: 25.911833 | M15: 25.764254 | N15: 24.596381
B16: Nov | C16: =#REF! -> #REF! | D16: 24.842139 | E16: 24.281086 | F16: 24.370364 | G16: 27.209794 | H16: 25.410465 | I16: 25.208214 | J16: 25.28 | K16: 26.428 | L16: 26.88 | M16: 25.574764 | N16: 25.327068
B17: Dec | C17: =#REF! -> #REF! | D17: 25.807675 | E17: 25.663568 | F17: 25.544211 | G17: 27.303537 | H17: 27.091963 | I17: 27.464238 | J17: 25.97 | K17: 27.402526 | L17: 28.2 | M17: 27.132339 | N17: 26.911576
B18: YTD | C18: =#REF! -> #REF! | D18: 23.891104 | E18: 22.277682 | F18: 24.550107 | G18: 25.463697 | H18: 25.035661 | I18: 23.766044 | J18: 23.968278 | K18: 26.167983 | L18: 26.324424 | M18: 25.23 | N18: 25.08
D19: =C9-E19 -> #REF! | E19: =D9-D10 -> 2.9138212
E20: Apr-May : El Niño Jun-Aug : La Niña | F20: Drought | G20: Continue rain | H20: Flooding | I20: Co-vid19 | J20: Drought/CMD | K20: Crisis /Drought /CMD | L20: Senka - Flooding | M20: Drought
B21: Price (THB./Kg.)
B22: Month | C22: 2026 | D22: 2025 | E22: 2024 | F22: 2023 | G22: 2022 | H22: 2021 | I22: 2020 | J22: 2019 | K22: 2018 | L22: 2017 | M22: 2016 | N22: 2015
B23: Jan | C23: 2.8182197 | D23: 2.3206125 | E23: 3.8811187 | F23: 3.3707016 | G23: 2.8679964 | H23: 2.4321249 | I23: 2.4349758 | J23: 2.7330793 | K23: 2.6846275 | L23: 1.9640519 | M23: 2.3831074 | N23: 2.6862319
B24: Feb | C24: ='LE02026 cost LV11022026_Origi'!C11 -> 2.8494175 | D24: 2.2929551 | E24: 3.8121126 | F24: 3.5307178 | G24: 2.8003392 | H24: 2.5347841 | I24: 2.3773005 | J24: 2.6221188 | K24: 2.7929828 | L24: 1.9008149 | M24: 2.2986145 | N24: 2.5758909
B25: Mar | C25: ='LE02026 cost LV11022026_Origi'!D11 -> 2.9097713 | D25: 2.0350253 | E25: 3.52454 | F25: 3.8271873 | G25: 2.9025373 | H25: 2.4968198 | I25: 2.2580928 | J25: 2.6008877 | K25: 3.0816588 | L25: 1.8959876 | M25: 2.2863871 | N25: 2.412576
B26: Apr | C26: =#REF! -> #REF! | D26: 1.8683628 | E26: 3.1336716 | F26: 3.9203079 | G26: 3.0721751 | H26: 2.5831193 | I26: 2.0728862 | J26: 2.4824865 | K26: 3.4087085 | L26: 1.7969313 | M26: 2.3015141 | N26: 2.4720834
B27: May | C27: =#REF! -> #REF! | D27: 1.8105822 | E27: 2.8330475 | F27: 3.591888 | G27: 3.2212402 | H27: 2.4395852 | I27: 2.1191505 | J27: 2.2385166 | K27: 3.2121688 | L27: 1.7619482 | M27: 2.1283473 | N27: 2.4768338
B28: Jun | C28: =#REF! -> #REF! | D28: 1.9014496 | E28: 2.3804216 | F28: 3.1777245 | G28: 3.1931162 | H28: 2.4319136 | I28: 2.1076855 | J28: 2.1460582 | K28: 3.0607744 | L28: 1.7574709 | M28: 2.0202376 | N28: 2.5179536
B29: Jul | C29: =#REF! -> #REF! | D29: 2.3831165 | E29: 2.5238319 | F29: 3.4243199 | G29: 3.3706548 | H29: 2.5888143 | I29: 2.2176649 | J29: 2.302884 | K29: 3.0627285 | L29: 1.8329102 | M29: 1.9109423 | N29: 2.5808822
B30: Aug | C30: =#REF! -> #REF! | D30: 2.4913376 | E30: 2.7262263 | F30: 3.621204 | G30: 3.2971745 | H30: 2.6210172 | I30: 2.308271 | J30: 2.3741792 | K30: 3.0904943 | L30: 1.874876 | M30: 1.8615915 | N30: 2.5745389
B31: Sep | C31: =#REF! -> #REF! | D31: 2.4337319 | E31: 2.8448843 | F31: 3.5944677 | G31: 3.3406941 | H31: 2.7038312 | I31: 2.3222267 | J31: 2.3502101 | K31: 3.2067345 | L31: 2.0527029 | M31: 1.7232699 | N31: 2.5489264
B32: Oct | C32: =#REF! -> #REF! | D32: 2.3955283 | E32: 2.5731024 | F32: 3.543168 | G32: 3.2375012 | H32: 2.6903687 | I32: 2.325409 | J32: 2.3754588 | K32: 3.1382285 | L32: 2.2131489 | M32: 1.6437255 | N32: 2.4681459
B33: Nov | C33: =#REF! -> #REF! | D33: 2.5972745 | E33: 2.5105695 | F33: 3.8483627 | G33: 3.2710718 | H33: 2.8612413 | I33: 2.3976659 | J33: 2.4911511 | K33: 3.0520859 | L33: 2.4194326 | M33: 1.8990576 | N33: 2.5117689
B34: Dec | C34: =#REF! -> #REF! | D34: 2.6599125 | E34: 2.3272461 | F34: 3.8269274 | G34: 3.2197843 | H34: 2.8350489 | I34: 2.4806185 | J34: 2.4320356 | K34: 2.9205169 | L34: 2.5506959 | M34: 2.0687513 | N34: 2.440626
B35: YTD | C35: =#REF! -> #REF! | D35: 2.2460448 | E35: 2.8880699 | F35: 3.6135815 | G35: 3.1609713 | H35: 2.5957875 | I35: 2.280929 | J35: 2.4192097 | K35: 3.0572651 | L35: 1.9961105 | M35: 2.0306835 | N35: 2.5222972
B38: PPDS (THB./Kg.)
B39: Month | C39: 2026 | D39: 2025 | E39: 2024 | F39: 2023 | G39: 2022 | H39: 2021 | I39: 2020 | J39: 2019 | K39: 2018 | L39: 2017 | M39: 2016 | N39: 2015
B40: Jan | C40: 10.41 | D40: 8.4491964 | E40: 14.616979 | F40: 11.91776 | G40: 10.215184 | H40: 8.5991199 | I40: 9.187 | J40: 9.9022604 | K40: 9.3393593 | L40: 6.8955851 | M40: 8.5146134 | N40: 9.413831
B41: Feb | C41: ='LE02026 cost LV11022026_Origi'!C12 -> 10.454157 | D41: 8.4479659 | E41: 14.067861 | F41: 12.49982 | G41: 10.122065 | H41: 8.9430675 | I41: 8.9923347 | J41: 9.5019659 | K41: 9.716073 | L41: 6.5577669 | M41: 8.058249 | N41: 8.897324
B42: Mar | C42: ='LE02026 cost LV11022026_Origi'!D12 -> 11.303505 | D42: 7.9785161 | E42: 14.012085 | F42: 14.033101 | G42: 11.068279 | H42: 9.3737357 | I42: 9.2438142 | J42: 10.009166 | K42: 11.519522 | L42: 6.7854588 | M42: 8.2253586 | N42: 9.04233
B43: Apr | C43: =#REF! -> #REF! | D43: 8.354534 | E43: 14.483125 | F43: 16.112195 | G43: 12.4014 | H43: 10.710796 | I43: 9.6449485 | J43: 10.926437 | K43: 13.714599 | L43: 7.076358 | M43: 9.1338112 | N43: 9.7023998
B44: May | C44: =#REF! -> #REF! | D44: 9.3090793 | E44: 15.530704 | F44: 17.495084 | G44: 13.945756 | H44: 10.797392 | I44: 10.363752 | J44: 10.953312 | K44: 13.735717 | L44: 7.5124997 | M44: 9.6380148 | N44: 10.193278
B45: Jun | C45: =#REF! -> #REF! | D45: 9.2311978 | E45: 14.310638 | F45: 15.825321 | G45: 13.84764 | H45: 10.739929 | I45: 10.117592 | J45: 10.19021 | K45: 12.886078 | L45: 7.2468682 | M45: 9.6272916 | N45: 10.983736
B46: Jul | C46: =#REF! -> #REF! | D46: 10.191198 | E46: 13.989938 | F46: 15.173235 | G46: 13.972969 | H46: 10.822016 | I46: 9.9623145 | J46: 10.44451 | K46: 12.275767 | L46: 7.2163631 | M46: 8.5435862 | N46: 11.605684
B47: Aug | C47: =#REF! -> #REF! | D47: 10.278405 | E47: 12.778091 | F47: 14.781177 | G47: 13.408998 | H47: 10.744115 | I47: 9.8748752 | J47: 10.366079 | K47: 11.948069 | L47: 7.2460694 | M47: 7.4062318 | N47: 10.907338
B48: Sep | C48: =#REF! -> #REF! | D48: 9.9182504 | E48: 12.360692 | F48: 14.952029 | G48: 13.230811 | H48: 10.957103 | I48: 9.7373851 | J48: 10.121432 | K48: 12.116474 | L48: 7.9189095 | M48: 6.7055965 | N48: 10.627369
B49: Oct | C49: =#REF! -> #REF! | D49: 9.9807478 | E49: 10.973772 | F49: 14.859697 | G49: 12.552659 | H49: 10.861995 | I49: 9.5678703 | J49: 9.6929291 | K49: 12.039456 | L49: 8.541074 | M49: 6.3798681 | N49: 10.03459
B50: Nov | C50: =#REF! -> #REF! | D50: 10.455116 | E50: 10.339609 | F50: 15.791158 | G50: 12.021671 | H50: 11.26009 | I50: 9.5114471 | J50: 9.85 | K50: 11.548683 | L50: 9.0002824 | M50: 7.4255137 | N50: 9.9173298
B51: Dec | C51: =#REF! -> #REF! | D51: 10.306672 | E51: 9.0682873 | F51: 14.981584 | G51: 11.792554 | H51: 10.464538 | I51: 9.0321766 | J51: 9.36 | K51: 10.657838 | L51: 9.044419 | M51: 7.6246697 | N51: 9.0690562
B52: YTD | C52: =#REF! -> #REF! | D52: 9.4011763 | E52: 12.963961 | F52: 14.719209 | G52: 12.413638 | H52: 10.36836 | I52: 9.5974283 | J52: 10.093381 | K52: 11.683228 | L52: 7.58 | M52: 8.05 | N52: 10.055094
B55: Farmer ratio of regular root at SK plant, %
B56: Month | C56: 2026 | D56: 2025 | E56: 2024 | F56: 2023 | G56: 2022 | H56: 2021 | I56: 2020 | J56: 2019 | K56: 2018 | L56: 2017 | M56: 2016 | N56: 2015
B57: Jan | C57: 16.822053 | D57: 46.744451 | E57: 47.328135 | F57: 49.313039 | G57: 55.328108 | H57: 53.856642 | I57: 51.082904 | J57: 46.366718 | K57: 57.38296 | L57: 67.816417 | M57: 76.396046 | N57: 95.089747
B58: Feb | C58: 17.011249 | D58: 43.641985 | E58: 46.875754 | F58: 45.158938 | G58: 53.335285 | H58: 40.956232 | I58: 49.407957 | J58: 36.77052 | K58: 50.488072 | L58: 69.661983 | M58: 75.840108 | N58: 76.508449
B59: Mar | D59: 43.948484 | E59: 50.174103 | F59: 32.552341 | G59: 36.825521 | H59: 48.238213 | I59: 43.546182 | J59: 29.653185 | K59: 26.785755 | L59: 46.375782 | M59: 70.563534 | N59: 85.958965
A60: Low sesonal of SK plant | B60: Apr | D60: 48.813182 | E60: 46.894103 | F60: 23.768885 | G60: 48.778404 | H60: 35.155245 | I60: 38.391769 | J60: 31.669496 | K60: 11.006388 | L60: 43.391665 | M60: 63.589943 | N60: 50.515012
B61: May | D61: 29.817966 | E61: 18.336852 | F61: 14.853418 | G61: 24.402908 | H61: 27.418823 | I61: 12.597807 | J61: 11.838503 | K61: 4.3930509 | L61: 14.91966 | M61: 27.324054 | N61: 28.28983
B62: Jun | D62: 39.88099 | E62: 23.521755 | F62: 45.63439 | G62: 44.072685 | H62: 33.174332 | I62: 18.039192 | J62: 7.4314477 | K62: 25.576839 | L62: 21.952311 | M62: 12.778572 | N62: 24.452272
B63: Jul | D63: 8.6936122 | E63: 25.953046 | F63: 29.851017 | G63: 14.311193 | H63: 12.299146 | I63: 18.530378 | J63: 7.2234477 | K63: 16.992185 | L63: 16.896658 | M63: 18.979723 | N63: 9.6649777
B64: Aug | D64: 2.9182525 | E64: 17.461098 | F64: 15.503981 | G64: 16.864038 | H64: 13.325462 | I64: 17.351241 | J64: 6.9412066 | K64: 9.8333698 | L64: 7.2065018 | M64: 13.590361 | N64: 3.8744705
B65: Sep | D65: 11.488072 | E65: 28.847277 | F65: 36.689826 | G65: 27.468099 | H65: 20.798471 | I65: 25.467666 | J65: 21.62962 | K65: 18.156093 | L65: 11.514729 | M65: 15.666816 | N65: 13.64245
B66: Oct | D66: 27.485729 | E66: 37.774696 | F66: 41.86864 | G66: 41.195546 | H66: 39.138149 | I66: 37.247378 | J66: 39.563258 | K66: 37.631226 | L66: 21.004282 | M66: 15.584259 | N66: 32.136982
B67: Nov | D67: 10.474762 | E67: 41.426022 | F67: 39.620466 | G67: 39.718051 | H67: 43.949186 | I67: 46.341419 | J67: 34.538145 | K67: 26.252632 | L67: 41.458726 | M67: 31.638793 | N67: 33.423935
B68: Dec | D68: 19.529223 | E68: 38.963149 | F68: 44.826667 | G68: 46.229808 | H68: 48.982344 | I68: 47.04375 | J68: 48.232387 | K68: 27.722387 | L68: 50.734915 | M68: 47.538284 | N68: 42.318982
B69: YTD | C69: ='[61]Regular+Waxy Farmer'!N94 -> 12.170484 | D69: 28.197528 | E69: 34.004902 | F69: 35.14574 | G69: 36.276747 | H69: 33.911514 | I69: 32.857325 | J69: 25.835374 | K69: 26.262126 | L69: 33.494095 | M69: 37.322971 | N69: 37.848035
B72: Farmer ratio of regular+waxy root at SK plant, %
B73: Month | C73: 2026 | D73: 2025 | E73: 2024 | F73: 2023 | G73: 2022 | H73: 2021 | I73: 2020 | J73: 2019
B74: Jan | C74: 36.291536 | D74: 55.007548 | E74: 51.707237 | F74: 55.040969 | G74: 61.66006 | H74: 60.452988 | I74: 55.860088 | J74: 50.553201
B75: Feb | C75: 38.666833 | D75: 49.083117 | E75: 52.815593 | F75: 53.944779 | G75: 58.445229 | H75: 49.022493 | I75: 53.047407 | J75: 41.239131
B76: Mar | D76: 47.92089 | E76: 54.448063 | F76: 37.930284 | G76: 46.038707 | H76: 51.469751 | I76: 45.715417 | J76: 32.530908
A77: Low sesonal of SK plant | B77: Apr | D77: 48.813182 | E77: 49.567845 | F77: 27.130181 | G77: 51.754688 | H77: 35.155245 | I77: 38.391769 | J77: 31.669496
B78: May | D78: 30.65349 | E78: 18.336852 | F78: 15.835483 | G78: 26.012109 | H78: 28.562153 | I78: 12.597807 | J78: 11.838503
B79: Jun | D79: 39.88099 | E79: 24.106135 | F79: 46.575184 | G79: 45.969551 | H79: 33.174332 | I79: 18.039192 | J79: 9.6947561
B80: Jul | D80: 10.339389 | E80: 26.44529 | F80: 29.851017 | G80: 15.357145 | H80: 13.825758 | I80: 21.421449 | J80: 8.5299666
B81: Aug | D81: 4.3878101 | E81: 17.461098 | F81: 15.503981 | G81: 18.118256 | H81: 14.954403 | I81: 17.351241 | J81: 8.2175355
B82: Sep | D82: 13.880771 | E82: 29.651793 | F82: 38.128047 | G82: 29.015232 | H82: 21.53558 | I82: 26.903914 | J82: 21.62962
B83: Oct | D83: 32.434841 | E83: 38.928141 | F83: 42.59052 | G83: 44.353942 | H83: 39.793352 | I83: 38.307969 | J83: 41.070466
B84: Nov | D84: 28.998602 | E84: 47.349226 | F84: 42.129106 | G84: 43.135857 | H84: 47.313301 | I84: 48.089978 | J84: 34.538145
B85: Dec | D85: 29.587852 | E85: 45.047443 | F85: 46.376892 | G85: 53.45105 | H85: 54.033034 | I85: 50.138287 | J85: 48.232387
B86: YTD | C86: ='[61]Regular+Waxy Farmer'!N153 -> 29.499934 | D86: 32.358473 | E86: 37.006712 | F86: 38.17754 | G86: 40.402705 | H86: 36.952988 | I86: 34.832257 | J86: 27.481225

Sheet KSN ST+Price+PPDS+Farmer_Origi
B2: KSN plant
B4: Starch content in root (%)
B5: Month | C5: 2026 El Niño | D5: 2025 La Niña | E5: 2024 El Niño | F5: 2023 El Niño | G5: 2022 La Niña | H5: 2021 La Niña | I5: 2020 La Niña | J5: 2019 | K5: 2018 | L5: 2017 | M5: 2016 | N5: 2015
B6: Jan | C6: 27.464032 | D6: 27.998711 | E6: 27.831058 | F6: 28.890165 | G6: 29.79685 | H6: 29.951744 | I6: 27.983759 | J6: 28.3263 | K6: 29.360267 | L6: 28.66 | M6: 28.58 | N6: 29.96
B7: Feb | C7: ='LE02026 cost LV11022026_Origi'!C31 -> 27.333333 | D7: 28.332372 | E7: 27.763914 | F7: 28.97 | G7: 28.897075 | H7: 29.888329 | I7: 28.328713 | J7: 27.99 | K7: 29.135215 | L7: 29 | M7: 29.1 | N7: 29.91
B8: Mar | C8: ='LE02026 cost LV11022026_Origi'!D31 -> 26.184615 | D8: 26.571255 | E8: 25.857648 | F8: 27.471619 | G8: 27.259585 | H8: 27.528401 | I8: 26.064775 | J8: 26.122664 | K8: 27.29331 | L8: 27.49 | M8: 28.3 | N8: 27.351603
B9: Apr | C9: =#REF! -> #REF! | D9: 23.546041 | E9: 23.014333 | F9: 23.549197 | G9: 25.455601 | H9: 24.752392 | I9: 22.982705 | J9: 23.57 | K9: 25.585359 | L9: 25.4 | M9: 25.24 | N9: 25.819486
B10: May | C10: =#REF! -> #REF! | D10: 20.654164 | E10: 18.614028 | F10: 20.110915 | G10: 22.712972 | H10: 21.841452 | I10: 21.197042 | J10: 20.38 | K10: 24.154912 | L10: 23.99 | M10: 21.2 | N10: 23.81
B11: Jun | C11: =#REF! -> #REF! | D11: 20.603923 | E11: 17.547046 | F11: 18.828485 | G11: 23.336883 | H11: 21.901615 | I11: 19.767931 | J11: 21.13 | K11: 24.529697 | L11: 24.8 | M11: 20.1 | N11: 23.136897
B12: Jul | C12: =#REF! -> #REF! | D12: 22.594806 | E12: 20.086249 | F12: 22.09855 | G12: 23.962162 | H12: 24.132313 | I12: 21.613157 | J12: 23.39 | K12: 24.902171 | L12: 25.36 | M12: 22.84 | N12: 23.048973
B13: Aug | C13: =#REF! -> #REF! | D13: 24.402037 | E13: 22.971605 | F13: 23.521527 | G13: 24.758563 | H13: 25.202569 | I13: 23.497326 | J13: 24.4 | K13: 25.398905 | L13: 25.32 | M13: 25.21 | N13: 24.14
B14: Sep | C14: =#REF! -> #REF! | D14: 24.325976 | E14: 24.393695 | F14: 23.500475 | G14: 25.502384 | H14: 24.637115 | I14: 24.475376 | J14: 24.18 | K14: 26.36366 | L14: 26 | M14: 26.02 | N14: 25.32228
B15: Oct | C15: =#REF! -> #REF! | D15: 24.318543 | E15: 24.929827 | F15: 22.977083 | G15: 25.838381 | H15: 25.089759 | I15: 24.952312 | J15: 25.16 | K15: 26.606374 | L15: 25.81 | M15: 26.95 | N15: 25.61
B16: Nov | C16: =#REF! -> #REF! | D16: 25.291087 | E16: 24.474989 | F16: 24.13544 | G16: 27.695088 | H16: 26.639214 | I16: 26.123322 | J16: 26.13 | K16: 27.142752 | L16: 27.15 | M16: 27.48 | N16: 26.57
B17: Dec | C17: =#REF! -> #REF! | D17: 26.88498 | E17: 26.427034 | F17: 26.922452 | G17: 28.171766 | H17: 28.718051 | I17: 28.293256 | J17: 27.34 | K17: 27.941427 | L17: 28.85 | M17: 28.39 | N17: 28.07
B18: YTD | C18: =#REF! -> #REF! | D18: 24.261657 | E18: 23.134132 | F18: 24.01466 | G18: 25.909621 | H18: 25.501995 | I18: 24.233087 | J18: 24.603335 | K18: 26.408333 | L18: 26.389148 | M18: 25.44 | N18: 25.82
E20: Apr-May : El Niño Jun-Aug : La Niña | F20: Drought | G20: Continue rain | H20: Flooding | I20: Co-vid19 | J20: Drought/CMD | K20: Crisis /Drought /CMD | L20: Senka - Flooding | M20: Drought
B21: Price (THB./Kg.)
B22: Month | C22: 2026 | D22: 2025 | E22: 2024 | F22: 2023 | G22: 2022 | H22: 2021 | I22: 2020 | J22: 2019 | K22: 2018 | L22: 2017 | M22: 2016 | N22: 2015
B23: Jan | C23: 2.9210987 | D23: 2.5153376 | E23: 3.9841768 | F23: 3.2305394 | G23: 2.8289854 | H23: 2.3969436 | I23: 2.512711 | J23: 2.7280059 | K23: 2.696913 | L23: 1.7575173 | M23: 2.3450617 | N23: 2.6225755
B24: Feb | C24: ='LE02026 cost LV11022026_Origi'!C32 -> 2.9346667 | D24: 2.4836266 | E24: 3.9021217 | F24: 3.3178 | G24: 2.7485421 | H24: 2.3849143 | I24: 2.4262581 | J24: 2.6591785 | K24: 2.7929384 | L24: 1.7066414 | M24: 2.2563447 | N24: 2.4865813
B25: Mar | C25: ='LE02026 cost LV11022026_Origi'!D32 -> 2.8946154 | D25: 2.0868943 | E25: 3.7081954 | F25: 3.7138849 | G25: 2.7082811 | H25: 2.329964 | I25: 2.2763665 | J25: 2.5430463 | K25: 2.9580896 | L25: 1.616567 | M25: 2.2148608 | N25: 2.3369921
B26: Apr | C26: =#REF! -> #REF! | D26: 1.9090338 | E26: 3.1475714 | F26: 3.7531813 | G26: 2.9025793 | H26: 2.4755762 | I26: 2.0372725 | J26: 2.4857329 | K26: 3.2826207 | L26: 1.4814408 | M26: 2.1353644 | N26: 2.4051347
B27: May | C27: =#REF! -> #REF! | D27: 1.7086305 | E27: 2.5878252 | F27: 3.1862869 | G27: 2.831493 | H27: 2.2663244 | I27: 2.0589458 | J27: 2.0472088 | K27: 3.0082832 | L27: 1.4697588 | M27: 1.8874036 | N27: 2.2677044
B28: Jun | C28: =#REF! -> #REF! | D28: 1.7616423 | E28: 2.1395366 | F28: 2.7686582 | G28: 2.8998355 | H28: 2.099712 | I28: 1.9367071 | J28: 1.9603276 | K28: 2.7831103 | L28: 1.4530547 | M28: 1.7727738 | N28: 2.3333356
B29: Jul | C29: =#REF! -> #REF! | D29: 1.9924686 | E29: 2.2800426 | F29: 2.9913696 | G29: 2.9728337 | H29: 2.2225414 | I29: 2.0233899 | J29: 2.0328453 | K29: 2.7763127 | L29: 1.5712545 | M29: 1.7685839 | N29: 2.3649371
B30: Aug | C30: =#REF! -> #REF! | D30: 2.10573 | E30: 2.2553393 | F30: 2.9003964 | G30: 2.9757138 | H30: 2.2592082 | I30: 2.0236813 | J30: 2.0770868 | K30: 2.6944052 | L30: 1.5526732 | M30: 1.6862067 | N30: 2.2677514
B31: Sep | C31: =#REF! -> #REF! | D31: 2.1321625 | E31: 2.4102102 | F31: 3.069449 | G31: 3.060559 | H31: 2.4908174 | I31: 1.9738633 | J31: 1.9726167 | K31: 2.9078292 | L31: 1.8559301 | M31: 1.5321458 | N31: 2.2959791
B32: Oct | C32: =#REF! -> #REF! | D32: 2.271931 | E32: 2.3921655 | F32: 3.2552228 | G32: 3.0786552 | H32: 2.565396 | I32: 2.132983 | J32: 2.2519283 | K32: 3.0302824 | L32: 2.0837522 | M32: 1.3423228 | N32: 2.3608616
B33: Nov | C33: =#REF! -> #REF! | D33: 2.6044364 | E33: 2.7203163 | F33: 3.8225022 | G33: 3.2549139 | H33: 2.8182062 | I33: 2.3789096 | J33: 2.5578976 | K33: 3.1416663 | L33: 2.4760928 | M33: 1.7800996 | N33: 2.5234369
B34: Dec | C34: =#REF! -> #REF! | D34: 2.271931 | E34: 2.5166382 | F34: 3.9160598 | G34: 3.160716 | H34: 2.7679215 | I34: 2.4757573 | J34: 2.5024061 | K34: 2.8384839 | L34: 2.6095655 | M34: 1.7629543 | N34: 2.4857577
B35: YTD | C35: =#REF! -> #REF! | D35: 2.1560263 | E35: 2.7456244 | F35: 3.3078485 | G35: 2.9542224 | H35: 2.4156792 | I35: 2.1673515 | J35: 2.2988835 | K35: 2.9087505 | L35: 1.8047401 | M35: 1.8609758 | N35: 2.3840134
B38: PPDS (THB./Kg.)
B39: Month | C39: 2026 | D39: 2025 | E39: 2024 | F39: 2023 | G39: 2022 | H39: 2021 | I39: 2020 | J39: 2019 | K39: 2018 | L39: 2017 | M39: 2016 | N39: 2015
B40: Jan | C40: 10.636088 | D40: 8.9837623 | E40: 14.315578 | F40: 11.182142 | G40: 9.4942433 | H40: 8.0026845 | I40: 8.97 | J40: 9.630647 | K40: 9.1855873 | L40: 6.1318817 | M40: 8.2055733 | N40: 8.7545334
B41: Feb | C41: ='LE02026 cost LV11022026_Origi'!C33 -> 10.736585 | D41: 8.7660383 | E41: 14.054653 | F41: 11.452537 | G41: 9.5114891 | H41: 7.9794168 | I41: 8.5646605 | J41: 9.5009204 | K41: 9.5861258 | L41: 5.8854481 | M41: 7.7531671 | N41: 8.3136127
B42: Mar | C42: ='LE02026 cost LV11022026_Origi'!D33 -> 11.054642 | D42: 7.8539546 | E42: 14.340807 | F42: 13.518988 | G42: 9.9351516 | H42: 8.4638552 | I42: 8.7334975 | J42: 9.7350193 | K42: 10.838149 | L42: 5.8794964 | M42: 7.8255764 | N42: 8.5442599
B43: Apr | C43: =#REF! -> #REF! | D43: 8.1076634 | E43: 13.67657 | F43: 15.937619 | G43: 11.402517 | H43: 10.001362 | I43: 8.8643722 | J43: 10.547872 | K43: 12.830075 | L43: 5.8329211 | M43: 8.4601465 | N43: 9.3151919
B44: May | C44: =#REF! -> #REF! | D44: 8.2725715 | E44: 13.902553 | F44: 15.84357 | G44: 12.466413 | H44: 10.376254 | I44: 9.7133636 | J44: 10.045914 | K44: 12.454126 | L44: 6.125333 | M44: 8.9015293 | N44: 9.5257509
B45: Jun | C45: =#REF! -> #REF! | D45: 8.5500334 | E45: 12.193144 | F45: 14.704626 | G45: 12.425976 | H45: 9.587019 | I45: 9.7972168 | J45: 9.2765628 | K45: 11.345881 | L45: 5.8586964 | M45: 8.8202944 | N45: 10.084911
B46: Jul | C46: =#REF! -> #REF! | D46: 8.8182593 | E46: 11.351262 | F46: 13.536497 | G46: 12.406366 | H46: 9.2098151 | I46: 9.3618435 | J46: 8.6915985 | K46: 11.148878 | L46: 6.194575 | M46: 7.7443349 | N46: 10.260488
B47: Aug | C47: =#REF! -> #REF! | D47: 8.6293209 | E47: 9.817944 | F47: 12.330817 | G47: 12.018928 | H47: 8.9641981 | I47: 8.6123899 | J47: 8.5110949 | K47: 10.608352 | L47: 6.1349235 | M47: 6.6886556 | N47: 9.3958888
B48: Sep | C48: =#REF! -> #REF! | D48: 8.7649617 | E48: 9.8804641 | F48: 13.061221 | G48: 12.00107 | H48: 10.110021 | I48: 8.0646905 | J48: 8.156436 | K48: 11.029687 | L48: 7.1391586 | M48: 5.8852706 | N48: 9.0670316
B49: Oct | C49: =#REF! -> #REF! | D49: 9.3423812 | E49: 9.595596 | F49: 14.167259 | G49: 11.915047 | H49: 10.224873 | I49: 8.5482381 | J49: 8.9517903 | K49: 11.38931 | L49: 8.0728121 | M49: 4.9800614 | N49: 9.2185146
B50: Nov | C50: =#REF! -> #REF! | D50: 10.297843 | E50: 11.114678 | F50: 15.837715 | G50: 11.752676 | H50: 10.579165 | I50: 9.106459 | J50: 9.8 | K50: 11.574605 | L50: 9.1211029 | M50: 6.4783216 | N50: 9.4990662
B51: Dec | C51: =#REF! -> #REF! | D51: 10.103045 | E51: 9.5229686 | F51: 14.545703 | G51: 11.219445 | H51: 9.6382637 | I51: 8.7503442 | J51: 9.15 | K51: 10.158694 | L51: 9.0443853 | M51: 6.2102758 | N51: 8.8545296
B52: YTD | C52: =#REF! -> #REF! | D52: 8.8865582 | E52: 11.868284 | F52: 13.774288 | G52: 11.402029 | H52: 9.4725108 | I52: 8.94377 | J52: 9.3437882 | K52: 11.01528 | L52: 6.8389481 | M52: 7.3165554 | N52: 9.2336583
B55: Farmer contribution of regular root at SK plant, %
B56: Month | C56: 2026 | D56: 2025 | E56: 2024 | F56: 2023 | G56: 2022 | H56: 2021 | I56: 2020 | J56: 2019 | K56: 2018 | L56: 2017 | M56: 2016 | N56: 2015
B57: Jan | C57: 10.566146 | D57: 26.020579 | E57: 69.339878 | F57: 68.136574 | G57: 84.778691 | H57: 78.688163 | I57: 27.892768 | J57: 17.740651 | K57: 38.689062 | L57: 56.212159 | M57: 51.775788 | N57: 30.616133
B58: Feb | C58: 18.866584 | D58: 55.853785 | E58: 76.470507 | F58: 77.6185 | G58: 76.37863 | H58: 88.42015 | I58: 44.647872 | J58: 13.512094 | K58: 30.841158 | L58: 55.636166 | M58: 69.529069 | N58: 43.364086
B59: Mar | D59: 77.309779 | E59: 90.977269 | F59: 42.815167 | G59: 66.5585 | H59: 68.837247 | I59: 49.852754 | J59: 20.37505 | K59: 25.044026 | L59: 54.191796 | M59: 64.139023 | N59: 43.314017
B60: Apr | D60: 50.708786 | E60: 79.435154 | F60: 28.970003 | G60: 46.698452 | H60: 54.076806 | I60: 36.568304 | J60: 38.078154 | K60: 28.504595 | L60: 64.272442 | M60: 67.972329 | N60: 30.604728
B61: May | D61: 41.506825 | E61: 60.068662 | F61: 55.569329 | G61: 54.294376 | H61: 43.386557 | I61: 20.911684 | J61: 49.34606 | K61: 28.219186 | L61: 51.031357 | M61: 51.087313 | N61: 32.204449
B62: Jun | D62: 38.36113 | E62: 36.977906 | F62: 59.221641 | G62: 64.590382 | H62: 63.639104 | I62: 33.892406 | J62: 54.738553 | K62: 45.644729 | L62: 61.420393 | M62: 51.373057 | N62: 47.401981
A63: Peak sesonal of KSN plant | B63: Jul | D63: 60.948308 | E63: 67.050972 | F63: 82.238402 | G63: 76.948121 | H63: 66.97671 | I63: 57.391837 | J63: 69.67791 | K63: 56.669354 | L63: 66.673528 | M63: 76.611994 | N63: 63.850183
B64: Aug | D64: 75.130332 | E64: 100 | F64: 87.810125 | G64: 75.588569 | H64: 57.788024 | I64: 84.161736 | J64: 73.932597 | K64: 57.726616 | L64: 69.344304 | M64: 82.812148 | N64: 92.342806
B65: Sep | D65: 76.180084 | E65: 98.620512 | F65: 81.41399 | G65: 56.894888 | H65: 38.955649 | I65: 76.547883 | J65: 64.773156 | K65: 43.444956 | L65: 31.498367 | M65: 78.109833 | N65: 58.436764
B66: Oct | D66: 28.099128 | E66: 74.692544 | F66: 46.372638 | G66: 45.160891 | H66: 44.014381 | I66: 58.275568 | J66: 15.103931 | K66: 20.8173 | L66: 15.189388 | M66: 80.194464 | N66: 26.093794
B67: Nov | D67: 5.1344728 | E67: 13.749954 | F67: 20.976876 | G67: 25.06179 | H67: 33.605386 | I67: 28.98858 | J67: 4.9917289 | K67: 3.9289739 | L67: 9.1396424 | M67: 13.951113 | N67: 6.4615484
B68: Dec | D68: 13.807588 | E68: 26.363888 | F68: 48.532557 | G68: 52.187976 | H68: 61.081344 | I68: 58.855847 | J68: 15 | K68: 16.191194 | L68: 53.428835 | M68: 61.379571 | N68: 38.898932
B69: YTD | C69: ='[61]Regular+Waxy Farmer'!N50 -> 15.546581 | D69: 46.119354 | E69: 65.16379 | F69: 58.821456 | G69: 59.472795 | H69: 56.719009 | I69: 47.446592 | J69: 36.893717 | K69: 33.431493 | L69: 48.439675 | M69: 62.276778 | N69: 44.05415

Sheet Planner 1.4.2026
B2: Day operation | E2: 27 | F2: 28 | G2: 31 | H2: 24 | I2: 31 | J2: 30 | K2: 30 | L2: 31 | M2: 31 | N2: 31 | O2: 30 | P2: 26
B3: Average Regular Root Grinding/day in period no Grind Waxy | E3: 1340 | F3: 1200 | G3: 1210 | H3: 1450 | I3: 1450 | J3: 1400 | K3: 1400 | L3: 1400 | M3: 1300 | N3: 1200 | O3: 1200 | P3: 1200
E4: Actual | F4: Actual | G4: Actual | H4: Actual+Plan | I4: Plan | J4: Plan | K4: Plan | L4: Plan | M4: Plan | N4: Plan | O4: Plan | P4: Plan
B5: Quarter | E5: Q1 | H5: Q2 | K5: Q3 | N5: Q4
B6: Month | D6: UOM | E6: Jan | F6: Feb | G6: Mar | H6: Apr | I6: May | J6: Jun | K6: Jul | L6: Aug | M6: Sep | N6: Oct | O6: Nov | P6: Dec | Q6: TOTAL | S6: LE0 2026 | T6: 2.2026 | U6: 03.2026 vs LE0 2026 | V6: 03.2026 vs 2.2026
B7: Regular Root Grinding Volume | D7: MT | E7: =[62]Daily!AH16 -> 29398 | F7: =[62]Daily!BK16 -> 30446.73 | G7: =[62]Daily!CQ16 -> 33527 | H7: =[62]Daily!DV16 -> 26978 | I7: =[62]Daily!FB16 -> 39250 | J7: =[62]Daily!GG16 -> 39800 | K7: =[62]Daily!HM16 -> 41800 | L7: =[62]Daily!IS16 -> 41700 | M7: =[62]Daily!JX16 -> 37200 | N7: =[62]Daily!LD16 -> 34300 | O7: =[62]Daily!MI16 -> 33150 | P7: =[62]Daily!NO16 -> 27600 | Q7: =SUM(E7:P7) -> 415149.73 | S7: 445200 | T7: 411365.73 | U7: =Q7-S7 -> -30050.27 | V7: =Q7-T7 -> 3784
B8: Average Regular Root Grinding | D8: MT | E8: =[62]Daily!AH21 -> 1088.8148 | F8: =[62]Daily!BK21 -> 1087.3832 | G8: =[62]Daily!CQ21 -> 1081.5161 | H8: =[62]Daily!DV21 -> 1124.0833 | I8: =[62]Daily!FB21 -> 1266.129 | J8: =[62]Daily!GG21 -> 1326.6667 | K8: =[62]Daily!HM21 -> 1348.3871 | L8: =[62]Daily!IS21 -> 1345.1613 | M8: =[62]Daily!JX21 -> 1240 | N8: =[62]Daily!LD21 -> 1106.4516 | O8: =[62]Daily!MI21 -> 1105 | P8: =[62]Daily!NO21 -> 1061.5385 | Q8: =AVERAGE(E8:P8) -> 1181.761 | S8: 1271.0071 | T8: 1172.4798 | U8: =Q8-S8 -> -89.246131 | V8: =Q8-T8 -> 9.281138
B9: Regular PPDS | D9: THB/kg | E9: =[62]Daily!AH20 -> 10.41 | F9: =[62]Daily!BK20 -> 10.98 | G9: =[62]Daily!CQ20 -> 12 | H9: =[62]Daily!DV20 -> 14 | I9: =[62]Daily!FB20 -> 13.8 | J9: =[62]Daily!GG20 -> 12.166667 | K9: =[62]Daily!HM20 -> 12.94 | L9: =[62]Daily!IS20 -> 12.6 | M9: =[62]Daily!JX20 -> 12.3 | N9: =[62]Daily!LD20 -> 11.95 | O9: =[62]Daily!MI20 -> 11.73 | P9: =[62]Daily!NO20 -> 11.54 | U9: =Q9-S9 -> 0 | V9: =Q9-T9 -> 0
B10: Waxy Root Grinding Volume | D10: MT | E10: =[62]Daily!AH24 -> 2720 | F10: =[62]Daily!BK24 -> 2729 | G10: =[62]Daily!CQ24 -> 2114 | H10: =[62]Daily!DV24 -> 4000 | I10: =[62]Daily!FB24 -> 6528 | J10: =[62]Daily!GG24 -> 1225 | K10: =[62]Daily!HM24 -> 900 | L10: =[62]Daily!IS24 -> 900 | M10: =[62]Daily!JX24 -> 1500 | N10: =[62]Daily!LD24 -> 3000 | O10: =[62]Daily!MI24 -> 3000 | P10: =[62]Daily!NO24 -> 3000 | Q10: =SUM(E10:P10) -> 31616 | S10: 23876 | T10: 31502 | U10: =Q10-S10 -> 7740 | V10: =Q10-T10 -> 114
B11: GLUCOSE - Sales | D11: MT | E11: =[62]Daily!AH99 -> 5234 | F11: =[62]Daily!BK99 -> 5504 | G11: =[62]Daily!CQ99 -> 5620 | H11: =[62]Daily!DV99 -> 4154 | I11: =[62]Daily!FB99 -> 4367 | J11: =[62]Daily!GG99 -> 6202 | K11: =[62]Daily!HM99 -> 5756 | L11: =[62]Daily!IS99 -> 5505 | M11: =[62]Daily!JX99 -> 5587 | N11: =[62]Daily!LD99 -> 5699 | O11: =[62]Daily!MI99 -> 5405 | P11: =[62]Daily!NO99 -> 5250 | Q11: =SUM(E11:P11) -> 64283 | S11: 66285.5 | T11: 63615 | U11: =Q11-S11 -> -2002.5 | V11: =Q11-T11 -> 668
B12: HMS - Sales | D12: MT | E12: =[62]Daily!AH108 -> 570 | F12: =[62]Daily!BK108 -> 600 | G12: =[62]Daily!CQ108 -> 870 | H12: =[62]Daily!DV108 -> 650 | I12: =[62]Daily!FB108 -> 596 | J12: =[62]Daily!GG108 -> 499 | K12: =[62]Daily!HM108 -> 504 | L12: =[62]Daily!IS108 -> 503 | M12: =[62]Daily!JX108 -> 559 | N12: =[62]Daily!LD108 -> 708 | O12: =[62]Daily!MI108 -> 799 | P12: =[62]Daily!NO108 -> 804 | Q12: =SUM(E12:P12) -> 7662 | S12: 8220.3 | T12: 7891 | U12: =Q12-S12 -> -558.3 | V12: =Q12-T12 -> -229
B13: Total Glucose & HMS - Sales | D13: MT | E13: =E11+E12 -> 5804 | F13: =F11+F12 -> 6104 | G13: =G11+G12 -> 6490 | H13: =H11+H12 -> 4804 | I13: =I11+I12 -> 4963 | J13: =J11+J12 -> 6701 | K13: =K11+K12 -> 6260 | L13: =L11+L12 -> 6008 | ... P13: =P11+P12 -> 6054 | Q13: =SUM(E13:P13) -> 71945 | S13: 74505.8 | T13: 71506 | U13: =Q13-S13 -> -2560.8 | V13: =Q13-T13 -> 439
B14: Stock Glucose Ending | D14: MT | E14: =[62]Daily!AH114 -> 973 | F14: =[62]Daily!BK114 -> 856 | G14: =[62]Daily!CQ114 -> 713 | H14: =[62]Daily!DV114 -> 829 | I14: =[62]Daily!FB114 -> 966 | J14: =[62]Daily!GG114 -> 965 | K14: =[62]Daily!HM114 -> 1105 | L14: =[62]Daily!IS114 -> 1097 | M14: =[62]Daily!JX114 -> 1051 | N14: =[62]Daily!LD114 -> 944 | O14: =[62]Daily!MI114 -> 1040 | P14: =[62]Daily!NO114 -> 1286 | U14: =Q14-S14 -> 0 | V14: =Q14-T14 -> 0
B15: REGULAR STARCH - Production | D15: MT | E15: =[62]Daily!AH146 -> 2523.9 | F15: =[62]Daily!BK146 -> 2550.37 | G15: =[62]Daily!CQ146 -> 2647 | H15: =[62]Daily!DV146 -> 1885 | I15: =[62]Daily!FB146 -> 2859.8969 | J15: =[62]Daily!GG146 -> 1706.8321 | K15: =[62]Daily!HM146 -> 2539.0427 | L15: =[62]Daily!IS146 -> 3537.599 | M15: =[62]Daily!JX146 -> 2850.6087 | N15: =[62]Daily!LD146 -> 2276.5969 | O15: =[62]Daily!MI146 -> 2418.0644 | P15: =[62]Daily!NO146 -> 958.11872 | Q15: =SUM(E15:P15) -> 28753.03 | S15: 33406.027 | T15: 27390.397 | U15: =Q15-S15 -> -4652.9974 | V15: =Q15-T15 -> 1362.6325
B16: REGULAR STARCH - in-house total Sales | D16: MT | E16: =[62]Daily!AH157 -> 2029.13 | F16: =[62]Daily!BK157 -> 4453.24 | G16: =[62]Daily!CQ157 -> 2012 | H16: =[62]Daily!DV157 -> 2280 | I16: =[62]Daily!FB157 -> 4733 | J16: =[62]Daily!GG157 -> 2767 | K16: =[62]Daily!HM157 -> 2315 | L16: =[62]Daily!IS157 -> 3002 | M16: =[62]Daily!JX157 -> 2536 | N16: =[62]Daily!LD157 -> 2007 | O16: =[62]Daily!MI157 -> 2240 | P16: =[62]Daily!NO157 -> 1742 | Q16: =SUM(E16:P16) -> 32116.37 | S16: 36370.34 | T16: 30146.98 | U16: =Q16-S16 -> -4253.97 | V16: =Q16-T16 -> 1969.39
B17: REGULAR STARCH - 3P Export Sales | D17: MT | E17: =[62]Daily!AH152 -> 1094 | F17: =[62]Daily!BK152 -> 1940 | G17: =[62]Daily!CQ152 -> 537 | H17: =[62]Daily!DV152 -> 716 | I17: =[62]Daily!FB152 -> 2233 | J17: =[62]Daily!GG152 -> 1602 | K17: =[62]Daily!HM152 -> 596 | L17: =[62]Daily!IS152 -> 520 | M17: =[62]Daily!JX152 -> 579 | N17: =[62]Daily!LD152 -> 581 | O17: =[62]Daily!MI152 -> 500 | P17: =[62]Daily!NO152 -> 543 | Q17: =SUM(E17:P17) -> 11441 | S17: 15676.8 | T17: 10390 | U17: =Q17-S17 -> -4235.8 | V17: =Q17-T17 -> 1051
B18: REGULAR STARCH - 3P Domestic Sales | D18: MT | E18: =[62]Daily!AH153 -> 189 | F18: =[62]Daily!BK153 -> 200 | G18: =[62]Daily!CQ153 -> 272 | H18: =[62]Daily!DV153 -> 185 | I18: =[62]Daily!FB153 -> 216 | J18: =[62]Daily!GG153 -> 195 | K18: =[62]Daily!HM153 -> 172 | L18: =[62]Daily!IS153 -> 172 | M18: =[62]Daily!JX153 -> 175 | N18: =[62]Daily!LD153 -> 206 | O18: =[62]Daily!MI153 -> 217 | P18: =[62]Daily!NO153 -> 200 | Q18: =SUM(E18:P18) -> 2399 | S18: 2431.58 | T18: 2355 | U18: =Q18-S18 -> -32.58 | V18: =Q18-T18 -> 44
B19: REGULAR STARCH - Sales Network Optimize | D19: MT | E19: =[62]Daily!AH154 -> 0 | F19: =[62]Daily!BK154 -> 0 | G19: =[62]Daily!CQ154 -> 0 | H19: =[62]Daily!DV154 -> 0 | I19: =[62]Daily!FB154 -> 0 | J19: =[62]Daily!GG154 -> 0 | K19: =[62]Daily!HM154 -> 250 | L19: =[62]Daily!IS154 -> 270 | M19: =[62]Daily!JX154 -> 250 | N19: =[62]Daily!LD154 -> 250 | O19: =[62]Daily!MI154 -> 300 | P19: =[62]Daily!NO154 -> 250 | Q19: =SUM(E19:P19) -> 1570 | S19: 3100 | T19: 1570 | U19: =Q19-S19 -> -1530 | V19: =Q19-T19 -> 0
B20: REGULAR STARCH - Inco Sales (Export) | D20: MT | E20: =[62]Daily!AH155 -> 746.13 | F20: =[62]Daily!BK155 -> 1004.24 | G20: =[62]Daily!CQ155 -> 548 | H20: =[62]Daily!DV155 -> 1379 | I20: =[62]Daily!FB155 -> 1264 | J20: =[62]Daily!GG155 -> 477 | K20: =[62]Daily!HM155 -> 888 | L20: =[62]Daily!IS155 -> 1085 | M20: =[62]Daily!JX155 -> 896 | N20: =[62]Daily!LD155 -> 817 | O20: =[62]Daily!MI155 -> 985 | P20: =[62]Daily!NO155 -> 749 | Q20: =SUM(E20:P20) -> 10838.37 | S20: 9001.96 | T20: 10150.98 | U20: =Q20-S20 -> 1836.41 | V20: =Q20-T20 -> 687.39
B21: REGULAR STARCH - ISD Jumbo | D21: MT | E21: =[62]Daily!AH156 -> 0 | F21: =[62]Daily!BK156 -> 1309 | G21: =[62]Daily!CQ156 -> 655 | H21: =[62]Daily!DV156 -> 0 | I21: =[62]Daily!FB156 -> 1020 | J21: =[62]Daily!GG156 -> 493 | K21: =[62]Daily!HM156 -> 409 | L21: =[62]Daily!IS156 -> 955 | M21: =[62]Daily!JX156 -> 636 | N21: =[62]Daily!LD156 -> 153 | O21: =[62]Daily!MI156 -> 238 | P21: =[62]Daily!NO156 -> 0 | Q21: =SUM(E21:P21) -> 5868 | S21: 6160 | T21: 5681 | U21: =Q21-S21 -> -292 | V21: =Q21-T21 -> 187
B22: REGULAR STARCH - END Inv (in-house) | D22: MT | E22: =[62]Daily!AH159 -> 5015.77 | F22: =[62]Daily!BK159 -> 3893.9 | G22: =[62]Daily!CQ159 -> 4309.9 | H22: =[62]Daily!DV159 -> 3914.9 | I22: =[62]Daily!FB159 -> 2041.7969 | J22: =[62]Daily!GG159 -> 981.62897 | K22: =[62]Daily!HM159 -> 1205.6717 | L22: =[62]Daily!IS159 -> 1741.2707 | M22: =[62]Daily!JX159 -> 2055.8795 | N22: =[62]Daily!LD159 -> 2325.4764 | O22: =[62]Daily!MI159 -> 2503.5408 | P22: =[62]Daily!NO159 -> 1719.6595
B23: On hold stock | D23: MT | E23: =SUM([62]Daily!AH160:AH161) -> 485.46 | F23: =SUM([62]Daily!BK160:BK161) -> 1201 | G23: =SUM([62]Daily!CQ160:CQ161) -> 156.6 | H23: =SUM([62]Daily!DV160:DV161) -> 156.6 | I23: =SUM([62]Daily!FB160:FB161) -> 156.6 | J23: =SUM([62]Daily!GG160:GG161) -> 0 | K23: =SUM([62]Daily!HM160:HM161) -> 0 | L23: =SUM([62]Daily!IS160:IS161) -> 0 | M23: =SUM([62]Daily!JX160:JX161) -> 0 | N23: =SUM([62]Daily!LD160:LD161) -> 0 | O23: =SUM([62]Daily!MI160:MI161) -> 0 | P23: =SUM([62]Daily!NO160:NO161) -> 0
B24: REGULAR STARCH - SALEABLE INVENTORY | D24: MT | E24: =[62]Daily!AH164 -> 3976.83 | F24: =[62]Daily!BK164 -> 2660.9 | G24: =[62]Daily!CQ164 -> 4146.787 | H24: =[62]Daily!DV164 -> 3758.3 | I24: =[62]Daily!FB164 -> 1885.1969 | J24: =[62]Daily!GG164 -> 981.62897 | K24: =[62]Daily!HM164 -> 1205.6717 | L24: =[62]Daily!IS164 -> 1741.2707 | M24: =[62]Daily!JX164 -> 2055.8795 | N24: =[62]Daily!LD164 -> 2325.4764 | O24: =[62]Daily!MI164 -> 2503.5408 | P24: =[62]Daily!NO164 -> 1719.6595

Sheet Planner 29.4.2026
B2: Day operation | E2: 27 | F2: 28 | G2: 31 | H2: 24 | I2: 31 | J2: 30 | K2: 30 | L2: 31 | M2: 31 | N2: 31 | O2: 30 | P2: 26
B3: Average Regular Root Grinding/day in period no Grind Waxy | E3: 1340 | F3: 1200 | G3: 1210 | H3: 936 | I3: 1000 | J3: 1000 | K3: 1000 | L3: 1200 | M3: 1400 | N3: 1700 | O3: 1700 | P3: 1700
E4: Actual | F4: Actual | G4: Actual | H4: Actual+Plan | I4: Plan | J4: Plan | K4: Plan | L4: Plan | M4: Plan | N4: Plan | O4: Plan | P4: Plan
B5: Quarter | E5: Q1 | H5: Q2 | K5: Q3 | N5: Q4
B6: Month | D6: UOM | E6: Jan | F6: Feb | G6: Mar | H6: Apr | I6: May | J6: Jun | K6: Jul | L6: Aug | M6: Sep | N6: Oct | O6: Nov | P6: Dec | Q6: TOTAL | S6: LE0 2026 | T6: 3.2026 | U6: 04.2026 vs LE0 2026 | V6: 04.2026 vs 2.2026
B7: Regular Root Grinding Volume | D7: MT | E7: =[63]Daily!AH16 -> 29398 | F7: =[63]Daily!BK16 -> 30446.73 | G7: =[63]Daily!CQ16 -> 33527 | H7: =[63]Daily!DV16 -> 18622 | I7: =[63]Daily!FB16 -> 32289 | J7: =[63]Daily!GG16 -> 30000 | K7: =[63]Daily!HM16 -> 31000 | L7: =[63]Daily!IS16 -> 37200 | M7: =[63]Daily!JX16 -> 30250 | N7: =[63]Daily!LD16 -> 45300 | O7: =[63]Daily!MI16 -> 43650 | P7: =[63]Daily!NO16 -> 35100 | Q7: =SUM(E7:P7) -> 396782.73 | S7: 445200 | T7: 406714.32 | U7: =Q7-S7 -> -48417.27 | V7: =Q7-T7 -> -9931.5857
B8: Average Regular Root Grinding | D8: MT | E8: =[63]Daily!AH21 -> 1088.8148 | F8: =[63]Daily!BK21 -> 1087.3832 | G8: =[63]Daily!CQ21 -> 1081.5161 | H8: =[63]Daily!DV21 -> 775.91667 | I8: =[63]Daily!FB21 -> 1041.5806 | J8: =[63]Daily!GG21 -> 1000 | K8: =[63]Daily!HM21 -> 1000 | L8: =[63]Daily!IS21 -> 1200 | M8: =[63]Daily!JX21 -> 1008.3333 | N8: =[63]Daily!LD21 -> 1461.2903 | O8: =[63]Daily!MI21 -> 1455 | P8: =[63]Daily!NO21 -> 1350 | Q8: =AVERAGE(E8:P8) -> 1129.1529 | S8: 1271.0071 | T8: 1156.5823 | U8: =Q8-S8 -> -141.85417 | V8: =Q8-T8 -> -27.429418
B9: Regular PPDS | D9: THB/kg | E9: =[63]Daily!AH20 -> 10.41 | F9: =[63]Daily!BK20 -> 10.98 | G9: =[63]Daily!CQ20 -> 12 | H9: =[63]Daily!DV20 -> 15.42 | I9: =[63]Daily!FB20 -> 16.75 | J9: =[63]Daily!GG20 -> 12.166667 | K9: =[63]Daily!HM20 -> 12.94 | L9: =[63]Daily!IS20 -> 12.6 | M9: =[63]Daily!JX20 -> 12.3 | N9: =[63]Daily!LD20 -> 11.95 | O9: =[63]Daily!MI20 -> 11.73 | P9: =[63]Daily!NO20 -> 11.54 | U9: =Q9-S9 -> 0 | V9: =Q9-T9 -> 0
B10: Waxy Root Grinding Volume | D10: MT | E10: =[63]Daily!AH24 -> 2720 | F10: =[63]Daily!BK24 -> 2729 | G10: =[63]Daily!CQ24 -> 2114 | H10: =[63]Daily!DV24 -> 3794 | I10: =[63]Daily!FB24 -> 2900 | J10: =[63]Daily!GG24 -> 0 | K10: =[63]Daily!HM24 -> 0 | L10: =[63]Daily!IS24 -> 0 | M10: =[63]Daily!JX24 -> 0 | N10: =[63]Daily!LD24 -> 3000 | O10: =[63]Daily!MI24 -> 3000 | P10: =[63]Daily!NO24 -> 3000 | Q10: =SUM(E10:P10) -> 23257 | S10: 23876 | T10: 24147 | U10: =Q10-S10 -> -619 | V10: =Q10-T10 -> -890
B11: GLUCOSE - Sales | D11: MT | E11: =[63]Daily!AH99 -> 5234 | F11: =[63]Daily!BK99 -> 5504 | G11: =[63]Daily!CQ99 -> 5620 | H11: =[63]Daily!DV99 -> 3646 | I11: =[63]Daily!FB99 -> 3238 | J11: =[63]Daily!GG99 -> 5017 | K11: =[63]Daily!HM99 -> 5683 | L11: =[63]Daily!IS99 -> 5522 | M11: =[63]Daily!JX99 -> 5524 | N11: =[63]Daily!LD99 -> 5605 | O11: =[63]Daily!MI99 -> 5453 | P11: =[63]Daily!NO99 -> 5343 | Q11: =SUM(E11:P11) -> 61389 | S11: 66285.5 | T11: 64268 | U11: =Q11-S11 -> -4896.5 | V11: =Q11-T11 -> -2879
B12: HMS - Sales | D12: MT | E12: =[63]Daily!AH108 -> 570 | F12: =[63]Daily!BK108 -> 600 | G12: =[63]Daily!CQ108 -> 870 | H12: =[63]Daily!DV108 -> 750 | I12: =[63]Daily!FB108 -> 600 | J12: =[63]Daily!GG108 -> 594 | K12: =[63]Daily!HM108 -> 504 | L12: =[63]Daily!IS108 -> 503 | M12: =[63]Daily!JX108 -> 559 | N12: =[63]Daily!LD108 -> 708 | O12: =[63]Daily!MI108 -> 799 | P12: =[63]Daily!NO108 -> 804 | Q12: =SUM(E12:P12) -> 7861 | S12: 8220.3 | T12: 7662 | U12: =Q12-S12 -> -359.3 | V12: =Q12-T12 -> 199
B13: Total Glucose & HMS - Sales | D13: MT | E13: =E11+E12 -> 5804 | F13: =F11+F12 -> 6104 | G13: =G11+G12 -> 6490 | H13: =H11+H12 -> 4396 | I13: =I11+I12 -> 3838 | J13: =J11+J12 -> 5611 | K13: =K11+K12 -> 6187 | L13: =L11+L12 -> 6025 | ... P13: =P11+P12 -> 6147 | Q13: =SUM(E13:P13) -> 69250 | S13: 74505.8 | T13: 71930 | U13: =Q13-S13 -> -5255.8 | V13: =Q13-T13 -> -2680
B14: Stock Glucose Ending | D14: MT | E14: =[63]Daily!AH114 -> 973 | F14: =[63]Daily!BK114 -> 852 | G14: =[63]Daily!CQ114 -> 713 | H14: =[63]Daily!DV114 -> 711 | I14: =[63]Daily!FB114 -> 1003 | J14: =[63]Daily!GG114 -> 1092 | K14: =[63]Daily!HM114 -> 1105 | L14: =[63]Daily!IS114 -> 1080 | M14: =[63]Daily!JX114 -> 1097 | N14: =[63]Daily!LD114 -> 1084 | O14: =[63]Daily!MI114 -> 1132 | P14: =[63]Daily!NO114 -> 1285 | U14: =Q14-S14 -> 0 | V14: =Q14-T14 -> 0
B15: REGULAR STARCH - Production | D15: MT | E15: =[63]Daily!AH146 -> 2523.9 | F15: =[63]Daily!BK146 -> 2518.4233 | G15: =[63]Daily!CQ146 -> 2716.1 | H15: =[63]Daily!DV146 -> 254.2 | I15: =[63]Daily!FB146 -> 1778 | J15: =[63]Daily!GG146 -> 659.24228 | K15: =[63]Daily!HM146 -> 643.28196 | L15: =[63]Daily!IS146 -> 2548.4217 | M15: =[63]Daily!JX146 -> 1073.0538 | N15: =[63]Daily!LD146 -> 4700 | O15: =[63]Daily!MI146 -> 4253.144 | P15: =[63]Daily!NO146 -> 3250 | Q15: =SUM(E15:P15) -> 26917.767 | S15: 33406.027 | T15: 27182.309 | U15: =Q15-S15 -> -6488.2599 | V15: =Q15-T15 -> -264.54233
B16: REGULAR STARCH - in-house total Sales | D16: MT | E16: =[63]Daily!AH157 -> 2029.13 | F16: =[63]Daily!BK157 -> 4453.24 | G16: =[63]Daily!CQ157 -> 2012 | H16: =[63]Daily!DV157 -> 1802 | I16: =[63]Daily!FB157 -> 2967.76 | J16: =[63]Daily!GG157 -> 2037.91 | K16: =[63]Daily!HM157 -> 2260 | L16: =[63]Daily!IS157 -> 2845 | M16: =[63]Daily!JX157 -> 2366 | N16: =[63]Daily!LD157 -> 2396 | O16: =[63]Daily!MI157 -> 2854 | P16: =[63]Daily!NO157 -> 1983 | Q16: =SUM(E16:P16) -> 30006.04 | S16: 36370.34 | T16: 29460.99 | U16: =Q16-S16 -> -6364.3 | V16: =Q16-T16 -> 545.05
B17: REGULAR STARCH - 3P Export Sales | D17: MT | E17: =[63]Daily!AH152 -> 1094 | F17: =[63]Daily!BK152 -> 1940 | G17: =[63]Daily!CQ152 -> 537 | H17: =[63]Daily!DV152 -> 809 | I17: =[63]Daily!FB152 -> 301 | J17: =[63]Daily!GG152 -> 543 | K17: =[63]Daily!HM152 -> 595 | L17: =[63]Daily!IS152 -> 522 | M17: =[63]Daily!JX152 -> 579 | N17: =[63]Daily!LD152 -> 761 | O17: =[63]Daily!MI152 -> 693 | P17: =[63]Daily!NO152 -> 687 | Q17: =SUM(E17:P17) -> 9061 | S17: 15676.8 | T17: 8684 | U17: =Q17-S17 -> -6615.8 | V17: =Q17-T17 -> 377
B18: REGULAR STARCH - 3P Domestic Sales | D18: MT | E18: =[63]Daily!AH153 -> 189 | F18: =[63]Daily!BK153 -> 200 | G18: =[63]Daily!CQ153 -> 272 | H18: =[63]Daily!DV153 -> 145 | I18: =[63]Daily!FB153 -> 173 | J18: =[63]Daily!GG153 -> 208 | K18: =[63]Daily!HM153 -> 171 | L18: =[63]Daily!IS153 -> 173 | M18: =[63]Daily!JX153 -> 173 | N18: =[63]Daily!LD153 -> 204 | O18: =[63]Daily!MI153 -> 215 | P18: =[63]Daily!NO153 -> 198 | Q18: =SUM(E18:P18) -> 2321 | S18: 2431.58 | T18: 2399 | U18: =Q18-S18 -> -110.58 | V18: =Q18-T18 -> -78
B19: REGULAR STARCH - Sales Network Optimize | D19: MT | E19: =[63]Daily!AH154 -> 0 | F19: =[63]Daily!BK154 -> 0 | G19: =[63]Daily!CQ154 -> 0 | H19: =[63]Daily!DV154 -> 0 | I19: =[63]Daily!FB154 -> 0 | J19: =[63]Daily!GG154 -> 0 | K19: =[63]Daily!HM154 -> 250 | L19: =[63]Daily!IS154 -> 250 | M19: =[63]Daily!JX154 -> 250 | N19: =[63]Daily!LD154 -> 250 | O19: =[63]Daily!MI154 -> 300 | P19: =[63]Daily!NO154 -> 250 | Q19: =SUM(E19:P19) -> 1550 | S19: 3100 | T19: 1570 | U19: =Q19-S19 -> -1550 | V19: =Q19-T19 -> -20
B20: REGULAR STARCH - Inco Sales (Export) | D20: MT | E20: =[63]Daily!AH155 -> 746.13 | F20: =[63]Daily!BK155 -> 1004.24 | G20: =[63]Daily!CQ155 -> 548 | H20: =[63]Daily!DV155 -> 848 | I20: =[63]Daily!FB155 -> 1473.76 | J20: =[63]Daily!GG155 -> 793.91 | K20: =[63]Daily!HM155 -> 827 | L20: =[63]Daily!IS155 -> 1118 | M20: =[63]Daily!JX155 -> 1050 | N20: =[63]Daily!LD155 -> 782 | O20: =[63]Daily!MI155 -> 1025 | P20: =[63]Daily!NO155 -> 848 | Q20: =SUM(E20:P20) -> 11064.04 | S20: 9001.96 | T20: 10939.99 | U20: =Q20-S20 -> 2062.08 | V20: =Q20-T20 -> 124.05
B21: REGULAR STARCH - ISD Jumbo | D21: MT | E21: =[63]Daily!AH156 -> 0 | F21: =[63]Daily!BK156 -> 1309 | G21: =[63]Daily!CQ156 -> 655 | H21: =[63]Daily!DV156 -> 0 | I21: =[63]Daily!FB156 -> 1020 | J21: =[63]Daily!GG156 -> 493 | K21: =[63]Daily!HM156 -> 417 | L21: =[63]Daily!IS156 -> 782 | M21: =[63]Daily!JX156 -> 314 | N21: =[63]Daily!LD156 -> 399 | O21: =[63]Daily!MI156 -> 621 | P21: =[63]Daily!NO156 -> 0 | Q21: =SUM(E21:P21) -> 6010 | S21: 6160 | T21: 5868 | U21: =Q21-S21 -> -150 | V21: =Q21-T21 -> 142
B22: REGULAR STARCH - END Inv (in-house) | D22: MT | E22: =[63]Daily!AH159 -> 5015.77 | F22: =[63]Daily!BK159 -> 3861.9533 | G22: =[63]Daily!CQ159 -> 4310.0533 | H22: =[63]Daily!DV159 -> 2762.2533 | I22: =[63]Daily!FB159 -> 1572.4933 | J22: =[63]Daily!GG159 -> 193.82554 | K22: =[63]Daily!HM159 -> -1422.8925 | L22: =[63]Daily!IS159 -> -1719.4708 | M22: =[63]Daily!JX159 -> -3012.417 | N22: =[63]Daily!LD159 -> -708.41704 | O22: =[63]Daily!MI159 -> 690.727 | P22: =[63]Daily!NO159 -> 1957.727
B23: On hold stock | D23: MT | E23: =SUM([63]Daily!AH160:AH161) -> 485.46 | F23: =SUM([63]Daily!BK160:BK161) -> 1201 | G23: =SUM([63]Daily!CQ160:CQ161) -> 156.6 | H23: =SUM([63]Daily!DV160:DV161) -> 0 | I23: =SUM([63]Daily!FB160:FB161) -> 0 | J23: =SUM([63]Daily!GG160:GG161) -> 0 | K23: =SUM([63]Daily!HM160:HM161) -> 0 | L23: =SUM([63]Daily!IS160:IS161) -> 0 | M23: =SUM([63]Daily!JX160:JX161) -> 0 | N23: =SUM([63]Daily!LD160:LD161) -> 0 | O23: =SUM([63]Daily!MI160:MI161) -> 0 | P23: =SUM([63]Daily!NO160:NO161) -> 0
B24: REGULAR STARCH - SALEABLE INVENTORY | D24: MT | E24: =[63]Daily!AH164 -> 3976.83 | F24: =[63]Daily!BK164 -> 2628.9533 | G24: =[63]Daily!CQ164 -> 4146.9403 | H24: =[63]Daily!DV164 -> 2762.2533 | I24: =[63]Daily!FB164 -> 1572.4933 | J24: =[63]Daily!GG164 -> 193.82554 | K24: =[63]Daily!HM164 -> -1422.8925 | L24: =[63]Daily!IS164 -> -1719.4708 | M24: =[63]Daily!JX164 -> -3012.417 | N24: =[63]Daily!LD164 -> -708.41704 | O24: =[63]Daily!MI164 -> 690.727 | P24: =[63]Daily!NO164 -> 1957.727

Sheet LV02.04.2026 cost+ Act.
A1: 2026 Cost projection_LV:26/3/2026
F2: LV:26/3/2026 | G2: LV:26/3/2026 | H2: LV:26/3/2026 | I2: LV:26/3/2026 | J2: LV:26/3/2026 | K2: LV:26/3/2026 | L2: LV:26/3/2026 | M2: LV:26/3/2026
A3: SK plant | B3: Jan | C3: Feb | D3: Mar | E3: Apr | F3: May | G3: Jun | H3: Jul | I3: Aug | J3: Sep | K3: Oct | L3: Nov | M3: Dec | N3: Total/Avg.
E4: Stop 8 days
A5: Day operation | B5: 27 | C5: 28 | D5: 31 | E5: 22 | F5: 31 | G5: 30 | H5: 30 | I5: 31 | J5: 31 | K5: 31 | L5: 30 | M5: 26 | N5: =SUM(B5:M5) -> 348 | P5: Plan
A6: Grinding/day without waxy | B6: =B7/B5 -> 1088.8185 | C6: 1087.38 | D6: =D7/D5 -> 1082.5681 | E6: =E7/E5 -> 819.51864 | F6: 1450 | G6: 1400 | H6: 1400 | I6: 1400 | J6: 1300 | K6: 1200 | L6: 1200 | M6: 1200 | N6: =N7/N5 -> 1167.3386 | P6: Apr-Dec
A7: Grinding/month , tons | B7: 29398.1 | C7: 30446.73 | D7: 33559.61 | E7: 18029.41 | F7: 39250 | G7: 39800 | H7: 41800 | I7: 41700 | J7: 37200 | K7: 34300 | L7: 33150 | M7: 27600 | N7: =SUM(B7:M7) -> 406233.85 | P7: From Planner
A9: Roots purchased/month , tons | B9: 29954.31 | C9: 30325.58 | D9: 33527.15 | E9: 18111.17 | F9: ='SK MAP - May 2026 _ 26.03.2026'!E6 -> 39250 | G9: ='SK MAP -June 2026 _ 26.03.2026'!E6 -> 41050 | H9: ='SK MAP -July 2026 _ 26.03.26'!E6 -> 41800 | I9: ='SK MAP -Aug 2026 _ 26.03.26'!E6 -> 41700 | J9: ='SK MAP -Sep 2026 _ 26.03.26 '!E6 -> 37200 | K9: ='SK MAP -Oct 2026 _ 26.03.26'!E6 -> 34300 | L9: ='SK MAP -Nov 2026 _ 26.03.26'!E6 -> 33150 | M9: ='SK MAP -Dec 2026 _ 26.03.26 '!E6 -> 27600 | N9: =SUM(B9:M9) -> 407968.21
A10: Starch content , % | B10: 27.073368 | C10: 26.63 | D10: 24.644387 | E10: 21.281729 | F10: ='SK MAP - May 2026 _ 26.03.2026'!E7*100 -> 20.970382 | G10: ='SK MAP -June 2026 _ 26.03.2026'!G13 -> 21 | H10: ='SK MAP -July 2026 _ 26.03.26'!E7*100 -> 22 | I10: ='SK MAP -Aug 2026 _ 26.03.26'!E7*100 -> 22.504484 | J10: ='SK MAP -Sep 2026 _ 26.03.26 '!E7*100 -> 22.801935 | K10: ='SK MAP -Oct 2026 _ 26.03.26'!E7*100 -> 22.995773 | L10: ='SK MAP -Nov 2026 _ 26.03.26'!E7*100 -> 24 | M10: ='SK MAP -Dec 2026 _ 26.03.26 '!E7*100 -> 25 | N10: =N14/(N9*1000)*100 -> 23.275981
A11: Price , THB/kg. | B11: 2.8182197 | C11: 2.92 | D11: 2.9583502 | E11: 3.286536 | F11: ='SK MAP - May 2026 _ 26.03.2026'!E8 -> 3.1263057 | G11: ='SK MAP -June 2026 _ 26.03.2026'!H13 -> 3.0808161 | H11: ='SK MAP -July 2026 _ 26.03.26'!E8 -> 3.1277512 | I11: ='SK MAP -Aug 2026 _ 26.03.26'!E8 -> 3.1165468 | J11: ='SK MAP -Sep 2026 _ 26.03.26 '!E8 -> 3.0435484 | K11: ='SK MAP -Oct 2026 _ 26.03.26'!E8 -> 2.955102 | L11: ='SK MAP -Nov 2026 _ 26.03.26'!E8 -> 3.0776018 | M11: ='SK MAP -Dec 2026 _ 26.03.26 '!E8 -> 3.1746377 | N11: =N15/(N9*1000) -> 3.0539345 | R11: Actual 2025
A12: PPDS , THB/kg. | B12: =B11/B10*100 -> 10.409564 | C12: 10.98 | D12: 12.004154 | E12: 15.442994 | F12: ='SK MAP - May 2026 _ 26.03.2026'!E9 -> 14.908196 | G12: ='SK MAP -June 2026 _ 26.03.2026'!I13 -> 14.670553 | H12: ='SK MAP -July 2026 _ 26.03.26'!E9 -> 14.217051 | I12: ='SK MAP -Aug 2026 _ 26.03.26'!E9 -> 13.848559 | J12: ='SK MAP -Sep 2026 _ 26.03.26 '!E9 -> 13.347763 | K12: ='SK MAP -Oct 2026 _ 26.03.26'!E9 -> 12.850632 | L12: ='SK MAP -Nov 2026 _ 26.03.26'!E9 -> 12.823341 | M12: ='SK MAP -Dec 2026 _ 26.03.26 '!E9 -> 12.698551 | N12: =N11/N10*100 -> 13.12054 | R12: =#REF! -> #REF!
A14: Weight starch , kg | B14: =((B9*1000)*B10)/100 -> 8109640.5 | C14: 8074417.2 | D14: =((D9*1000)*D10)/100 -> 8262560.5 | E14: =((E9*1000)*E10)/100 -> 3854370.1 | F14: =((F9*1000)*F10)/100 -> 8230875 | G14: =((G9*1000)*G10)/100 -> 8620500 | H14: =((H9*1000)*H10)/100 -> 9196000 | I14: =((I9*1000)*I10)/100 -> 9384370 | J14: =((J9*1000)*J10)/100 -> 8482320 | K14: =((K9*1000)*K10)/100 -> 7887550 | ... M14: =((M9*1000)*M10)/100 -> 6900000 | N14: =SUM(B14:M14) -> 94958603
A15: Amount , THB | B15: =(B9*1000)*B11 -> 84417826 | C15: 88684792 | D15: =(D9*1000)*D11 -> 99185052 | E15: =(E9*1000)*E11 -> 59523013 | F15: =(F9*1000)*F11 -> 122707500 | G15: =(G9*1000)*G11 -> 126467500 | H15: =(H9*1000)*H11 -> 1.3074e+08 | I15: =(I9*1000)*I11 -> 129960000 | J15: =(J9*1000)*J11 -> 113220000 | K15: =(K9*1000)*K11 -> 1.0136e+08 | ... M15: =(M9*1000)*M11 -> 87620000 | N15: =SUM(B15:M15) -> 1.2459082e+09
A17: Co-products prices , THB/kg
A18: Pulp (moisture 79%) | B18: 0.282 | C18: 0.282 | D18: 0.36561484 | E18: 0.369 | F18: 0.254 | G18: 0.254 | H18: 0.254 | I18: 0.254 | J18: 0.254 | K18: 0.254 | L18: 0.254 | M18: 0.254 | N18: =AVERAGE(B18:M18) -> 0.27755124
A19: Soil Skin | B19: 0.03 | C19: 0.03 | D19: 0.03 | E19: 0.029158726 | F19: 0.03 | G19: 0.03 | H19: 0.03 | I19: 0.03 | J19: 0.03 | K19: 0.03 | L19: 0.03 | M19: 0.03 | N19: =AVERAGE(B19:M19) -> 0.029929894
A20: Wash Skin | B20: 0.2 | C20: 0.2 | D20: 0.24733343 | E20: 0.25 | F20: 0.2 | G20: 0.2 | H20: 0.2 | I20: 0.2 | J20: 0.2 | K20: 0.2 | L20: 0.2 | M20: 0.2 | N20: =AVERAGE(B20:M20) -> 0.20811112
A21: Pulp moisture, actual | B21: 0.7875 | C21: 0.7869 | D21: 0.78003438 | E21: 0.77801844
A23: 2026 Cost projection_LV:02/4/2026
F24: LV:02/4/2026 | G24: LV:02/4/2026 | H24: LV:02/4/2026 | I24: LV:02/4/2026 | J24: LV:02/4/2026 | K24: LV:02/4/2026 | L24: LV:02/4/2026 | M24: LV:02/4/2026
A25: KSN plant | B25: Jan | C25: Feb | D25: Mar | E25: Apr | F25: May | G25: Jun | H25: Jul | I25: Aug | J25: Sep | K25: Oct | L25: Nov | M25: Dec | N25: Total/Avg.
C26: Stop 1 day | D26: Stop 2 days | E26: Stop 8 days
A27: Day operation | B27: 28 | C27: 27 | D27: 29 | E27: 22 | F27: 31 | G27: 30 | H27: 31 | I27: 31 | J27: 30 | K27: 31 | L27: 30 | M27: 26 | N27: =SUM(B27:M27) -> 346
A28: Grinding/day without waxy | B28: =B29/B27 -> 516.30804 | C28: 519.15 | D28: =D29/D27 -> 507.18548 | E28: =E29/E27 -> 521.34364 | F28: 700 | G28: 700 | H28: 700 | I28: 700 | J28: 700 | K28: 700 | L28: 700 | M28: 600 | N28: =N29/N27 -> 635.98695
A29: Grinding/month , tons | B29: 14456.625 | C29: 14016.92 | D29: 14708.379 | E29: 11469.56 | F29: =F28*F27 -> 21700 | G29: =G28*G27 -> 21000 | H29: =H28*H27 -> 21700 | I29: =I28*I27 -> 21700 | J29: =J28*J27 -> 21000 | K29: =K28*K27 -> 21700 | L29: =L28*L27 -> 21000 | M29: =M28*M27 -> 15600 | N29: =SUM(B29:M29) -> 220051.48
A31: Roots purchased/month , tons | B31: 15610.621 | C31: 14627.14 | D31: 14093.328 | E31: 12056.588 | F31: 21700 | G31: 21000 | H31: 21700 | I31: 21700 | J31: 21000 | K31: 21700 | L31: 21000 | M31: 15600 | N31: =SUM(B31:M31) -> 221787.68
A32: Actual starch content | B32: 27.464032 | C32: 27.61 | D32: 25.43097 | E32: 22.227507 | F32: ='KSN MAP - May 2026_02.04.26'!G13 -> 21.551429 | G32: ='KSN MAP - Jun 2026_02.04.26'!G13 -> 21.496429 | H32: ='KSN MAP - Jul 2026_02.04.26'!G13 -> 21.995 | I32: ='KSN MAP - Aug 2026_02.04.26'!G13 -> 23.5 | J32: ='KSN MAP - Sep 2026 _02.04.26'!G13 -> 24.404286 | K32: ='KSN MAP - Oct 2026_02.04.26'!G13 -> 25.2 | L32: ='KSN MAP - Nov 2026 _02.04.26'!G13 -> 25.7 | M32: ='KSN MAP - Dec 2026 _02.04.26'!G13 -> 27.5 | N32: =N36/(N31*1000)*100 -> 24.317285
A33: Actual price | B33: 2.9210987 | C33: 2.95 | D33: 2.8933837 | E33: 3.2285971 | F33: ='KSN MAP - May 2026_02.04.26'!H13 -> 3.005 | G33: ='KSN MAP - Jun 2026_02.04.26'!H13 -> 3.0014286 | H33: ='KSN MAP - Jul 2026_02.04.26'!H13 -> 2.9785714 | I33: ='KSN MAP - Aug 2026_02.04.26'!H13 -> 3.0085714 | J33: ='KSN MAP - Sep 2026 _02.04.26'!H13 -> 2.9985714 | K33: ='KSN MAP - Oct 2026_02.04.26'!H13 -> 3.0628571 | L33: ='KSN MAP - Nov 2026 _02.04.26'!H13 -> 3.1328571 | M33: ='KSN MAP - Dec 2026 _02.04.26'!H13 -> 3.2166667 | N33: =N37/(N31*1000) -> 3.0297179 | R33: =R11 -> Actual 2025
A34: PPDS | B34: 10.636088 | C34: 10.67 | D34: 11.377402 | E34: 14.525232 | F34: =F33/F32*100 -> 13.943391 | G34: =G33/G32*100 -> 13.962452 | H34: =H33/H32*100 -> 13.542039 | I34: =I33/I32*100 -> 12.802432 | J34: =J33/J32*100 -> 12.287069 | K34: =K33/K32*100 -> 12.154195 | L34: =L33/L32*100 -> 12.190106 | M34: =M33/M32*100 -> 11.69697 | N34: =N33/N32*100 -> 12.459113 | R34: =#REF! -> #REF!
A36: Weight starch , kg | B36: =((B31*1000)*B32)/100 -> 4287306 | C36: 4037862 | D36: =((D31*1000)*D32)/100 -> 3584070 | E36: =((E31*1000)*E32)/100 -> 2679879 | F36: =((F31*1000)*F32)/100 -> 4676660 | G36: =((G31*1000)*G32)/100 -> 4514250 | H36: =((H31*1000)*H32)/100 -> 4772915 | I36: =((I31*1000)*I32)/100 -> 5099500 | J36: =((J31*1000)*J32)/100 -> 5124900 | K36: =((K31*1000)*K32)/100 -> 5468400 | ... M36: =((M31*1000)*M32)/100 -> 4290000 | N36: =SUM(B36:M36) -> 53932742
A37: Amount , THB | B37: =(B31*1000)*B33 -> 45600164 | C37: 43087170 | D37: =(D31*1000)*D33 -> 40777405 | E37: =(E31*1000)*E33 -> 38925865 | F37: =(F31*1000)*F33 -> 65208500 | G37: =(G31*1000)*G33 -> 63030000 | H37: =(H31*1000)*H33 -> 64635000 | I37: =(I31*1000)*I33 -> 65286000 | J37: =(J31*1000)*J33 -> 62970000 | K37: =(K31*1000)*K33 -> 66464000 | ... M37: =(M31*1000)*M33 -> 50180000 | N37: =SUM(B37:M37) -> 6.7195411e+08
A39: Co-products prices, THB/kg
A40: Pulp | B40: 0.134 | C40: 0.134 | D40: 0.134 | E40: 0.134 | F40: 0.134 | G40: 0.134 | H40: 0.134 | I40: 0.134 | J40: 0.134 | K40: 0.134 | L40: 0.134 | M40: 0.134 | N40: =AVERAGE(B40:M40) -> 0.134
A41: Soil Skin | B41: 0.03 | C41: 0.03 | D41: 0.03 | E41: 0.03 | F41: 0.03 | G41: 0.03 | H41: 0.03 | I41: 0.03 | J41: 0.03 | K41: 0.03 | L41: 0.03 | M41: 0.03 | N41: =AVERAGE(B41:M41) -> 0.03
A42: Wash Skin | B42: 0.12 | C42: 0.12 | D42: 0.12 | E42: 0.12 | F42: 0.12 | G42: 0.12 | H42: 0.12 | I42: 0.12 | J42: 0.12 | K42: 0.12 | L42: 0.12 | M42: 0.12 | N42: =AVERAGE(B42:M42) -> 0.12

Sheet SK ST+Price+PPDS_LV02.04.2026
B2: SK plant
B4: Starch content in root (%)
B5: Month | C5: 2026 El Niño | D5: 2025 La Niña | E5: 2024 El Niño | F5: 2023 El Niño | G5: 2022 La Niña | H5: 2021 La Niña | I5: 2020 La Niña | J5: 2019 | K5: 2018 | L5: 2017 | M5: 2016 | N5: 2015
B6: Jan | C6: 27.073368 | D6: 27.465482 | E6: 26.552126 | F6: 28.283012 | G6: 28.075819 | H6: 28.283416 | I6: 26.452771 | J6: 27.600559 | K6: 28.75 | L6: 28.48 | M6: 27.988439 | N6: 28.53
B7: Feb | C7: ='LV02.04.2026 cost+ Act.'!C10 -> 26.63 | D7: 27.142097 | E7: 27.098026 | F7: 28.246149 | G7: 27.665692 | H7: 28.343564 | I7: 26.436967 | J7: 27.6 | K7: 28.75 | L7: 28.99 | M7: 28.524987 | N7: 28.9513
B8: Mar | C8: ='LV02.04.2026 cost+ Act.'!D10 -> 24.644387 | D8: 25.506314 | E8: 25.153572 | F8: 27.27257 | G8: 26.223927 | H8: 26.636336 | I8: 24.42815 | J8: 25.985059 | K8: 26.75 | L8: 27.941922 | M8: 27.796808 | N8: 26.68091
B9: Apr | C9: ='LV02.04.2026 cost+ Act.'!E10 -> 21.281729 | D9: 22.363459 | E9: 21.636709 | F9: 24.331309 | G9: 24.772808 | H9: 24.116969 | I9: 21.491937 | J9: 22.72 | K9: 24.85 | L9: 25.393449 | M9: 25.197741 | N9: 25.48
B10: May | C10: ='LV02.04.2026 cost+ Act.'!F10 -> 20.970382 | D10: 19.449638 | E10: 18.241591 | F10: 20.530842 | G10: 23.098356 | H10: 22.594208 | I10: 20.447716 | J10: 20.44 | K10: 23.39 | L10: 23.453555 | M10: 22.082839 | N10: 24.298698
B11: Jun | C11: ='LV02.04.2026 cost+ Act.'!G10 -> 21 | D11: 20.598081 | E11: 16.633931 | F11: 20.08 | G11: 23.058919 | H11: 22.643665 | I11: 20.831887 | J11: 21.06 | K11: 23.75 | L11: 24.251453 | M11: 20.984485 | N11: 22.924381
B12: Jul | C12: ='LV02.04.2026 cost+ Act.'!H10 -> 22 | D12: 23.384067 | E12: 18.040337 | F12: 22.568159 | G12: 24.122682 | H12: 23.921738 | I12: 22.260539 | J12: 22.05 | K12: 24.95 | L12: 25.399363 | M12: 22.366981 | N12: 22.238087
B13: Aug | C13: ='LV02.04.2026 cost+ Act.'!I10 -> 22.504484 | D13: 24.238562 | E13: 21.33516 | F13: 24.498753 | G13: 24.589269 | H13: 24.39491 | I13: 23.375192 | J13: 22.9 | K13: 25.87 | L13: 25.874386 | M13: 25.135475 | N13: 23.603732
B14: Sep | C14: ='LV02.04.2026 cost+ Act.'!J10 -> 22.801935 | D14: 24.537915 | E14: 23.015575 | F14: 24.04 | G14: 25.249353 | H14: 24.676516 | I14: 23.848565 | J14: 23.22 | K14: 26.47 | L14: 25.921535 | M14: 25.698979 | N14: 23.984547
B15: Oct | C15: ='LV02.04.2026 cost+ Act.'!K10 -> 22.995773 | D15: 24.001491 | E15: 23.447747 | F15: 23.844147 | G15: 25.791357 | H15: 24.768643 | I15: 24.304353 | J15: 24.51 | K15: 26.07 | L15: 25.911833 | M15: 25.764254 | N15: 24.596381
B16: Nov | C16: ='LV02.04.2026 cost+ Act.'!L10 -> 24 | D16: 24.842139 | E16: 24.281086 | F16: 24.370364 | G16: 27.209794 | H16: 25.410465 | I16: 25.208214 | J16: 25.28 | K16: 26.428 | L16: 26.88 | M16: 25.574764 | N16: 25.327068
B17: Dec | C17: ='LV02.04.2026 cost+ Act.'!M10 -> 25 | D17: 25.807675 | E17: 25.663568 | F17: 25.544211 | G17: 27.303537 | H17: 27.091963 | I17: 27.464238 | J17: 25.97 | K17: 27.402526 | L17: 28.2 | M17: 27.132339 | N17: 26.911576
B18: YTD | C18: ='LV02.04.2026 cost+ Act.'!N10 -> 23.275981 | D18: 23.891104 | E18: 22.277682 | F18: 24.550107 | G18: 25.463697 | H18: 25.035661 | I18: 23.766044 | J18: 23.968278 | K18: 26.167983 | L18: 26.324424 | M18: 25.23 | N18: 25.08
D19: =C9-E19 -> 18.367908 | E19: =D9-D10 -> 2.9138212
E20: Apr-May : El Niño Jun-Aug : La Niña | F20: Drought | G20: Continue rain | H20: Flooding | I20: Co-vid19 | J20: Drought/CMD | K20: Crisis /Drought /CMD | L20: Senka - Flooding | M20: Drought
B21: Price (THB./Kg.)
B22: Month | C22: 2026 | D22: 2025 | E22: 2024 | F22: 2023 | G22: 2022 | H22: 2021 | I22: 2020 | J22: 2019 | K22: 2018 | L22: 2017 | M22: 2016 | N22: 2015
B23: Jan | C23: 2.8182197 | D23: 2.3206125 | E23: 3.8811187 | F23: 3.3707016 | G23: 2.8679964 | H23: 2.4321249 | I23: 2.4349758 | J23: 2.7330793 | K23: 2.6846275 | L23: 1.9640519 | M23: 2.3831074 | N23: 2.6862319
B24: Feb | C24: ='LV02.04.2026 cost+ Act.'!C11 -> 2.92 | D24: 2.2929551 | E24: 3.8121126 | F24: 3.5307178 | G24: 2.8003392 | H24: 2.5347841 | I24: 2.3773005 | J24: 2.6221188 | K24: 2.7929828 | L24: 1.9008149 | M24: 2.2986145 | N24: 2.5758909
B25: Mar | C25: ='LV02.04.2026 cost+ Act.'!D11 -> 2.9583502 | D25: 2.0350253 | E25: 3.52454 | F25: 3.8271873 | G25: 2.9025373 | H25: 2.4968198 | I25: 2.2580928 | J25: 2.6008877 | K25: 3.0816588 | L25: 1.8959876 | M25: 2.2863871 | N25: 2.412576
B26: Apr | C26: ='LV02.04.2026 cost+ Act.'!E11 -> 3.286536 | D26: 1.8683628 | E26: 3.1336716 | F26: 3.9203079 | G26: 3.0721751 | H26: 2.5831193 | I26: 2.0728862 | J26: 2.4824865 | K26: 3.4087085 | L26: 1.7969313 | M26: 2.3015141 | N26: 2.4720834
B27: May | C27: ='LV02.04.2026 cost+ Act.'!F11 -> 3.1263057 | D27: 1.8105822 | E27: 2.8330475 | F27: 3.591888 | G27: 3.2212402 | H27: 2.4395852 | I27: 2.1191505 | J27: 2.2385166 | K27: 3.2121688 | L27: 1.7619482 | M27: 2.1283473 | N27: 2.4768338
B28: Jun | C28: ='LV02.04.2026 cost+ Act.'!G11 -> 3.0808161 | D28: 1.9014496 | E28: 2.3804216 | F28: 3.1777245 | G28: 3.1931162 | H28: 2.4319136 | I28: 2.1076855 | J28: 2.1460582 | K28: 3.0607744 | L28: 1.7574709 | M28: 2.0202376 | N28: 2.5179536
B29: Jul | C29: ='LV02.04.2026 cost+ Act.'!H11 -> 3.1277512 | D29: 2.3831165 | E29: 2.5238319 | F29: 3.4243199 | G29: 3.3706548 | H29: 2.5888143 | I29: 2.2176649 | J29: 2.302884 | K29: 3.0627285 | L29: 1.8329102 | M29: 1.9109423 | N29: 2.5808822
B30: Aug | C30: ='LV02.04.2026 cost+ Act.'!I11 -> 3.1165468 | D30: 2.4913376 | E30: 2.7262263 | F30: 3.621204 | G30: 3.2971745 | H30: 2.6210172 | I30: 2.308271 | J30: 2.3741792 | K30: 3.0904943 | L30: 1.874876 | M30: 1.8615915 | N30: 2.5745389
B31: Sep | C31: ='LV02.04.2026 cost+ Act.'!J11 -> 3.0435484 | D31: 2.4337319 | E31: 2.8448843 | F31: 3.5944677 | G31: 3.3406941 | H31: 2.7038312 | I31: 2.3222267 | J31: 2.3502101 | K31: 3.2067345 | L31: 2.0527029 | M31: 1.7232699 | N31: 2.5489264
B32: Oct | C32: ='LV02.04.2026 cost+ Act.'!K11 -> 2.955102 | D32: 2.3955283 | E32: 2.5731024 | F32: 3.543168 | G32: 3.2375012 | H32: 2.6903687 | I32: 2.325409 | J32: 2.3754588 | K32: 3.1382285 | L32: 2.2131489 | M32: 1.6437255 | N32: 2.4681459
B33: Nov | C33: ='LV02.04.2026 cost+ Act.'!L11 -> 3.0776018 | D33: 2.5972745 | E33: 2.5105695 | F33: 3.8483627 | G33: 3.2710718 | H33: 2.8612413 | I33: 2.3976659 | J33: 2.4911511 | K33: 3.0520859 | L33: 2.4194326 | M33: 1.8990576 | N33: 2.5117689
B34: Dec | C34: ='LV02.04.2026 cost+ Act.'!M11 -> 3.1746377 | D34: 2.6599125 | E34: 2.3272461 | F34: 3.8269274 | G34: 3.2197843 | H34: 2.8350489 | I34: 2.4806185 | J34: 2.4320356 | K34: 2.9205169 | L34: 2.5506959 | M34: 2.0687513 | N34: 2.440626
B35: YTD | C35: ='LV02.04.2026 cost+ Act.'!N11 -> 3.0539345 | D35: 2.2460448 | E35: 2.8880699 | F35: 3.6135815 | G35: 3.1609713 | H35: 2.5957875 | I35: 2.280929 | J35: 2.4192097 | K35: 3.0572651 | L35: 1.9961105 | M35: 2.0306835 | N35: 2.5222972
B38: PPDS (THB./Kg.)
B39: Month | C39: 2026 | D39: 2025 | E39: 2024 | F39: 2023 | G39: 2022 | H39: 2021 | I39: 2020 | J39: 2019 | K39: 2018 | L39: 2017 | M39: 2016 | N39: 2015 | AD39: PPDS (THB./Kg.)
B40: Jan | C40: 10.41 | D40: 8.4491964 | E40: 14.616979 | F40: 11.91776 | G40: 10.215184 | H40: 8.5991199 | I40: 9.187 | J40: 9.9022604 | K40: 9.3393593 | L40: 6.8955851 | M40: 8.5146134 | N40: 9.413831 | AD40: Month | AE40: Act'25 | AF40: LV'26 | AG40: Act'26
B41: Feb | C41: ='LV02.04.2026 cost+ Act.'!C12 -> 10.98 | D41: 8.4479659 | E41: 14.067861 | F41: 12.49982 | G41: 10.122065 | H41: 8.9430675 | I41: 8.9923347 | J41: 9.5019659 | K41: 9.716073 | L41: 6.5577669 | M41: 8.058249 | N41: 8.897324 | AD41: Jan | AE41: 8.4491964 | AF41: 10.409564 | AG41: 10.409564
B42: Mar | C42: ='LV02.04.2026 cost+ Act.'!D12 -> 12.004154 | D42: 7.9785161 | E42: 14.012085 | F42: 14.033101 | G42: 11.068279 | H42: 9.3737357 | I42: 9.2438142 | J42: 10.009166 | K42: 11.519522 | L42: 6.7854588 | M42: 8.2253586 | N42: 9.04233 | AD42: Feb | AE42: 8.4479659 | AF42: 10.98 | AG42: 10.98
B43: Apr | C43: ='LV02.04.2026 cost+ Act.'!E12 -> 15.442994 | D43: 8.354534 | E43: 14.483125 | F43: 16.112195 | G43: 12.4014 | H43: 10.710796 | I43: 9.6449485 | J43: 10.926437 | K43: 13.714599 | L43: 7.076358 | M43: 9.1338112 | N43: 9.7023998 | AD43: Mar | AE43: 7.9785161 | AF43: 12.004154 | AG43: 12.004154
B44: May | C44: ='LV02.04.2026 cost+ Act.'!F12 -> 14.908196 | D44: 9.3090793 | E44: 15.530704 | F44: 17.495084 | G44: 13.945756 | H44: 10.797392 | I44: 10.363752 | J44: 10.953312 | K44: 13.735717 | L44: 7.5124997 | M44: 9.6380148 | N44: 10.193278 | AD44: Apr | AE44: 8.354534 | AF44: 13.999383 | AG44: 15.442994
B45: Jun | C45: ='LV02.04.2026 cost+ Act.'!G12 -> 14.670553 | D45: 9.2311978 | E45: 14.310638 | F45: 15.825321 | G45: 13.84764 | H45: 10.739929 | I45: 10.117592 | J45: 10.19021 | K45: 12.886078 | L45: 7.2468682 | M45: 9.6272916 | N45: 10.983736 | AD45: May | AE45: 9.3090793 | AF45: 14.908196 | AG45: 16.75
B46: Jul | C46: ='LV02.04.2026 cost+ Act.'!H12 -> 14.217051 | D46: 10.191198 | E46: 13.989938 | F46: 15.173235 | G46: 13.972969 | H46: 10.822016 | I46: 9.9623145 | J46: 10.44451 | K46: 12.275767 | L46: 7.2163631 | M46: 8.5435862 | N46: 11.605684 | AD46: Jun | AE46: 9.2311978 | AF46: 14.670553
B47: Aug | C47: ='LV02.04.2026 cost+ Act.'!I12 -> 13.848559 | D47: 10.278405 | E47: 12.778091 | F47: 14.781177 | G47: 13.408998 | H47: 10.744115 | I47: 9.8748752 | J47: 10.366079 | K47: 11.948069 | L47: 7.2460694 | M47: 7.4062318 | N47: 10.907338 | AD47: Jul | AE47: 10.191198 | AF47: 14.217051
B48: Sep | C48: ='LV02.04.2026 cost+ Act.'!J12 -> 13.347763 | D48: 9.9182504 | E48: 12.360692 | F48: 14.952029 | G48: 13.230811 | H48: 10.957103 | I48: 9.7373851 | J48: 10.121432 | K48: 12.116474 | L48: 7.9189095 | M48: 6.7055965 | N48: 10.627369 | AD48: Aug | AE48: 10.278405 | AF48: 13.848559
B49: Oct | C49: ='LV02.04.2026 cost+ Act.'!K12 -> 12.850632 | D49: 9.9807478 | E49: 10.973772 | F49: 14.859697 | G49: 12.552659 | H49: 10.861995 | I49: 9.5678703 | J49: 9.6929291 | K49: 12.039456 | L49: 8.541074 | M49: 6.3798681 | N49: 10.03459 | AD49: Sep | AE49: 9.9182504 | AF49: 13.347763
B50: Nov | C50: ='LV02.04.2026 cost+ Act.'!L12 -> 12.823341 | D50: 10.455116 | E50: 10.339609 | F50: 15.791158 | G50: 12.021671 | H50: 11.26009 | I50: 9.5114471 | J50: 9.85 | K50: 11.548683 | L50: 9.0002824 | M50: 7.4255137 | N50: 9.9173298 | AD50: Oct | AE50: 9.9807478 | AF50: 12.850632
B51: Dec | C51: ='LV02.04.2026 cost+ Act.'!M12 -> 12.698551 | D51: 10.306672 | E51: 9.0682873 | F51: 14.981584 | G51: 11.792554 | H51: 10.464538 | I51: 9.0321766 | J51: 9.36 | K51: 10.657838 | L51: 9.044419 | M51: 7.6246697 | N51: 9.0690562 | AD51: Nov | AE51: 10.455116 | AF51: 12.823341
B52: YTD | C52: ='LV02.04.2026 cost+ Act.'!N12 -> 13.12054 | D52: 9.4011763 | E52: 12.963961 | F52: 14.719209 | G52: 12.413638 | H52: 10.36836 | I52: 9.5974283 | J52: 10.093381 | K52: 11.683228 | L52: 7.58 | M52: 8.05 | N52: 10.055094 | AD52: Dec | AE52: 10.306672 | AF52: 12.698551
B55: Farmer ratio of regular root at SK plant, %
B56: Month | C56: 2026 | D56: 2025 | E56: 2024 | F56: 2023 | G56: 2022 | H56: 2021 | I56: 2020 | J56: 2019 | K56: 2018 | L56: 2017 | M56: 2016 | N56: 2015
B57: Jan | C57: 16.82 | D57: 46.744451 | E57: 47.328135 | F57: 49.313039 | G57: 55.328108 | H57: 53.856642 | I57: 51.082904 | J57: 46.366718 | K57: 57.38296 | L57: 67.816417 | M57: 76.396046 | N57: 95.089747
B58: Feb | C58: 17.01 | D58: 43.641985 | E58: 46.875754 | F58: 45.158938 | G58: 53.335285 | H58: 40.956232 | I58: 49.407957 | J58: 36.77052 | K58: 50.488072 | L58: 69.661983 | M58: 75.840108 | N58: 76.508449
B59: Mar | C59: 17.29822 | D59: 43.948484 | E59: 50.174103 | F59: 32.552341 | G59: 36.825521 | H59: 48.238213 | I59: 43.546182 | J59: 29.653185 | K59: 26.785755 | L59: 46.375782 | M59: 70.563534 | N59: 85.958965
A60: Low sesonal of SK plant | B60: Apr | D60: 48.813182 | E60: 46.894103 | F60: 23.768885 | G60: 48.778404 | H60: 35.155245 | I60: 38.391769 | J60: 31.669496 | K60: 11.006388 | L60: 43.391665 | M60: 63.589943 | N60: 50.515012
B61: May | D61: 29.817966 | E61: 18.336852 | F61: 14.853418 | G61: 24.402908 | H61: 27.418823 | I61: 12.597807 | J61: 11.838503 | K61: 4.3930509 | L61: 14.91966 | M61: 27.324054 | N61: 28.28983
B62: Jun | D62: 39.88099 | E62: 23.521755 | F62: 45.63439 | G62: 44.072685 | H62: 33.174332 | I62: 18.039192 | J62: 7.4314477 | K62: 25.576839 | L62: 21.952311 | M62: 12.778572 | N62: 24.452272
B63: Jul | D63: 8.6936122 | E63: 25.953046 | F63: 29.851017 | G63: 14.311193 | H63: 12.299146 | I63: 18.530378 | J63: 7.2234477 | K63: 16.992185 | L63: 16.896658 | M63: 18.979723 | N63: 9.6649777
B64: Aug | D64: 2.9182525 | E64: 17.461098 | F64: 15.503981 | G64: 16.864038 | H64: 13.325462 | I64: 17.351241 | J64: 6.9412066 | K64: 9.8333698 | L64: 7.2065018 | M64: 13.590361 | N64: 3.8744705
B65: Sep | D65: 11.488072 | E65: 28.847277 | F65: 36.689826 | G65: 27.468099 | H65: 20.798471 | I65: 25.467666 | J65: 21.62962 | K65: 18.156093 | L65: 11.514729 | M65: 15.666816 | N65: 13.64245
B66: Oct | D66: 27.485729 | E66: 37.774696 | F66: 41.86864 | G66: 41.195546 | H66: 39.138149 | I66: 37.247378 | J66: 39.563258 | K66: 37.631226 | L66: 21.004282 | M66: 15.584259 | N66: 32.136982
B67: Nov | D67: 10.474762 | E67: 41.426022 | F67: 39.620466 | G67: 39.718051 | H67: 43.949186 | I67: 46.341419 | J67: 34.538145 | K67: 26.252632 | L67: 41.458726 | M67: 31.638793 | N67: 33.423935
B68: Dec | D68: 19.529223 | E68: 38.963149 | F68: 44.826667 | G68: 46.229808 | H68: 48.982344 | I68: 47.04375 | J68: 48.232387 | K68: 27.722387 | L68: 50.734915 | M68: 47.538284 | N68: 42.318982
B69: YTD | C69: 17.0534 | D69: 28.197528 | E69: 34.004902 | F69: 35.14574 | G69: 36.276747 | H69: 33.911514 | I69: 32.857325 | J69: 25.835374 | K69: 26.262126 | L69: 33.494095 | M69: 37.322971 | N69: 37.848035
B72: Farmer ratio of regular+waxy root at SK plant, %
B73: Month | C73: 2026 | D73: 2025 | E73: 2024 | F73: 2023 | G73: 2022 | H73: 2021 | I73: 2020 | J73: 2019
B74: Jan | C74: 36.29 | D74: 55.007548 | E74: 51.707237 | F74: 55.040969 | G74: 61.66006 | H74: 60.452988 | I74: 55.860088 | J74: 50.553201
B75: Feb | C75: 38.67 | D75: 49.083117 | E75: 52.815593 | F75: 53.944779 | G75: 58.445229 | H75: 49.022493 | I75: 53.047407 | J75: 41.239131
B76: Mar | C76: 25.863851 | D76: 47.92089 | E76: 54.448063 | F76: 37.930284 | G76: 46.038707 | H76: 51.469751 | I76: 45.715417 | J76: 32.530908
A77: Low sesonal of SK plant | B77: Apr | D77: 48.813182 | E77: 49.567845 | F77: 27.130181 | G77: 51.754688 | H77: 35.155245 | I77: 38.391769 | J77: 31.669496
B78: May | D78: 30.65349 | E78: 18.336852 | F78: 15.835483 | G78: 26.012109 | H78: 28.562153 | I78: 12.597807 | J78: 11.838503
B79: Jun | D79: 39.88099 | E79: 24.106135 | F79: 46.575184 | G79: 45.969551 | H79: 33.174332 | I79: 18.039192 | J79: 9.6947561
B80: Jul | D80: 10.339389 | E80: 26.44529 | F80: 29.851017 | G80: 15.357145 | H80: 13.825758 | I80: 21.421449 | J80: 8.5299666
B81: Aug | D81: 4.3878101 | E81: 17.461098 | F81: 15.503981 | G81: 18.118256 | H81: 14.954403 | I81: 17.351241 | J81: 8.2175355
B82: Sep | D82: 13.880771 | E82: 29.651793 | F82: 38.128047 | G82: 29.015232 | H82: 21.53558 | I82: 26.903914 | J82: 21.62962
B83: Oct | D83: 32.434841 | E83: 38.928141 | F83: 42.59052 | G83: 44.353942 | H83: 39.793352 | I83: 38.307969 | J83: 41.070466
B84: Nov | D84: 28.998602 | E84: 47.349226 | F84: 42.129106 | G84: 43.135857 | H84: 47.313301 | I84: 48.089978 | J84: 34.538145
B85: Dec | D85: 29.587852 | E85: 45.047443 | F85: 46.376892 | G85: 53.45105 | H85: 54.033034 | I85: 50.138287 | J85: 48.232387
B86: YTD | C86: 33.802739 | D86: 32.358473 | E86: 37.006712 | F86: 38.17754 | G86: 40.402705 | H86: 36.952988 | I86: 34.832257 | J86: 27.481225

Sheet KSN ST+Price+PPDS_LV02.04.2026
B2: KSN plant
B4: Starch content in root (%)
B5: Month | C5: 2026 El Niño | D5: 2025 La Niña | E5: 2024 El Niño | F5: 2023 El Niño | G5: 2022 La Niña | H5: 2021 La Niña | I5: 2020 La Niña | J5: 2019 | K5: 2018 | L5: 2017 | M5: 2016 | N5: 2015
B6: Jan | C6: 27.464032 | D6: 27.998711 | E6: 27.831058 | F6: 28.890165 | G6: 29.79685 | H6: 29.951744 | I6: 27.983759 | J6: 28.3263 | K6: 29.360267 | L6: 28.66 | M6: 28.58 | N6: 29.96
B7: Feb | C7: ='LV02.04.2026 cost+ Act.'!C32 -> 27.61 | D7: 28.332372 | E7: 27.763914 | F7: 28.97 | G7: 28.897075 | H7: 29.888329 | I7: 28.328713 | J7: 27.99 | K7: 29.135215 | L7: 29 | M7: 29.1 | N7: 29.91
B8: Mar | C8: ='LV02.04.2026 cost+ Act.'!D32 -> 25.43097 | D8: 26.571255 | E8: 25.857648 | F8: 27.471619 | G8: 27.259585 | H8: 27.528401 | I8: 26.064775 | J8: 26.122664 | K8: 27.29331 | L8: 27.49 | M8: 28.3 | N8: 27.351603
B9: Apr | C9: ='LV02.04.2026 cost+ Act.'!E32 -> 22.227507 | D9: 23.546041 | E9: 23.014333 | F9: 23.549197 | G9: 25.455601 | H9: 24.752392 | I9: 22.982705 | J9: 23.57 | K9: 25.585359 | L9: 25.4 | M9: 25.24 | N9: 25.819486
B10: May | C10: ='LV02.04.2026 cost+ Act.'!F32 -> 21.551429 | D10: 20.654164 | E10: 18.614028 | F10: 20.110915 | G10: 22.712972 | H10: 21.841452 | I10: 21.197042 | J10: 20.38 | K10: 24.154912 | L10: 23.99 | M10: 21.2 | N10: 23.81
B11: Jun | C11: ='LV02.04.2026 cost+ Act.'!G32 -> 21.496429 | D11: 20.603923 | E11: 17.547046 | F11: 18.828485 | G11: 23.336883 | H11: 21.901615 | I11: 19.767931 | J11: 21.13 | K11: 24.529697 | L11: 24.8 | M11: 20.1 | N11: 23.136897
B12: Jul | C12: ='LV02.04.2026 cost+ Act.'!H32 -> 21.995 | D12: 22.594806 | E12: 20.086249 | F12: 22.09855 | G12: 23.962162 | H12: 24.132313 | I12: 21.613157 | J12: 23.39 | K12: 24.902171 | L12: 25.36 | M12: 22.84 | N12: 23.048973
B13: Aug | C13: ='LV02.04.2026 cost+ Act.'!I32 -> 23.5 | D13: 24.402037 | E13: 22.971605 | F13: 23.521527 | G13: 24.758563 | H13: 25.202569 | I13: 23.497326 | J13: 24.4 | K13: 25.398905 | L13: 25.32 | M13: 25.21 | N13: 24.14
B14: Sep | C14: ='LV02.04.2026 cost+ Act.'!J32 -> 24.404286 | D14: 24.325976 | E14: 24.393695 | F14: 23.500475 | G14: 25.502384 | H14: 24.637115 | I14: 24.475376 | J14: 24.18 | K14: 26.36366 | L14: 26 | M14: 26.02 | N14: 25.32228
B15: Oct | C15: ='LV02.04.2026 cost+ Act.'!K32 -> 25.2 | D15: 24.318543 | E15: 24.929827 | F15: 22.977083 | G15: 25.838381 | H15: 25.089759 | I15: 24.952312 | J15: 25.16 | K15: 26.606374 | L15: 25.81 | M15: 26.95 | N15: 25.61
B16: Nov | C16: ='LV02.04.2026 cost+ Act.'!L32 -> 25.7 | D16: 25.291087 | E16: 24.474989 | F16: 24.13544 | G16: 27.695088 | H16: 26.639214 | I16: 26.123322 | J16: 26.13 | K16: 27.142752 | L16: 27.15 | M16: 27.48 | N16: 26.57
B17: Dec | C17: ='LV02.04.2026 cost+ Act.'!M32 -> 27.5 | D17: 26.88498 | E17: 26.427034 | F17: 26.922452 | G17: 28.171766 | H17: 28.718051 | I17: 28.293256 | J17: 27.34 | K17: 27.941427 | L17: 28.85 | M17: 28.39 | N17: 28.07
B18: YTD | C18: ='LV02.04.2026 cost+ Act.'!N32 -> 24.317285 | D18: 24.261657 | E18: 23.134132 | F18: 24.01466 | G18: 25.909621 | H18: 25.501995 | I18: 24.233087 | J18: 24.603335 | K18: 26.408333 | L18: 26.389148 | M18: 25.44 | N18: 25.82
E20: Apr-May : El Niño Jun-Aug : La Niña | F20: Drought | G20: Continue rain | H20: Flooding | I20: Co-vid19 | J20: Drought/CMD | K20: Crisis /Drought /CMD | L20: Senka - Flooding | M20: Drought
B21: Price (THB./Kg.)
B22: Month | C22: 2026 | D22: 2025 | E22: 2024 | F22: 2023 | G22: 2022 | H22: 2021 | I22: 2020 | J22: 2019 | K22: 2018 | L22: 2017 | M22: 2016 | N22: 2015
B23: Jan | C23: 2.9210987 | D23: 2.5153376 | E23: 3.9841768 | F23: 3.2305394 | G23: 2.8289854 | H23: 2.3969436 | I23: 2.512711 | J23: 2.7280059 | K23: 2.696913 | L23: 1.7575173 | M23: 2.3450617 | N23: 2.6225755
B24: Feb | C24: ='LV02.04.2026 cost+ Act.'!C33 -> 2.95 | D24: 2.4836266 | E24: 3.9021217 | F24: 3.3178 | G24: 2.7485421 | H24: 2.3849143 | I24: 2.4262581 | J24: 2.6591785 | K24: 2.7929384 | L24: 1.7066414 | M24: 2.2563447 | N24: 2.4865813
B25: Mar | C25: ='LV02.04.2026 cost+ Act.'!D33 -> 2.8933837 | D25: 2.0868943 | E25: 3.7081954 | F25: 3.7138849 | G25: 2.7082811 | H25: 2.329964 | I25: 2.2763665 | J25: 2.5430463 | K25: 2.9580896 | L25: 1.616567 | M25: 2.2148608 | N25: 2.3369921
B26: Apr | C26: ='LV02.04.2026 cost+ Act.'!E33 -> 3.2285971 | D26: 1.9090338 | E26: 3.1475714 | F26: 3.7531813 | G26: 2.9025793 | H26: 2.4755762 | I26: 2.0372725 | J26: 2.4857329 | K26: 3.2826207 | L26: 1.4814408 | M26: 2.1353644 | N26: 2.4051347
B27: May | C27: ='LV02.04.2026 cost+ Act.'!F33 -> 3.005 | D27: 1.7086305 | E27: 2.5878252 | F27: 3.1862869 | G27: 2.831493 | H27: 2.2663244 | I27: 2.0589458 | J27: 2.0472088 | K27: 3.0082832 | L27: 1.4697588 | M27: 1.8874036 | N27: 2.2677044
B28: Jun | C28: ='LV02.04.2026 cost+ Act.'!G33 -> 3.0014286 | D28: 1.7616423 | E28: 2.1395366 | F28: 2.7686582 | G28: 2.8998355 | H28: 2.099712 | I28: 1.9367071 | J28: 1.9603276 | K28: 2.7831103 | L28: 1.4530547 | M28: 1.7727738 | N28: 2.3333356
B29: Jul | C29: ='LV02.04.2026 cost+ Act.'!H33 -> 2.9785714 | D29: 1.9924686 | E29: 2.2800426 | F29: 2.9913696 | G29: 2.9728337 | H29: 2.2225414 | I29: 2.0233899 | J29: 2.0328453 | K29: 2.7763127 | L29: 1.5712545 | M29: 1.7685839 | N29: 2.3649371
B30: Aug | C30: ='LV02.04.2026 cost+ Act.'!I33 -> 3.0085714 | D30: 2.10573 | E30: 2.2553393 | F30: 2.9003964 | G30: 2.9757138 | H30: 2.2592082 | I30: 2.0236813 | J30: 2.0770868 | K30: 2.6944052 | L30: 1.5526732 | M30: 1.6862067 | N30: 2.2677514
B31: Sep | C31: ='LV02.04.2026 cost+ Act.'!J33 -> 2.9985714 | D31: 2.1321625 | E31: 2.4102102 | F31: 3.069449 | G31: 3.060559 | H31: 2.4908174 | I31: 1.9738633 | J31: 1.9726167 | K31: 2.9078292 | L31: 1.8559301 | M31: 1.5321458 | N31: 2.2959791
B32: Oct | C32: ='LV02.04.2026 cost+ Act.'!K33 -> 3.0628571 | D32: 2.271931 | E32: 2.3921655 | F32: 3.2552228 | G32: 3.0786552 | H32: 2.565396 | I32: 2.132983 | J32: 2.2519283 | K32: 3.0302824 | L32: 2.0837522 | M32: 1.3423228 | N32: 2.3608616
B33: Nov | C33: ='LV02.04.2026 cost+ Act.'!L33 -> 3.1328571 | D33: 2.6044364 | E33: 2.7203163 | F33: 3.8225022 | G33: 3.2549139 | H33: 2.8182062 | I33: 2.3789096 | J33: 2.5578976 | K33: 3.1416663 | L33: 2.4760928 | M33: 1.7800996 | N33: 2.5234369
B34: Dec | C34: ='LV02.04.2026 cost+ Act.'!M33 -> 3.2166667 | D34: 2.271931 | E34: 2.5166382 | F34: 3.9160598 | G34: 3.160716 | H34: 2.7679215 | I34: 2.4757573 | J34: 2.5024061 | K34: 2.8384839 | L34: 2.6095655 | M34: 1.7629543 | N34: 2.4857577
B35: YTD | C35: ='LV02.04.2026 cost+ Act.'!N33 -> 3.0297179 | D35: 2.1560263 | E35: 2.7456244 | F35: 3.3078485 | G35: 2.9542224 | H35: 2.4156792 | I35: 2.1673515 | J35: 2.2988835 | K35: 2.9087505 | L35: 1.8047401 | M35: 1.8609758 | N35: 2.3840134
B38: PPDS (THB./Kg.)
B39: Month | C39: 2026 | D39: 2025 | E39: 2024 | F39: 2023 | G39: 2022 | H39: 2021 | I39: 2020 | J39: 2019 | K39: 2018 | L39: 2017 | M39: 2016 | N39: 2015
B40: Jan | C40: 10.636088 | D40: 8.9837623 | E40: 14.315578 | F40: 11.182142 | G40: 9.4942433 | H40: 8.0026845 | I40: 8.97 | J40: 9.630647 | K40: 9.1855873 | L40: 6.1318817 | M40: 8.2055733 | N40: 8.7545334
B41: Feb | C41: ='LV02.04.2026 cost+ Act.'!C34 -> 10.67 | D41: 8.7660383 | E41: 14.054653 | F41: 11.452537 | G41: 9.5114891 | H41: 7.9794168 | I41: 8.5646605 | J41: 9.5009204 | K41: 9.5861258 | L41: 5.8854481 | M41: 7.7531671 | N41: 8.3136127
B42: Mar | C42: ='LV02.04.2026 cost+ Act.'!D34 -> 11.377402 | D42: 7.8539546 | E42: 14.340807 | F42: 13.518988 | G42: 9.9351516 | H42: 8.4638552 | I42: 8.7334975 | J42: 9.7350193 | K42: 10.838149 | L42: 5.8794964 | M42: 7.8255764 | N42: 8.5442599
B43: Apr | C43: ='LV02.04.2026 cost+ Act.'!E34 -> 14.525232 | D43: 8.1076634 | E43: 13.67657 | F43: 15.937619 | G43: 11.402517 | H43: 10.001362 | I43: 8.8643722 | J43: 10.547872 | K43: 12.830075 | L43: 5.8329211 | M43: 8.4601465 | N43: 9.3151919
B44: May | C44: ='LV02.04.2026 cost+ Act.'!F34 -> 13.943391 | D44: 8.2725715 | E44: 13.902553 | F44: 15.84357 | G44: 12.466413 | H44: 10.376254 | I44: 9.7133636 | J44: 10.045914 | K44: 12.454126 | L44: 6.125333 | M44: 8.9015293 | N44: 9.5257509
B45: Jun | C45: ='LV02.04.2026 cost+ Act.'!G34 -> 13.962452 | D45: 8.5500334 | E45: 12.193144 | F45: 14.704626 | G45: 12.425976 | H45: 9.587019 | I45: 9.7972168 | J45: 9.2765628 | K45: 11.345881 | L45: 5.8586964 | M45: 8.8202944 | N45: 10.084911
B46: Jul | C46: ='LV02.04.2026 cost+ Act.'!H34 -> 13.542039 | D46: 8.8182593 | E46: 11.351262 | F46: 13.536497 | G46: 12.406366 | H46: 9.2098151 | I46: 9.3618435 | J46: 8.6915985 | K46: 11.148878 | L46: 6.194575 | M46: 7.7443349 | N46: 10.260488
B47: Aug | C47: ='LV02.04.2026 cost+ Act.'!I34 -> 12.802432 | D47: 8.6293209 | E47: 9.817944 | F47: 12.330817 | G47: 12.018928 | H47: 8.9641981 | I47: 8.6123899 | J47: 8.5110949 | K47: 10.608352 | L47: 6.1349235 | M47: 6.6886556 | N47: 9.3958888
B48: Sep | C48: ='LV02.04.2026 cost+ Act.'!J34 -> 12.287069 | D48: 8.7649617 | E48: 9.8804641 | F48: 13.061221 | G48: 12.00107 | H48: 10.110021 | I48: 8.0646905 | J48: 8.156436 | K48: 11.029687 | L48: 7.1391586 | M48: 5.8852706 | N48: 9.0670316
B49: Oct | C49: ='LV02.04.2026 cost+ Act.'!K34 -> 12.154195 | D49: 9.3423812 | E49: 9.595596 | F49: 14.167259 | G49: 11.915047 | H49: 10.224873 | I49: 8.5482381 | J49: 8.9517903 | K49: 11.38931 | L49: 8.0728121 | M49: 4.9800614 | N49: 9.2185146
B50: Nov | C50: ='LV02.04.2026 cost+ Act.'!L34 -> 12.190106 | D50: 10.297843 | E50: 11.114678 | F50: 15.837715 | G50: 11.752676 | H50: 10.579165 | I50: 9.106459 | J50: 9.8 | K50: 11.574605 | L50: 9.1211029 | M50: 6.4783216 | N50: 9.4990662
B51: Dec | C51: ='LV02.04.2026 cost+ Act.'!M34 -> 11.69697 | D51: 10.103045 | E51: 9.5229686 | F51: 14.545703 | G51: 11.219445 | H51: 9.6382637 | I51: 8.7503442 | J51: 9.15 | K51: 10.158694 | L51: 9.0443853 | M51: 6.2102758 | N51: 8.8545296
B52: YTD | C52: ='LV02.04.2026 cost+ Act.'!N34 -> 12.459113 | D52: 8.8865582 | E52: 11.868284 | F52: 13.774288 | G52: 11.402029 | H52: 9.4725108 | I52: 8.94377 | J52: 9.3437882 | K52: 11.01528 | L52: 6.8389481 | M52: 7.3165554 | N52: 9.2336583
B55: Farmer contribution of regular root at SK plant, %
B56: Month | C56: 2026 | D56: 2025 | E56: 2024 | F56: 2023 | G56: 2022 | H56: 2021 | I56: 2020 | J56: 2019 | K56: 2018 | L56: 2017 | M56: 2016 | N56: 2015
B57: Jan | C57: 10.57 | D57: 26.020579 | E57: 69.339878 | F57: 68.136574 | G57: 84.778691 | H57: 78.688163 | I57: 27.892768 | J57: 17.740651 | K57: 38.689062 | L57: 56.212159 | M57: 51.775788 | N57: 30.616133
B58: Feb | C58: 18.87 | D58: 55.853785 | E58: 76.470507 | F58: 77.6185 | G58: 76.37863 | H58: 88.42015 | I58: 44.647872 | J58: 13.512094 | K58: 30.841158 | L58: 55.636166 | M58: 69.529069 | N58: 43.364086
B59: Mar | C59: 34.322823 | D59: 77.309779 | E59: 90.977269 | F59: 42.815167 | G59: 66.5585 | H59: 68.837247 | I59: 49.852754 | J59: 20.37505 | K59: 25.044026 | L59: 54.191796 | M59: 64.139023 | N59: 43.314017
B60: Apr | D60: 50.708786 | E60: 79.435154 | F60: 28.970003 | G60: 46.698452 | H60: 54.076806 | I60: 36.568304 | J60: 38.078154 | K60: 28.504595 | L60: 64.272442 | M60: 67.972329 | N60: 30.604728
B61: May | D61: 41.506825 | E61: 60.068662 | F61: 55.569329 | G61: 54.294376 | H61: 43.386557 | I61: 20.911684 | J61: 49.34606 | K61: 28.219186 | L61: 51.031357 | M61: 51.087313 | N61: 32.204449
B62: Jun | D62: 38.36113 | E62: 36.977906 | F62: 59.221641 | G62: 64.590382 | H62: 63.639104 | I62: 33.892406 | J62: 54.738553 | K62: 45.644729 | L62: 61.420393 | M62: 51.373057 | N62: 47.401981
A63: Peak sesonal of KSN plant | B63: Jul | D63: 60.948308 | E63: 67.050972 | F63: 82.238402 | G63: 76.948121 | H63: 66.97671 | I63: 57.391837 | J63: 69.67791 | K63: 56.669354 | L63: 66.673528 | M63: 76.611994 | N63: 63.850183
B64: Aug | D64: 75.130332 | E64: 100 | F64: 87.810125 | G64: 75.588569 | H64: 57.788024 | I64: 84.161736 | J64: 73.932597 | K64: 57.726616 | L64: 69.344304 | M64: 82.812148 | N64: 92.342806
B65: Sep | D65: 76.180084 | E65: 98.620512 | F65: 81.41399 | G65: 56.894888 | H65: 38.955649 | I65: 76.547883 | J65: 64.773156 | K65: 43.444956 | L65: 31.498367 | M65: 78.109833 | N65: 58.436764
B66: Oct | D66: 28.099128 | E66: 74.692544 | F66: 46.372638 | G66: 45.160891 | H66: 44.014381 | I66: 58.275568 | J66: 15.103931 | K66: 20.8173 | L66: 15.189388 | M66: 80.194464 | N66: 26.093794
B67: Nov | D67: 5.1344728 | E67: 13.749954 | F67: 20.976876 | G67: 25.06179 | H67: 33.605386 | I67: 28.98858 | J67: 4.9917289 | K67: 3.9289739 | L67: 9.1396424 | M67: 13.951113 | N67: 6.4615484
B68: Dec | D68: 13.807588 | E68: 26.363888 | F68: 48.532557 | G68: 52.187976 | H68: 61.081344 | I68: 58.855847 | J68: 15 | K68: 16.191194 | L68: 53.428835 | M68: 61.379571 | N68: 38.898932
B69: YTD | C69: 20.857396 | D69: 46.119354 | E69: 65.16379 | F69: 58.821456 | G69: 59.472795 | H69: 56.719009 | I69: 47.446592 | J69: 36.893717 | K69: 33.431493 | L69: 48.439675 | M69: 62.276778 | N69: 44.05415

Sheet Summary plan 11.02.26
B2: Day operation | E2: 27 | F2: 28 | G2: 31 | H2: 24 | I2: 31 | J2: 30 | K2: 30 | L2: 31 | M2: 31 | N2: 31 | O2: 30 | P2: 26
B3: Average Regular Root Grinding/day in period no Grind Waxy | E3: 1340 | F3: 1390 | G3: 1700 | H3: 1650 | I3: 1650 | J3: 1500 | K3: 1400 | L3: 1400 | M3: 1400 | N3: 1400 | O3: 1400 | P3: 1400
E4: Actual | F4: Actual | G4: Plan | H4: Plan | I4: Plan | J4: Plan | K4: Plan | L4: Plan | M4: Plan | N4: Plan | O4: Plan | P4: Plan
B5: Quarter | E5: Q1 | H5: Q2 | K5: Q3 | N5: Q4
B6: Month | D6: UOM | E6: Jan | F6: Feb | G6: Mar | H6: Apr | I6: May | J6: Jun | K6: Jul | L6: Aug | M6: Sep | N6: Oct | O6: Nov | P6: Dec | Q6: TOTAL | S6: LE0 2026 | T6: 12.2025 | U6: 01.2026 vs LE0 2026 | V6: 01.2026 vs 12.2025
B7: Regular Root Grinding Volume | D7: MT | E7: =[64]Daily!AH16 -> 29398 | F7: =[64]Daily!BK16 -> 34554 | G7: =[64]Daily!CQ16 -> 48100 | H7: =[64]Daily!DV16 -> 30050 | I7: =[64]Daily!FB16 -> 47700 | J7: =[64]Daily!GG16 -> 42300 | K7: =[64]Daily!HM16 -> 41800 | L7: =[64]Daily!IS16 -> 41700 | M7: =[64]Daily!JX16 -> 39700 | N7: =[64]Daily!LD16 -> 38700 | O7: =[64]Daily!MI16 -> 37350 | P7: =[64]Daily!NO16 -> 30600 | Q7: =SUM(E7:P7) -> 461952 | S7: 445200 | T7: 443121 | U7: =Q7-S7 -> 16752 | V7: =Q7-T7 -> 18831
B8: Average Regular Root Grinding | D8: MT | E8: =[64]Daily!AH21 -> 1088.8148 | F8: =[64]Daily!BK21 -> 1234.0714 | G8: =[64]Daily!CQ21 -> 1551.6129 | H8: =[64]Daily!DV21 -> 1252.0833 | I8: =[64]Daily!FB21 -> 1538.7097 | J8: =[64]Daily!GG21 -> 1410 | K8: =[64]Daily!HM21 -> 1348.3871 | L8: =[64]Daily!IS21 -> 1345.1613 | M8: =[64]Daily!JX21 -> 1323.3333 | N8: =[64]Daily!LD21 -> 1248.3871 | O8: =[64]Daily!MI21 -> 1245 | P8: =[64]Daily!NO21 -> 1176.9231 | Q8: =AVERAGE(E8:P8) -> 1313.5403 | S8: 1271.0071 | T8: 1264.4249 | U8: =Q8-S8 -> 42.533236 | V8: =Q8-T8 -> 49.115424
B9: Regular PPDS | D9: THB/kg | E9: =[64]Daily!AH20 -> 10.41 | F9: =[64]Daily!BK20 -> 10.45 | G9: =[64]Daily!CQ20 -> 10.77 | H9: =[64]Daily!DV20 -> 10.13 | I9: =[64]Daily!FB20 -> 10.74 | J9: =[64]Daily!GG20 -> 10.63 | K9: =[64]Daily!HM20 -> 10.54 | L9: =[64]Daily!IS20 -> 9.81 | M9: =[64]Daily!JX20 -> 9.66 | N9: =[64]Daily!LD20 -> 9.66 | O9: =[64]Daily!MI20 -> 9.81 | P9: =[64]Daily!NO20 -> 9.63 | U9: =Q9-S9 -> 0 | V9: =Q9-T9 -> 0
B10: Waxy Root Grinding Volume | D10: MT | E10: =[64]Daily!AH24 -> 2720 | F10: =[64]Daily!BK24 -> 2850 | G10: =[64]Daily!CQ24 -> 2000 | H10: =[64]Daily!DV24 -> 1665 | I10: =[64]Daily!FB24 -> 1500 | J10: =[64]Daily!GG24 -> 1225 | K10: =[64]Daily!HM24 -> 900 | L10: =[64]Daily!IS24 -> 900 | M10: =[64]Daily!JX24 -> 1500 | N10: =[64]Daily!LD24 -> 3000 | O10: =[64]Daily!MI24 -> 3000 | P10: =[64]Daily!NO24 -> 3000 | Q10: =SUM(E10:P10) -> 24260 | S10: 23876 | T10: 26990 | U10: =Q10-S10 -> 384 | V10: =Q10-T10 -> -2730
B11: GLUCOSE - Sales | D11: MT | E11: =[64]Daily!AH99 -> 5234 | F11: =[64]Daily!BK99 -> 5821 | G11: =[64]Daily!CQ99 -> 6016 | H11: =[64]Daily!DV99 -> 5150 | I11: =[64]Daily!FB99 -> 5343 | J11: =[64]Daily!GG99 -> 5268 | K11: =[64]Daily!HM99 -> 5859 | L11: =[64]Daily!IS99 -> 5572 | M11: =[64]Daily!JX99 -> 5624 | N11: =[64]Daily!LD99 -> 5655 | O11: =[64]Daily!MI99 -> 5453 | P11: =[64]Daily!NO99 -> 5307 | Q11: =SUM(E11:P11) -> 66302 | S11: 66285.5 | T11: 64945.278 | U11: =Q11-S11 -> 16.5 | V11: =Q11-T11 -> 1356.722
B12: HMS - Sales | D12: MT | E12: =[64]Daily!AH108 -> 570 | F12: =[64]Daily!BK108 -> 600 | G12: =[64]Daily!CQ108 -> 991 | H12: =[64]Daily!DV108 -> 744 | I12: =[64]Daily!FB108 -> 594 | J12: =[64]Daily!GG108 -> 499 | K12: =[64]Daily!HM108 -> 504 | L12: =[64]Daily!IS108 -> 503 | M12: =[64]Daily!JX108 -> 559 | N12: =[64]Daily!LD108 -> 708 | O12: =[64]Daily!MI108 -> 799 | P12: =[64]Daily!NO108 -> 805 | Q12: =SUM(E12:P12) -> 7876 | S12: 8220.3 | T12: 8015.658 | U12: =Q12-S12 -> -344.3 | V12: =Q12-T12 -> -139.658
B13: Total Glucose & HMS - Sales | D13: MT | E13: =E11+E12 -> 5804 | F13: =F11+F12 -> 6421 | G13: =G11+G12 -> 7007 | H13: =H11+H12 -> 5894 | I13: =I11+I12 -> 5937 | J13: =J11+J12 -> 5767 | K13: =K11+K12 -> 6363 | L13: =L11+L12 -> 6075 | ... P13: =P11+P12 -> 6112 | Q13: =SUM(E13:P13) -> 74178 | S13: 74505.8 | T13: 72960.936 | U13: =Q13-S13 -> -327.8 | V13: =Q13-T13 -> 1217.064
B14: Stock Glucose Ending | D14: MT | E14: =[64]Daily!AH114 -> 973 | F14: =[64]Daily!BK114 -> 977 | G14: =[64]Daily!CQ114 -> 1070 | H14: =[64]Daily!DV114 -> 1076 | I14: =[64]Daily!FB114 -> 1139 | J14: =[64]Daily!GG114 -> 972 | K14: =[64]Daily!HM114 -> 1009 | L14: =[64]Daily!IS114 -> 1034 | M14: =[64]Daily!JX114 -> 1051 | N14: =[64]Daily!LD114 -> 988 | O14: =[64]Daily!MI114 -> 1036 | P14: =[64]Daily!NO114 -> 1324 | U14: =Q14-S14 -> 0 | V14: =Q14-T14 -> 0
B15: REGULAR STARCH - Production | D15: MT | E15: =[64]Daily!AH146 -> 2523.9 | F15: =[64]Daily!BK146 -> 3004.85 | G15: =[64]Daily!CQ146 -> 4735.7175 | H15: =[64]Daily!DV146 -> 1550.7561 | I15: =[64]Daily!FB146 -> 4083.0888 | J15: =[64]Daily!GG146 -> 3510.006 | K15: =[64]Daily!HM146 -> 3113.5464 | L15: =[64]Daily!IS146 -> 3915.3907 | M15: =[64]Daily!JX146 -> 3620.8961 | N15: =[64]Daily!LD146 -> 3426.5833 | O15: =[64]Daily!MI146 -> 3301.8737 | P15: =[64]Daily!NO146 -> 1706.2178 | Q15: =SUM(E15:P15) -> 38492.826 | S15: 33406.027 | T15: 35527.782 | U15: =Q15-S15 -> 5086.7994 | V15: =Q15-T15 -> 2965.0445
B16: REGULAR STARCH - in-house total Sales | D16: MT | E16: =[64]Daily!AH157 -> 2029.13 | F16: =[64]Daily!BK157 -> 4617.24 | G16: =[64]Daily!CQ157 -> 2987.83 | H16: =[64]Daily!DV157 -> 2160 | I16: =[64]Daily!FB157 -> 3984 | J16: =[64]Daily!GG157 -> 3365 | K16: =[64]Daily!HM157 -> 3078 | L16: =[64]Daily!IS157 -> 3733 | M16: =[64]Daily!JX157 -> 3758 | N16: =[64]Daily!LD157 -> 2878 | O16: =[64]Daily!MI157 -> 2310 | P16: =[64]Daily!NO157 -> 2704 | Q16: =SUM(E16:P16) -> 37604.2 | S16: 36370.34 | T16: 37042.352 | U16: =Q16-S16 -> 1233.86 | V16: =Q16-T16 -> 561.848
B17: REGULAR STARCH - 3P Export Sales | D17: MT | E17: =[64]Daily!AH152 -> 1094 | F17: =[64]Daily!BK152 -> 2116 | G17: =[64]Daily!CQ152 -> 1222 | H17: =[64]Daily!DV152 -> 1325 | I17: =[64]Daily!FB152 -> 1253 | J17: =[64]Daily!GG152 -> 1314 | K17: =[64]Daily!HM152 -> 1437 | L17: =[64]Daily!IS152 -> 1259 | M17: =[64]Daily!JX152 -> 1380 | N17: =[64]Daily!LD152 -> 1338 | O17: =[64]Daily!MI152 -> 1069 | P17: =[64]Daily!NO152 -> 1302 | Q17: =SUM(E17:P17) -> 16109 | S17: 15676.8 | T17: 15195.075 | U17: =Q17-S17 -> 432.2 | V17: =Q17-T17 -> 913.925
B18: REGULAR STARCH - 3P Domestic Sales | D18: MT | E18: =[64]Daily!AH153 -> 189 | F18: =[64]Daily!BK153 -> 197 | G18: =[64]Daily!CQ153 -> 278 | H18: =[64]Daily!DV153 -> 225 | I18: =[64]Daily!FB153 -> 265 | J18: =[64]Daily!GG153 -> 223 | K18: =[64]Daily!HM153 -> 212 | L18: =[64]Daily!IS153 -> 212 | M18: =[64]Daily!JX153 -> 215 | N18: =[64]Daily!LD153 -> 246 | O18: =[64]Daily!MI153 -> 256 | P18: =[64]Daily!NO153 -> 237 | Q18: =SUM(E18:P18) -> 2755 | S18: 2431.58 | T18: 2425.594 | U18: =Q18-S18 -> 323.42 | V18: =Q18-T18 -> 329.406
B19: REGULAR STARCH - Sales Network Optimize | D19: MT | E19: =[64]Daily!AH154 -> 0 | F19: =[64]Daily!BK154 -> 180 | G19: =[64]Daily!CQ154 -> 50 | H19: =[64]Daily!DV154 -> 330 | I19: =[64]Daily!FB154 -> 480 | J19: =[64]Daily!GG154 -> 270 | K19: =[64]Daily!HM154 -> 320 | L19: =[64]Daily!IS154 -> 490 | M19: =[64]Daily!JX154 -> 370 | N19: =[64]Daily!LD154 -> 320 | O19: =[64]Daily!MI154 -> 320 | P19: =[64]Daily!NO154 -> 300 | Q19: =SUM(E19:P19) -> 3430 | S19: 3100 | T19: 3315 | U19: =Q19-S19 -> 330 | V19: =Q19-T19 -> 115
B20: REGULAR STARCH - Inco Sales (Export) | D20: MT | E20: =[64]Daily!AH155 -> 746.13 | F20: =[64]Daily!BK155 -> 815.24 | G20: =[64]Daily!CQ155 -> 791.83 | H20: =[64]Daily!DV155 -> 189 | I20: =[64]Daily!FB155 -> 989 | J20: =[64]Daily!GG155 -> 972 | K20: =[64]Daily!HM155 -> 927 | L20: =[64]Daily!IS155 -> 863 | M20: =[64]Daily!JX155 -> 884 | N20: =[64]Daily!LD155 -> 974 | O20: =[64]Daily!MI155 -> 665 | P20: =[64]Daily!NO155 -> 865 | Q20: =SUM(E20:P20) -> 9681.2 | S20: 9001.96 | T20: 9814.683 | U20: =Q20-S20 -> 679.24 | V20: =Q20-T20 -> -133.483
B21: REGULAR STARCH - ISD Jumbo | D21: MT | E21: =[64]Daily!AH156 -> 0 | F21: =[64]Daily!BK156 -> 1309 | G21: =[64]Daily!CQ156 -> 646 | H21: =[64]Daily!DV156 -> 91 | I21: =[64]Daily!FB156 -> 997 | J21: =[64]Daily!GG156 -> 586 | K21: =[64]Daily!HM156 -> 182 | L21: =[64]Daily!IS156 -> 909 | M21: =[64]Daily!JX156 -> 909 | N21: =[64]Daily!LD156 -> 0 | O21: =[64]Daily!MI156 -> 0 | P21: =[64]Daily!NO156 -> 0 | Q21: =SUM(E21:P21) -> 5629 | S21: 6160 | T21: 6292
B22: REGULAR STARCH - END Inv (in-house) | D22: MT | E22: =[64]Daily!AH159 -> 5015.77 | F22: =[64]Daily!BK159 -> 2007.44 | G22: =[64]Daily!CQ159 -> 2725.8175 | H22: =[64]Daily!DV159 -> 2116.5736 | I22: =[64]Daily!FB159 -> 2215.6623 | J22: =[64]Daily!GG159 -> 2360.6683 | K22: =[64]Daily!HM159 -> 2396.2147 | L22: =[64]Daily!IS159 -> 2578.6054 | M22: =[64]Daily!JX159 -> 2441.5015 | N22: =[64]Daily!LD159 -> 2990.0848 | O22: =[64]Daily!MI159 -> 3981.9585 | P22: =[64]Daily!NO159 -> 2984.1763
B23: On hold stock | D23: MT | E23: =SUM([64]Daily!AH160:AH161) -> 485.46 | F23: =SUM([64]Daily!BK160:BK161) -> 672.51 | G23: =SUM([64]Daily!CQ160:CQ161) -> 0 | H23: =SUM([64]Daily!DV160:DV161) -> 0 | I23: =SUM([64]Daily!FB160:FB161) -> 0 | J23: =SUM([64]Daily!GG160:GG161) -> 0 | K23: =SUM([64]Daily!HM160:HM161) -> 0 | L23: =SUM([64]Daily!IS160:IS161) -> 0 | M23: =SUM([64]Daily!JX160:JX161) -> 0 | N23: =SUM([64]Daily!LD160:LD161) -> 0 | O23: =SUM([64]Daily!MI160:MI161) -> 0 | P23: =SUM([64]Daily!NO160:NO161) -> 0
B24: REGULAR STARCH - SALEABLE INVENTORY | D24: MT | E24: =[64]Daily!AH164 -> 3976.83 | F24: =[64]Daily!BK164 -> 977.93 | G24: =[64]Daily!CQ164 -> 2725.8175 | H24: =[64]Daily!DV164 -> 2116.5736 | I24: =[64]Daily!FB164 -> 2215.6623 | J24: =[64]Daily!GG164 -> 2360.6683 | K24: =[64]Daily!HM164 -> 2396.2147 | L24: =[64]Daily!IS164 -> 2578.6054 | M24: =[64]Daily!JX164 -> 2441.5015 | N24: =[64]Daily!LD164 -> 2990.0848 | O24: =[64]Daily!MI164 -> 3981.9585 | P24: =[64]Daily!NO164 -> 2984.1763

Sheet SK MAP - Mar 2026  (2)
B1: Monthly Activities Plan
B3: SK plant : The Root Purchasing of March 2026 (Total Operation Day 31 days)
B4: Root rolling Forecast | C4: Plan Original LE0.2026 | D4: Latest View | E4: Root purchase forecasting | F4: Remarks
C5: (18/12/25) | D5: (19/01/26) | E5: Most likely
B6: Root purchase expectation | C6: 48250 | D6: =E6 -> 33527.15 | E6: =F13 -> 33527.15 | M6: Number of Days | N6: 31
B7: Starch content forecasting | C7: 0.262 | D7: =E7 -> 0.2563015 | E7: =G13/100 -> 0.2563015 | M7: Volume Plan | N7: ='LV02.04.2026 cost+ Act.'!D9 -> 33527.15
B8: Root price forecasting | C8: 2.45 | D8: =E8 -> 2.8705527 | E8: =H13 -> 2.8705527 | M8: Farmer Daily supply | N8: 400
B9: PPDS. Forecasting | C9: 10.11 | D9: =E9 -> 11.199906 | E9: =I13 -> 11.199906
B10: Expectation of root source purchasing. | E10: Farmer % of supply | F10: Volume/month | G10: Starch (%) | H10: Price(B./kg) | I10: PPDS (B./kg) | J10: Root expense amount (K baht)
B11: Farmer | E11: =F11/E6 -> 0.36984951 | F11: =N6*N8 -> 12400 | G11: 25 | H11: 2.65 | I11: =(H11/G11)*100 -> 10.6 | J11: =H11*F11 -> 32860 | M11: F : 25% | N11: 2.65
B12: Broker | E12: =100%-E11 -> 0.63015049 | F12: =N7-F11 -> 21127.15 | G12: 26 | H12: 3 | I12: =(H12/G12)*100 -> 11.538462 | J12: =H12*F12 -> 63381.45 | M12: B : 25% | N12: 2.95
B13: Total | E13: =SUM(E11:E12) -> 1 | F13: =SUM(F11:F12) -> 33527.15 | G13: =SUMPRODUCT($E$11:$E$12,G11:G12) -> 25.63015 | H13: =SUMPRODUCT($E$11:$E$12,H11:H12) -> 2.8705527 | I13: =(H13/G13)*100 -> 11.199906 | J13: =SUM(J11:J12) -> 96241.45
B15: Expectation of Co-products | E15: Portion to root grinding | F15: Volume (tons) | G15: Unit price (baht) | H15: Total revenue (baht)
B16: Wash skin | E16: 0.02 | F16: =E6*E16 -> 670.543 | G16: 0.2 | H16: =G16*F16*1000 -> 134108.6
B17: Soil skin | E17: 0.061 | F17: =E6*E17 -> 2045.1562 | G17: 0.03 | H17: =G17*F17*1000 -> 61354.684
B18: Pulp with 79% moisture content | E18: 0.2 | F18: =E6*E18 -> 6705.43 | G18: 0.282 | H18: =G18*F18*1000 -> 1890931.3
G19: Total
B22: Activities | C22: Response | E22: Target | H22: Budget | J22: Remarks
B23: Farmers-broker visit & | C23: Buyer | E23: Continuous root supply through year. | H23: 15000 | J23: - Farmer-Broker
B24: meeting expense for | J24: visit budget
B25: Root Sourcing department
E26: Total | H26: =SUM(H23:H25) -> 15000
B42: หมายเหตุ : กรณีไม่มีการเซ็นอนุมัติในแบบฟอร์ม ให้แนบเป็นอีเมลล์อนุมัติแทนได้

Sheet SK MAP - Mar 2026 _22.02.2026
B1: Monthly Activities Plan
B3: SK plant : The Root Purchasing of March 2026 (Total Operation Day 31 days)
B4: Root rolling Forecast | C4: Plan Original LE0.2026 | D4: Latest View | E4: Root purchase forecasting | F4: Remarks
C5: (18/12/25) | D5: (11/02/26) | E5: Most likely
B6: Root purchase expectation | C6: 48250 | D6: =E6 -> 48100 | E6: =F13 -> 48100 | F6: - Total Volume Plan: 48,100 tons | M6: Number of Days | N6: 31
B7: Starch content forecasting | C7: 0.262 | D7: 0.25742204 | E7: =G13/100 -> 0.26841996 | F7: - Farmer Daily Supply (Non‑Waxy Cassava): ~300 tons/day | M7: Volume Plan | N7: 48100
B8: Root price forecasting | C8: 2.45 | D8: 2.9097713 | E8: =H13 -> 3.0300624 | F8: - Waxy Cassava Root Grinding Plan: 2,000 tons | M8: Farmer Daily supply | N8: 300
B9: PPDS. Forecasting | C9: 10.11 | D9: 11.303505 | E9: =I13 -> 11.288514
B10: Expectation of root source purchasing. | E10: Farmer % of supply | F10: Volume/month | G10: Starch (%) | H10: Price(B./kg) | I10: PPDS (B./kg) | J10: Root expense amount (K baht)
B11: Farmer | E11: =F11/E6 -> 0.19334719 | F11: =N6*N8 -> 9300 | G11: 26.6 | H11: 2.78 | I11: =(H11/G11)*100 -> 10.451128 | J11: =H11*F11 -> 25854 | M11: F : 25% | N11: 2.7
B12: Broker | E12: =100%-E11 -> 0.80665281 | F12: =N7-F11 -> 38800 | G12: 26.9 | H12: 3.09 | I12: =(H12/G12)*100 -> 11.486989 | J12: =H12*F12 -> 119892 | M12: B : 25% | N12: 3
B13: Total | E13: =SUM(E11:E12) -> 1 | F13: =SUM(F11:F12) -> 48100 | G13: =SUMPRODUCT($E$11:$E$12,G11:G12) -> 26.841996 | H13: =SUMPRODUCT($E$11:$E$12,H11:H12) -> 3.0300624 | I13: =(H13/G13)*100 -> 11.288514 | J13: =SUM(J11:J12) -> 145746
B15: Expectation of Co-products | E15: Portion to root grinding | F15: Volume (tons) | G15: Unit price (baht) | H15: Total revenue (baht)
B16: Wash skin | E16: 0.02 | F16: =E6*E16 -> 962 | G16: 0.2 | H16: =G16*F16*1000 -> 192400
B17: Soil skin | E17: 0.061 | F17: =E6*E17 -> 2934.1 | G17: 0.03 | H17: =G17*F17*1000 -> 88023
B18: Pulp with 79% moisture content | E18: 0.2 | F18: =E6*E18 -> 9620 | G18: 0.282 | H18: =G18*F18*1000 -> 2712840
G19: Total
B22: Activities | C22: Response | E22: Target | H22: Budget | J22: Remarks
B23: Farmers-broker visit & | C23: Buyer | E23: Continuous root supply through year. | H23: 15000 | J23: - Farmer-Broker
B24: meeting expense for | J24: visit budget
B25: Root Sourcing department
E26: Total | H26: =SUM(H23:H25) -> 15000
B42: หมายเหตุ : กรณีไม่มีการเซ็นอนุมัติในแบบฟอร์ม ให้แนบเป็นอีเมลล์อนุมัติแทนได้

Sheet SK MAP - Apr 2026 (2)
B1: Monthly Activities Plan
B3: SK plant : The Root Purchasing of April 2026 (Total Operation Day 24 days)
B4: Root rolling Forecast | C4: Plan Original LE0.2026 | D4: Latest View | E4: Root purchase forecasting | F4: Remarks
C5: (18/12/25) | E5: Most likely
B6: Root purchase expectation | E6: =F13 -> 18111.17 | M6: Number of Days | N6: 24
B7: Starch content forecasting | E7: =G13/100 -> 0.22 | M7: Volume Plan | N7: ='LV02.04.2026 cost+ Act.'!E9 -> 18111.17
B8: Root price forecasting | E8: =H13 -> 2.8704911 | M8: Farmer Daily supply | N8: 150
B9: PPDS. Forecasting | E9: =I13 -> 13.047687
B10: Expectation of root source purchasing. | E10: Farmer % of supply | F10: Volume/month | G10: Starch (%) | H10: Price(B./kg) | I10: PPDS (B./kg) | J10: Root expense amount (K baht)
B11: Farmer | E11: =F11/E6 -> 0.19877236 | F11: =N6*N8 -> 3600 | G11: 22 | H11: 2.55 | I11: =(H11/G11)*100 -> 11.590909 | J11: =H11*F11 -> 9180 | M11: F : 25% | N11: 2.7
B12: Broker | E12: =100%-E11 -> 0.80122764 | F12: =N7-F11 -> 14511.17 | G12: 22 | H12: 2.95 | I12: =(H12/G12)*100 -> 13.409091 | J12: =H12*F12 -> 42807.951 | M12: B : 25% | N12: 3.1
B13: Total | E13: =SUM(E11:E12) -> 1 | F13: =SUM(F11:F12) -> 18111.17 | G13: =SUMPRODUCT($E$11:$E$12,G11:G12) -> 22 | H13: =SUMPRODUCT($E$11:$E$12,H11:H12) -> 2.8704911 | I13: =(H13/G13)*100 -> 13.047687 | J13: =SUM(J11:J12) -> 51987.951
B15: Expectation of Co-products | E15: Portion to root grinding | F15: Volume (tons) | G15: Unit price (baht) | H15: Total revenue (baht)
B16: Wash skin | E16: 0.02 | F16: =E6*E16 -> 362.2234 | G16: 0.2 | H16: =G16*F16*1000 -> 72444.68
B17: Soil skin | E17: 0.061 | F17: =E6*E17 -> 1104.7814 | G17: 0.03 | H17: =G17*F17*1000 -> 33143.441
B18: Pulp with 79% moisture content | E18: 0.2 | F18: =E6*E18 -> 3622.234 | G18: 0.282 | H18: =G18*F18*1000 -> 1021470
G19: Total
B22: Activities | C22: Response | E22: Target | H22: Budget | J22: Remarks
B23: Farmers-broker visit & | C23: Buyer | E23: Continuous root supply through year. | H23: 15000 | J23: - Farmer-Broker
B24: meeting expense for | J24: visit budget
B25: Root Sourcing department
E26: Total | H26: =SUM(H23:H25) -> 15000
B42: หมายเหตุ : กรณีไม่มีการเซ็นอนุมัติในแบบฟอร์ม ให้แนบเป็นอีเมลล์อนุมัติแทนได้

Sheet SK MAP - Apr 2026 _ 26.03.2026
B1: Monthly Activities Plan
B3: SK plant : The Root Purchasing of April 2026 (Total Operation Day 24 days)
B4: Root rolling Forecast | C4: Plan Original LE0.2026 | D4: Latest View | E4: Root purchase forecasting | F4: Remarks
C5: (18/12/25) | D5: (11/2/2026) | E5: Most likely
B6: Root purchase expectation | C6: 39135 | D6: 30050 | E6: =F13 -> 29500 | F6: - Reference plan from Planner - 18/3/2026: Regular cassava root plan: 26,900 tons / Waxy cassava root plan: 4,000 tons - According to this month’s projection reference, the industry is facing high competition from starch mills and cassava chip factories, limited root supply, low starch content, and a continuing fuel crisis. - The estimated volume supply from farmers is approximately 75 tons per day. | M6: Number of Days | N6: 24
B7: Starch content forecasting | C7: 0.242 | D7: 0.22 | E7: =G13/100 -> 0.21969492 | M7: Volume Plan | N7: 29500
B8: Root price forecasting | C8: 2.51 | D8: 2.9020799 | E8: =H13 -> 3.0755932 | M8: Farmer Daily supply | N8: 75
B9: PPDS. Forecasting | C9: 10.371901 | D9: 13.191272 | E9: =I13 -> 13.999383
B10: Expectation of root source purchasing. | E10: Farmer % of supply | F10: Volume/month | G10: Starch (%) | H10: Price(B./kg) | I10: PPDS (B./kg) | J10: Root expense amount (K baht)
B11: Farmer | E11: =F11/E6 -> 0.061016949 | F11: =N6*N8 -> 1800 | G11: 21.5 | H11: 2.7 | I11: =(H11/G11)*100 -> 12.55814 | J11: =H11*F11 -> 4860 | M11: F : 25% | N11: 2.85
B12: Broker | E12: =100%-E11 -> 0.93898305 | F12: =N7-F11 -> 27700 | G12: 22 | H12: 3.1 | I12: =(H12/G12)*100 -> 14.090909 | J12: =H12*F12 -> 85870 | M12: B : 25% | N12: 3.25
B13: Total | E13: =SUM(E11:E12) -> 1 | F13: =SUM(F11:F12) -> 29500 | G13: =SUMPRODUCT($E$11:$E$12,G11:G12) -> 21.969492 | H13: =SUMPRODUCT($E$11:$E$12,H11:H12) -> 3.0755932 | I13: =(H13/G13)*100 -> 13.999383 | J13: =SUM(J11:J12) -> 90730
B15: Expectation of Co-products | E15: Portion to root grinding | F15: Volume (tons) | G15: Unit price (baht) | H15: Total revenue (baht)
B16: Wash skin | G16: 0.25
B17: Soil skin | G17: 0.03
B18: Pulp with 79% moisture content | G18: 0.352
G19: Total
B22: Activities | C22: Response | E22: Target | H22: Budget | J22: Remarks
E26: Total | H26: =SUM(H23:H25) -> 0
B42: หมายเหตุ : กรณีไม่มีการเซ็นอนุมัติในแบบฟอร์ม ให้แนบเป็นอีเมลล์อนุมัติแทนได้

Sheet SK MAP - May 2026 (2)
B1: Monthly Activities Plan
B3: SK plant : The Root Purchasing of May 2026 (Total Operation Day 31 days)
B4: Root rolling Forecast | C4: Plan Original LE0.2026 | D4: Latest View | E4: Root purchase forecasting | F4: Remarks
C5: (18/12/25) | E5: Most likely
B6: Root purchase expectation | E6: =F13 -> 39250 | M6: Number of Days | N6: 31
B7: Starch content forecasting | E7: =G13/100 -> 0.20421019 | M7: Volume Plan | N7: ='LV02.04.2026 cost+ Act.'!F9 -> 39250
B8: Root price forecasting | E8: =H13 -> 2.8078662 | M8: Farmer Daily supply | N8: 200
B9: PPDS. Forecasting | E9: =I13 -> 13.749883
B10: Expectation of root source purchasing. | E10: Farmer % of supply | F10: Volume/month | G10: Starch (%) | H10: Price(B./kg) | I10: PPDS (B./kg) | J10: Root expense amount (K baht)
B11: Farmer | E11: =F11/E6 -> 0.15796178 | F11: =N6*N8 -> 6200 | G11: 20 | H11: 2.45 | I11: =(H11/G11)*100 -> 12.25 | J11: =H11*F11 -> 15190 | M11: F : 25% | N11: 2.7
B12: Broker | E12: =100%-E11 -> 0.84203822 | F12: =N7-F11 -> 33050 | G12: 20.5 | H12: 2.875 | I12: =(H12/G12)*100 -> 14.02439 | J12: =H12*F12 -> 95018.75 | M12: B : 25% | N12: 3.1
B13: Total | E13: =SUM(E11:E12) -> 1 | F13: =SUM(F11:F12) -> 39250 | G13: =SUMPRODUCT($E$11:$E$12,G11:G12) -> 20.421019 | H13: =SUMPRODUCT($E$11:$E$12,H11:H12) -> 2.8078662 | I13: =(H13/G13)*100 -> 13.749883 | J13: =SUM(J11:J12) -> 110208.75
B15: Expectation of Co-products | E15: Portion to root grinding | F15: Volume (tons) | G15: Unit price (baht) | H15: Total revenue (baht)
B16: Wash skin | E16: 0.02 | F16: =E6*E16 -> 785 | G16: 0.2 | H16: =G16*F16*1000 -> 157000
B17: Soil skin | E17: 0.061 | F17: =E6*E17 -> 2394.25 | G17: 0.03 | H17: =G17*F17*1000 -> 71827.5
B18: Pulp with 79% moisture content | E18: 0.2 | F18: =E6*E18 -> 7850 | G18: 0.282 | H18: =G18*F18*1000 -> 2213700
G19: Total
B22: Activities | C22: Response | E22: Target | H22: Budget | J22: Remarks
B23: Farmers-broker visit & | C23: Buyer | E23: Continuous root supply through year. | H23: 15000 | J23: - Farmer-Broker
B24: meeting expense for | J24: visit budget
B25: Root Sourcing department
E26: Total | H26: =SUM(H23:H25) -> 15000
B42: หมายเหตุ : กรณีไม่มีการเซ็นอนุมัติในแบบฟอร์ม ให้แนบเป็นอีเมลล์อนุมัติแทนได้

Sheet SK MAP - May 2026 _ 26.03.2026
B1: Monthly Activities Plan
B3: SK plant : The Root Purchasing of May 2026 (Total Operation Day 31 days)
B4: Root rolling Forecast | C4: Plan Original LE0.2026 | D4: Latest View | E4: Root purchase forecasting | F4: Remarks
C5: (18/12/25) | D5: (11/2/2026) | E5: Most likely
B6: Root purchase expectation | D6: 47700 | E6: =F13 -> 39250 | M6: Number of Days | N6: 31
B7: Starch content forecasting | D7: 0.2043501 | E7: =G13/100 -> 0.20970382 | M7: Volume Plan | N7: 39250
B8: Root price forecasting | D8: 2.8197589 | E8: =H13 -> 3.1263057 | M8: Farmer Daily supply | N8: 75
B9: PPDS. Forecasting | D9: 13.798666 | E9: =I13 -> 14.908196
B10: Expectation of root source purchasing. | E10: Farmer % of supply | F10: Volume/month | G10: Starch (%) | H10: Price(B./kg) | I10: PPDS (B./kg) | J10: Root expense amount (K baht)
B11: Farmer | E11: =F11/E6 -> 0.059235669 | F11: =N6*N8 -> 2325 | G11: 20.5 | H11: 2.75 | I11: =(H11/G11)*100 -> 13.414634 | J11: =H11*F11 -> 6393.75 | M11: F : 25% | N11: 2.95
B12: Broker | E12: =100%-E11 -> 0.94076433 | F12: =N7-F11 -> 36925 | G12: 21 | H12: 3.15 | I12: =(H12/G12)*100 -> 15 | J12: =H12*F12 -> 116313.75 | M12: B : 25% | N12: 3.35
B13: Total | E13: =SUM(E11:E12) -> 1 | F13: =SUM(F11:F12) -> 39250 | G13: =SUMPRODUCT($E$11:$E$12,G11:G12) -> 20.970382 | H13: =SUMPRODUCT($E$11:$E$12,H11:H12) -> 3.1263057 | I13: =(H13/G13)*100 -> 14.908196 | J13: =SUM(J11:J12) -> 122707.5
B15: Expectation of Co-products | E15: Portion to root grinding | F15: Volume (tons) | G15: Unit price (baht) | H15: Total revenue (baht)
B16: Wash skin | G16: 0.25
B17: Soil skin | G17: 0.03
B18: Pulp with 79% moisture content | G18: 0.352
G19: Total
B22: Activities | C22: Response | E22: Target | H22: Budget | J22: Remarks
E26: Total | H26: =SUM(H23:H25) -> 0
B42: หมายเหตุ : กรณีไม่มีการเซ็นอนุมัติในแบบฟอร์ม ให้แนบเป็นอีเมลล์อนุมัติแทนได้

Sheet SK MAP - May 2026 _ 24.04.26
B1: Monthly Activities Plan
B3: SK plant : The Root Purchasing of May 2026 (Total Operation Day 31 days)
B4: Root rolling Forecast | C4: Plan Original LE0.2026 | D4: Latest View | E4: Root purchase forecasting | F4: Remarks
C5: (18/12/25) | D5: (26/3/2026) | E5: Most likely
B6: Root purchase expectation | C6: 52158 | D6: 39250 | E6: =F13 -> 21700 | F6: - The estimated volume supply is approximately 700 tons/day, With farmers contributing about 50 tons /day. - According to this month’s projection reference, the industry is facing high competition from starch mills and cassava chip factories, limited root supply, low starch content. Remark: Waxy cassava root plan 3,584 tons | M6: Number of Days | N6: 31
B7: Starch content forecasting | C7: 0.225 | D7: 0.20970382 | E7: =G13/100 -> 0.20428571 | M7: Volume Plan | N7: =700*N6 -> 21700
B8: Root price forecasting | C8: 2.43 | D8: 3.1263057 | E8: =H13 -> 3.4214286 | M8: Farmer Daily supply | N8: 50
B9: PPDS. Forecasting | C9: 10.8 | D9: 14.908196 | E9: =I13 -> 16.748252
B10: Expectation of root source purchasing. | E10: Farmer % of supply | F10: Volume/month | G10: Starch (%) | H10: Price(B./kg) | I10: PPDS (B./kg) | J10: Root expense amount (K baht)
B11: Farmer | E11: =F11/E6 -> 0.071428571 | F11: =N6*N8 -> 1550 | G11: 19.5 | H11: 2.725 | I11: =(H11/G11)*100 -> 13.974359 | J11: =H11*F11 -> 4223.75 | M11: F : 25% | N11: 3
B12: Broker | E12: =100%-E11 -> 0.92857143 | F12: =N7-F11 -> 20150 | G12: 20.5 | H12: 3.475 | I12: =(H12/G12)*100 -> 16.95122 | J12: =H12*F12 -> 70021.25 | M12: B : 25% | N12: 3.65
B13: Total | E13: =SUM(E11:E12) -> 1 | F13: =SUM(F11:F12) -> 21700 | G13: =SUMPRODUCT($E$11:$E$12,G11:G12) -> 20.428571 | H13: =SUMPRODUCT($E$11:$E$12,H11:H12) -> 3.4214286 | I13: =(H13/G13)*100 -> 16.748252 | J13: =SUM(J11:J12) -> 74245
B15: Expectation of Co-products | E15: Portion to root grinding | F15: Volume (tons) | G15: Unit price (baht) | H15: Total revenue (baht)
B16: Wash skin | G16: 0.25
B17: Soil skin | G17: 0.03
B18: Pulp with 79% moisture content | G18: 0.352
G19: Total
B22: Activities | C22: Response | E22: Target | H22: Budget | J22: Remarks
E26: Total | H26: =SUM(H23:H25) -> 0
B42: หมายเหตุ : กรณีไม่มีการเซ็นอนุมัติในแบบฟอร์ม ให้แนบเป็นอีเมลล์อนุมัติแทนได้

Sheet SK MAP - Jun 2026 (2)
B1: Monthly Activities Plan
B3: SK plant : The Root Purchasing of June 2026 (Total Operation Day 30 days)
B4: Root rolling Forecast | C4: Plan Original LE0.2026 | D4: Latest View | E4: Root purchase forecasting | F4: Remarks
C5: (18/12/25) | E5: Most likely
B6: Root purchase expectation | E6: =F13 -> 41050 | M6: Number of Days | N6: 30
B7: Starch content forecasting | E7: =G13/100 -> 0.20853837 | M7: Volume Plan | N7: ='LV02.04.2026 cost+ Act.'!G9 -> 41050
B8: Root price forecasting | E8: =H13 -> 2.8342266 | M8: Farmer Daily supply | N8: 200
B9: PPDS. Forecasting | E9: =I13 -> 13.590912
B10: Expectation of root source purchasing. | E10: Farmer % of supply | F10: Volume/month | G10: Starch (%) | H10: Price(B./kg) | I10: PPDS (B./kg) | J10: Root expense amount (K baht)
B11: Farmer | E11: =F11/E6 -> 0.14616322 | F11: =N6*N8 -> 6000 | G11: 20 | H11: 2.45 | I11: =(H11/G11)*100 -> 12.25 | J11: =H11*F11 -> 14700 | M11: F : 25% | N11: 2.7
B12: Broker | E12: =100%-E11 -> 0.85383678 | F12: =N7-F11 -> 35050 | G12: 21 | H12: 2.9 | I12: =(H12/G12)*100 -> 13.809524 | J12: =H12*F12 -> 101645 | M12: B : 25% | N12: 3.1
B13: Total | E13: =SUM(E11:E12) -> 1 | F13: =SUM(F11:F12) -> 41050 | G13: =SUMPRODUCT($E$11:$E$12,G11:G12) -> 20.853837 | H13: =SUMPRODUCT($E$11:$E$12,H11:H12) -> 2.8342266 | I13: =(H13/G13)*100 -> 13.590912 | J13: =SUM(J11:J12) -> 116345
B15: Expectation of Co-products | E15: Portion to root grinding | F15: Volume (tons) | G15: Unit price (baht) | H15: Total revenue (baht)
B16: Wash skin | E16: 0.02 | F16: =E6*E16 -> 821 | G16: 0.2 | H16: =G16*F16*1000 -> 164200
B17: Soil skin | E17: 0.061 | F17: =E6*E17 -> 2504.05 | G17: 0.03 | H17: =G17*F17*1000 -> 75121.5
B18: Pulp with 79% moisture content | E18: 0.2 | F18: =E6*E18 -> 8210 | G18: 0.282 | H18: =G18*F18*1000 -> 2315220
G19: Total
B22: Activities | C22: Response | E22: Target | H22: Budget | J22: Remarks
B23: Farmers-broker visit & | C23: Buyer | E23: Continuous root supply through year. | H23: 15000 | J23: - Farmer-Broker
B24: meeting expense for | J24: visit budget
B25: Root Sourcing department
E26: Total | H26: =SUM(H23:H25) -> 15000
B42: หมายเหตุ : กรณีไม่มีการเซ็นอนุมัติในแบบฟอร์ม ให้แนบเป็นอีเมลล์อนุมัติแทนได้

Sheet SK MAP -June 2026 _ 26.03.2026
B1: Monthly Activities Plan
B3: SK plant : The Root Purchasing of June 2026 (Total Operation Day 30 days)
B4: Root rolling Forecast | C4: Plan Original LE0.2026 | D4: Latest View | E4: Root purchase forecasting | F4: Remarks
C5: (18/12/25) | D5: (11/2/2026) | E5: Most likely
B6: Root purchase expectation | E6: =F13 -> 41050 | M6: Number of Days | N6: 30
B7: Starch content forecasting | E7: =G13/100 -> 0.21 | M7: Volume Plan | N7: 41050
B8: Root price forecasting | E8: =H13 -> 3.0808161 | M8: Farmer Daily supply | N8: 75
B9: PPDS. Forecasting | E9: =I13 -> 14.670553
B10: Expectation of root source purchasing. | E10: Farmer % of supply | F10: Volume/month | G10: Starch (%) | H10: Price(B./kg) | I10: PPDS (B./kg) | J10: Root expense amount (K baht)
B11: Farmer | E11: =F11/E6 -> 0.054811206 | F11: =N6*N8 -> 2250 | G11: 21 | H11: 2.75 | I11: =(H11/G11)*100 -> 13.095238 | J11: =H11*F11 -> 6187.5 | M11: F : 25% | N11: 2.95
B12: Broker | E12: =100%-E11 -> 0.94518879 | F12: =N7-F11 -> 38800 | G12: 21 | H12: 3.1 | I12: =(H12/G12)*100 -> 14.761905 | J12: =H12*F12 -> 120280 | M12: B : 25% | N12: 3.3
B13: Total | E13: =SUM(E11:E12) -> 1 | F13: =SUM(F11:F12) -> 41050 | G13: =SUMPRODUCT($E$11:$E$12,G11:G12) -> 21 | H13: =SUMPRODUCT($E$11:$E$12,H11:H12) -> 3.0808161 | I13: =(H13/G13)*100 -> 14.670553 | J13: =SUM(J11:J12) -> 126467.5
B15: Expectation of Co-products | E15: Portion to root grinding | F15: Volume (tons) | G15: Unit price (baht) | H15: Total revenue (baht)
B16: Wash skin | G16: 0.25
B17: Soil skin | G17: 0.03
B18: Pulp with 79% moisture content | G18: 0.352
G19: Total
B22: Activities | C22: Response | E22: Target | H22: Budget | J22: Remarks
E26: Total | H26: =SUM(H23:H25) -> 0
B42: หมายเหตุ : กรณีไม่มีการเซ็นอนุมัติในแบบฟอร์ม ให้แนบเป็นอีเมลล์อนุมัติแทนได้

Sheet SK MAP - May 2026Rev01 5.5.2026
B1: Monthly Activities Plan
B3: SK plant : The Root Purchasing of May 2026 (Total Operation Day 31 days) Rev.01
B4: Root rolling Forecast | C4: Plan Original LE0.2026 | D4: Latest View | E4: Root purchase forecasting | F4: Remarks
C5: (18/12/25) | D5: (26/3/2026) | E5: Most likely
B6: Root purchase expectation | C6: 52158 | D6: 39250 | E6: =F13 -> 40300 | F6: - The estimated volume supply has been revised from 700 tons/day to 1,300 tons/day, with farmers contributing about 50 tons/day. - According to this month’s projection reference, the industry is facing high competition from starch mills and cassava chip factories, limited root supply, low starch content. Remark: Waxy cassava root plan 2,900 tons | M6: Number of Days | N6: 31
B7: Starch content forecasting | C7: 0.225 | D7: 0.20970382 | E7: =G13/100 -> 0.185 | M7: Volume Plan | N7: =1300*N6 -> 40300
B8: Root price forecasting | C8: 2.43 | D8: 3.1263057 | E8: =H13 -> 3.4048077 | M8: Farmer Daily supply | N8: 50
B9: PPDS. Forecasting | C9: 10.8 | D9: 14.908196 | E9: =I13 -> 18.404366
B10: Expectation of root source purchasing. | E10: Farmer % of supply | F10: Volume/month | G10: Starch (%) | H10: Price(B./kg) | I10: PPDS (B./kg) | J10: Root expense amount (K baht)
B11: Farmer | E11: =F11/E6 -> 0.038461538 | F11: =N6*N8 -> 1550 | G11: 18.5 | H11: =2.75+0.025 -> 2.775 | I11: =(H11/G11)*100 -> 15 | J11: =H11*F11 -> 4301.25 | M11: F : 25% | N11: 3.1
B12: Broker | E12: =100%-E11 -> 0.96153846 | F12: =N7-F11 -> 38750 | G12: 18.5 | H12: =3.4+0.03 -> 3.43 | I12: =(H12/G12)*100 -> 18.540541 | J12: =H12*F12 -> 132912.5 | M12: B : 25% | N12: 3.75
B13: Total | E13: =SUM(E11:E12) -> 1 | F13: =SUM(F11:F12) -> 40300 | G13: =SUMPRODUCT($E$11:$E$12,G11:G12) -> 18.5 | H13: =SUMPRODUCT($E$11:$E$12,H11:H12) -> 3.4048077 | I13: =(H13/G13)*100 -> 18.404366 | J13: =SUM(J11:J12) -> 137213.75
B15: Expectation of Co-products | E15: Portion to root grinding | F15: Volume (tons) | G15: Unit price (baht) | H15: Total revenue (baht)
B16: Wash skin | G16: 0.25
B17: Soil skin | G17: 0.03
B18: Pulp with 79% moisture content | G18: 0.352
G19: Total
B22: Activities | C22: Response | E22: Target | H22: Budget | J22: Remarks
E26: Total | H26: =SUM(H23:H25) -> 0
B42: หมายเหตุ : กรณีไม่มีการเซ็นอนุมัติในแบบฟอร์ม ให้แนบเป็นอีเมลล์อนุมัติแทนได้

Sheet SK MAP - Jul 2026 (2)
B1: Monthly Activities Plan
B3: SK plant : The Root Purchasing of July 2026 (Total Operation Day 31 days)
B4: Root rolling Forecast | C4: Plan Original LE0.2026 | D4: Latest View | E4: Root purchase forecasting | F4: Remarks
C5: (18/12/25) | E5: Most likely
B6: Root purchase expectation | E6: =F13 -> 41800 | M6: Number of Days | N6: 31
B7: Starch content forecasting | E7: =G13/100 -> 0.215 | M7: Volume Plan | N7: ='LV02.04.2026 cost+ Act.'!H9 -> 41800
B8: Root price forecasting | E8: =H13 -> 2.781244 | M8: Farmer Daily supply | N8: 200
B9: PPDS. Forecasting | E9: =I13 -> 12.936019
B10: Expectation of root source purchasing. | E10: Farmer % of supply | F10: Volume/month | G10: Starch (%) | H10: Price(B./kg) | I10: PPDS (B./kg) | J10: Root expense amount (K baht)
B11: Farmer | E11: =F11/E6 -> 0.14832536 | F11: =N6*N8 -> 6200 | G11: 21.5 | H11: 2.53 | I11: =(H11/G11)*100 -> 11.767442 | J11: =H11*F11 -> 15686 | M11: F : 25% | N11: 2.7
B12: Broker | E12: =100%-E11 -> 0.85167464 | F12: =N7-F11 -> 35600 | G12: 21.5 | H12: 2.825 | I12: =(H12/G12)*100 -> 13.139535 | J12: =H12*F12 -> 100570 | M12: B : 25% | N12: 3.1
B13: Total | E13: =SUM(E11:E12) -> 1 | F13: =SUM(F11:F12) -> 41800 | G13: =SUMPRODUCT($E$11:$E$12,G11:G12) -> 21.5 | H13: =SUMPRODUCT($E$11:$E$12,H11:H12) -> 2.781244 | I13: =(H13/G13)*100 -> 12.936019 | J13: =SUM(J11:J12) -> 116256
B15: Expectation of Co-products | E15: Portion to root grinding | F15: Volume (tons) | G15: Unit price (baht) | H15: Total revenue (baht)
B16: Wash skin | E16: 0.02 | F16: =E6*E16 -> 836 | G16: 0.2 | H16: =G16*F16*1000 -> 167200
B17: Soil skin | E17: 0.061 | F17: =E6*E17 -> 2549.8 | G17: 0.03 | H17: =G17*F17*1000 -> 76494
B18: Pulp with 79% moisture content | E18: 0.2 | F18: =E6*E18 -> 8360 | G18: 0.282 | H18: =G18*F18*1000 -> 2357520
G19: Total
B22: Activities | C22: Response | E22: Target | H22: Budget | J22: Remarks
B23: Farmers-broker visit & | C23: Buyer | E23: Continuous root supply through year. | H23: 15000 | J23: - Farmer-Broker
B24: meeting expense for | J24: visit budget
B25: Root Sourcing department
E26: Total | H26: =SUM(H23:H25) -> 15000
B42: หมายเหตุ : กรณีไม่มีการเซ็นอนุมัติในแบบฟอร์ม ให้แนบเป็นอีเมลล์อนุมัติแทนได้

Sheet SK MAP -July 2026 _ 26.03.26
B1: Monthly Activities Plan
B3: SK plant : The Root Purchasing of July 2026 (Total Operation Day 31 days)
B4: Root rolling Forecast | C4: Plan Original LE0.2026 | D4: Latest View | E4: Root purchase forecasting | F4: Remarks
C5: (18/12/25) | D5: (11/2/2026) | E5: Most likely
B6: Root purchase expectation | E6: =F13 -> 41800 | M6: Number of Days | N6: 31
B7: Starch content forecasting | E7: =G13/100 -> 0.22 | M7: Volume Plan | N7: 41800
B8: Root price forecasting | E8: =H13 -> 3.1277512 | M8: Farmer Daily supply | N8: 75
B9: PPDS. Forecasting | E9: =I13 -> 14.217051
B10: Expectation of root source purchasing. | E10: Farmer % of supply | F10: Volume/month | G10: Starch (%) | H10: Price(B./kg) | I10: PPDS (B./kg) | J10: Root expense amount (K baht)
B11: Farmer | E11: =F11/E6 -> 0.05562201 | F11: =N6*N8 -> 2325 | G11: 22 | H11: 2.75 | I11: =(H11/G11)*100 -> 12.5 | J11: =H11*F11 -> 6393.75 | M11: F : 25% | N11: 2.9
B12: Broker | E12: =100%-E11 -> 0.94437799 | F12: =N7-F11 -> 39475 | G12: 22 | H12: 3.15 | I12: =(H12/G12)*100 -> 14.318182 | J12: =H12*F12 -> 124346.25 | M12: B : 25% | N12: 3.3
B13: Total | E13: =SUM(E11:E12) -> 1 | F13: =SUM(F11:F12) -> 41800 | G13: =SUMPRODUCT($E$11:$E$12,G11:G12) -> 22 | H13: =SUMPRODUCT($E$11:$E$12,H11:H12) -> 3.1277512 | I13: =(H13/G13)*100 -> 14.217051 | J13: =SUM(J11:J12) -> 130740
B15: Expectation of Co-products | E15: Portion to root grinding | F15: Volume (tons) | G15: Unit price (baht) | H15: Total revenue (baht)
B16: Wash skin | G16: 0.25
B17: Soil skin | G17: 0.03
B18: Pulp with 79% moisture content | G18: 0.352
G19: Total
B22: Activities | C22: Response | E22: Target | H22: Budget | J22: Remarks
E26: Total | H26: =SUM(H23:H25) -> 0
B42: หมายเหตุ : กรณีไม่มีการเซ็นอนุมัติในแบบฟอร์ม ให้แนบเป็นอีเมลล์อนุมัติแทนได้

Sheet SK MAP - Aug 2026 (2)
B1: Monthly Activities Plan
B3: SK plant : The Root Purchasing of August 2026 (Total Operation Day 31 days)
B4: Root rolling Forecast | C4: Plan Original LE0.2026 | D4: Latest View | E4: Root purchase forecasting | F4: Remarks
C5: (18/12/25) | E5: Most likely
B6: Root purchase expectation | E6: =F13 -> 41700 | M6: Number of Days | N6: 31
B7: Starch content forecasting | E7: =G13/100 -> 0.22977698 | M7: Volume Plan | N7: ='LV02.04.2026 cost+ Act.'!I9 -> 41700
B8: Root price forecasting | E8: =H13 -> 2.8942446 | M8: Farmer Daily supply | N8: 200
B9: PPDS. Forecasting | E9: =I13 -> 12.595886
B10: Expectation of root source purchasing. | E10: Farmer % of supply | F10: Volume/month | G10: Starch (%) | H10: Price(B./kg) | I10: PPDS (B./kg) | J10: Root expense amount (K baht)
B11: Farmer | E11: =F11/E6 -> 0.14868106 | F11: =N6*N8 -> 6200 | G11: 22.85 | H11: 2.575 | I11: =(H11/G11)*100 -> 11.269147 | J11: =H11*F11 -> 15965 | M11: F : 25% | N11: 2.7
B12: Broker | E12: =100%-E11 -> 0.85131894 | F12: =N7-F11 -> 35500 | G12: 23 | H12: 2.95 | I12: =(H12/G12)*100 -> 12.826087 | J12: =H12*F12 -> 104725 | M12: B : 25% | N12: 3.05
B13: Total | E13: =SUM(E11:E12) -> 1 | F13: =SUM(F11:F12) -> 41700 | G13: =SUMPRODUCT($E$11:$E$12,G11:G12) -> 22.977698 | H13: =SUMPRODUCT($E$11:$E$12,H11:H12) -> 2.8942446 | I13: =(H13/G13)*100 -> 12.595886 | J13: =SUM(J11:J12) -> 120690
B15: Expectation of Co-products | E15: Portion to root grinding | F15: Volume (tons) | G15: Unit price (baht) | H15: Total revenue (baht)
B16: Wash skin | E16: 0.02 | F16: =E6*E16 -> 834 | G16: 0.2 | H16: =G16*F16*1000 -> 166800
B17: Soil skin | E17: 0.061 | F17: =E6*E17 -> 2543.7 | G17: 0.03 | H17: =G17*F17*1000 -> 76311
B18: Pulp with 79% moisture content | E18: 0.2 | F18: =E6*E18 -> 8340 | G18: 0.282 | H18: =G18*F18*1000 -> 2351880
G19: Total
B22: Activities | C22: Response | E22: Target | H22: Budget | J22: Remarks
B23: Farmers-broker visit & | C23: Buyer | E23: Continuous root supply through year. | H23: 15000 | J23: - Farmer-Broker
B24: meeting expense for | J24: visit budget
B25: Root Sourcing department
E26: Total | H26: =SUM(H23:H25) -> 15000
B42: หมายเหตุ : กรณีไม่มีการเซ็นอนุมัติในแบบฟอร์ม ให้แนบเป็นอีเมลล์อนุมัติแทนได้

Sheet SK MAP -Aug 2026 _ 26.03.26
B1: Monthly Activities Plan
B3: SK plant : The Root Purchasing of August 2026 (Total Operation Day 31 days)
B4: Root rolling Forecast | C4: Plan Original LE0.2026 | D4: Latest View | E4: Root purchase forecasting | F4: Remarks
C5: (18/12/25) | D5: (11/2/2026) | E5: Most likely
B6: Root purchase expectation | E6: =F13 -> 41700 | M6: Number of Days | N6: 31
B7: Starch content forecasting | E7: =G13/100 -> 0.22504484 | M7: Volume Plan | N7: 41700
B8: Root price forecasting | E8: =H13 -> 3.1165468 | M8: Farmer Daily supply | N8: 100
B9: PPDS. Forecasting | E9: =I13 -> 13.848559
B10: Expectation of root source purchasing. | E10: Farmer % of supply | F10: Volume/month | G10: Starch (%) | H10: Price(B./kg) | I10: PPDS (B./kg) | J10: Root expense amount (K baht)
B11: Farmer | E11: =F11/E6 -> 0.074340528 | F11: =N6*N8 -> 3100 | G11: 22 | H11: 2.7 | I11: =(H11/G11)*100 -> 12.272727 | J11: =H11*F11 -> 8370 | M11: F : 25% | N11: 2.85
B12: Broker | E12: =100%-E11 -> 0.92565947 | F12: =N7-F11 -> 38600 | G12: 22.545 | H12: 3.15 | I12: =(H12/G12)*100 -> 13.972056 | J12: =H12*F12 -> 121590 | M12: B : 25% | N12: 3.25
B13: Total | E13: =SUM(E11:E12) -> 1 | F13: =SUM(F11:F12) -> 41700 | G13: =SUMPRODUCT($E$11:$E$12,G11:G12) -> 22.504484 | H13: =SUMPRODUCT($E$11:$E$12,H11:H12) -> 3.1165468 | I13: =(H13/G13)*100 -> 13.848559 | J13: =SUM(J11:J12) -> 129960
B15: Expectation of Co-products | E15: Portion to root grinding | F15: Volume (tons) | G15: Unit price (baht) | H15: Total revenue (baht)
B16: Wash skin | G16: 0.25
B17: Soil skin | G17: 0.03
B18: Pulp with 79% moisture content | G18: 0.352
G19: Total
B22: Activities | C22: Response | E22: Target | H22: Budget | J22: Remarks
E26: Total | H26: =SUM(H23:H25) -> 0
B42: หมายเหตุ : กรณีไม่มีการเซ็นอนุมัติในแบบฟอร์ม ให้แนบเป็นอีเมลล์อนุมัติแทนได้

Sheet SK MAP - Sep 26 (2)
B1: Monthly Activities Plan
B3: SK plant : The Root Purchasing of September 2026 (Total Operation Day 30 days)
B4: Root rolling Forecast | C4: Plan Original LE0.2026 | D4: Latest View | E4: Root purchase forecasting | F4: Remarks
C5: (18/12/25) | E5: Most likely
B6: Root purchase expectation | E6: =F13 -> 37200 | M6: Number of Days | N6: 30
B7: Starch content forecasting | E7: =G13/100 -> 0.23919355 | M7: Volume Plan | N7: ='LV02.04.2026 cost+ Act.'!J9 -> 37200
B8: Root price forecasting | E8: =H13 -> 2.9395161 | M8: Farmer Daily supply | N8: 200
B9: PPDS. Forecasting | E9: =I13 -> 12.289278
B10: Expectation of root source purchasing. | E10: Farmer % of supply | F10: Volume/month | G10: Starch (%) | H10: Price(B./kg) | I10: PPDS (B./kg) | J10: Root expense amount (K baht)
B11: Farmer | E11: =F11/E6 -> 0.16129032 | F11: =N6*N8 -> 6000 | G11: 23.5 | H11: 2.625 | I11: =(H11/G11)*100 -> 11.170213 | J11: =H11*F11 -> 15750 | M11: F : 25% | N11: 2.7
B12: Broker | E12: =100%-E11 -> 0.83870968 | F12: =N7-F11 -> 31200 | G12: 24 | H12: 3 | I12: =(H12/G12)*100 -> 12.5 | J12: =H12*F12 -> 93600 | M12: B : 25% | N12: 3.05
B13: Total | E13: =SUM(E11:E12) -> 1 | F13: =SUM(F11:F12) -> 37200 | G13: =SUMPRODUCT($E$11:$E$12,G11:G12) -> 23.919355 | H13: =SUMPRODUCT($E$11:$E$12,H11:H12) -> 2.9395161 | I13: =(H13/G13)*100 -> 12.289278 | J13: =SUM(J11:J12) -> 109350
B15: Expectation of Co-products | E15: Portion to root grinding | F15: Volume (tons) | G15: Unit price (baht) | H15: Total revenue (baht)
B16: Wash skin | E16: 0.02 | F16: =E6*E16 -> 744 | G16: 0.2 | H16: =G16*F16*1000 -> 148800
B17: Soil skin | E17: 0.061 | F17: =E6*E17 -> 2269.2 | G17: 0.03 | H17: =G17*F17*1000 -> 68076
B18: Pulp with 79% moisture content | E18: 0.2 | F18: =E6*E18 -> 7440 | G18: 0.282 | H18: =G18*F18*1000 -> 2098080
G19: Total
B22: Activities | C22: Response | E22: Target | H22: Budget | J22: Remarks
B23: Farmers-broker visit & | C23: Buyer | E23: Continuous root supply through year. | H23: 15000 | J23: - Farmer-Broker
B24: meeting expense for | J24: visit budget
B25: Root Sourcing department
E26: Total | H26: =SUM(H23:H25) -> 15000
B42: หมายเหตุ : กรณีไม่มีการเซ็นอนุมัติในแบบฟอร์ม ให้แนบเป็นอีเมลล์อนุมัติแทนได้

Sheet SK MAP -Sep 2026 _ 26.03.26 
B1: Monthly Activities Plan
B3: SK plant : The Root Purchasing of September 2026 (Total Operation Day 30 days)
B4: Root rolling Forecast | C4: Plan Original LE0.2026 | D4: Latest View | E4: Root purchase forecasting | F4: Remarks
C5: (18/12/25) | D5: (11/2/2026) | E5: Most likely
B6: Root purchase expectation | E6: =F13 -> 37200 | M6: Number of Days | N6: 30
B7: Starch content forecasting | E7: =G13/100 -> 0.22801935 | M7: Volume Plan | N7: 37200
B8: Root price forecasting | E8: =H13 -> 3.0435484 | M8: Farmer Daily supply | N8: 200
B9: PPDS. Forecasting | E9: =I13 -> 13.347763
B10: Expectation of root source purchasing. | E10: Farmer % of supply | F10: Volume/month | G10: Starch (%) | H10: Price(B./kg) | I10: PPDS (B./kg) | J10: Root expense amount (K baht)
B11: Farmer | E11: =F11/E6 -> 0.16129032 | F11: =N6*N8 -> 6000 | G11: 22.5 | H11: 2.75 | I11: =(H11/G11)*100 -> 12.222222 | J11: =H11*F11 -> 16500 | M11: F : 25% | N11: 2.85
B12: Broker | E12: =100%-E11 -> 0.83870968 | F12: =N7-F11 -> 31200 | G12: 22.86 | H12: 3.1 | I12: =(H12/G12)*100 -> 13.560805 | J12: =H12*F12 -> 96720 | M12: B : 25% | N12: 3.2
B13: Total | E13: =SUM(E11:E12) -> 1 | F13: =SUM(F11:F12) -> 37200 | G13: =SUMPRODUCT($E$11:$E$12,G11:G12) -> 22.801935 | H13: =SUMPRODUCT($E$11:$E$12,H11:H12) -> 3.0435484 | I13: =(H13/G13)*100 -> 13.347763 | J13: =SUM(J11:J12) -> 113220
B15: Expectation of Co-products | E15: Portion to root grinding | F15: Volume (tons) | G15: Unit price (baht) | H15: Total revenue (baht)
B16: Wash skin | G16: 0.25
B17: Soil skin | G17: 0.03
B18: Pulp with 79% moisture content | G18: 0.352
G19: Total
B22: Activities | C22: Response | E22: Target | H22: Budget | J22: Remarks
E26: Total | H26: =SUM(H23:H25) -> 0
B42: หมายเหตุ : กรณีไม่มีการเซ็นอนุมัติในแบบฟอร์ม ให้แนบเป็นอีเมลล์อนุมัติแทนได้

Sheet SK MAP - Oct 26 (2)
B1: Monthly Activities Plan
B3: SK plant : The Root Purchasing of October 2026 (Total Operation Day 31 days)
B4: Root rolling Forecast | C4: Plan Original LE0.2026 | D4: Latest View | E4: Root purchase forecasting | F4: Remarks
C5: (18/12/25) | E5: Most likely
B6: Root purchase expectation | E6: =F13 -> 34300 | M6: Number of Days | N6: 31
B7: Starch content forecasting | E7: =G13/100 -> 0.24491545 | M7: Volume Plan | N7: ='LV02.04.2026 cost+ Act.'!K9 -> 34300
B8: Root price forecasting | E8: =H13 -> 2.9161224 | M8: Farmer Daily supply | N8: 300
B9: PPDS. Forecasting | E9: =I13 -> 11.90665
B10: Expectation of root source purchasing. | E10: Farmer % of supply | F10: Volume/month | G10: Starch (%) | H10: Price(B./kg) | I10: PPDS (B./kg) | J10: Root expense amount (K baht)
B11: Farmer | E11: =F11/E6 -> 0.27113703 | F11: =N6*N8 -> 9300 | G11: 24.2 | H11: 2.61 | I11: =(H11/G11)*100 -> 10.785124 | J11: =H11*F11 -> 24273 | M11: F : 25% | N11: 2.65
B12: Broker | E12: =100%-E11 -> 0.72886297 | F12: =N7-F11 -> 25000 | G12: 24.6 | H12: 3.03 | I12: =(H12/G12)*100 -> 12.317073 | J12: =H12*F12 -> 75750 | M12: B : 25% | N12: 3.05
B13: Total | E13: =SUM(E11:E12) -> 1 | F13: =SUM(F11:F12) -> 34300 | G13: =SUMPRODUCT($E$11:$E$12,G11:G12) -> 24.491545 | H13: =SUMPRODUCT($E$11:$E$12,H11:H12) -> 2.9161224 | I13: =(H13/G13)*100 -> 11.90665 | J13: =SUM(J11:J12) -> 100023
B15: Expectation of Co-products | E15: Portion to root grinding | F15: Volume (tons) | G15: Unit price (baht) | H15: Total revenue (baht)
B16: Wash skin | E16: 0.02 | F16: =E6*E16 -> 686 | G16: 0.2 | H16: =G16*F16*1000 -> 137200
B17: Soil skin | E17: 0.061 | F17: =E6*E17 -> 2092.3 | G17: 0.03 | H17: =G17*F17*1000 -> 62769
B18: Pulp with 79% moisture content | E18: 0.2 | F18: =E6*E18 -> 6860 | G18: 0.282 | H18: =G18*F18*1000 -> 1934520
G19: Total
B22: Activities | C22: Response | E22: Target | H22: Budget | J22: Remarks
B23: Farmers-broker visit & | C23: Buyer | E23: Continuous root supply through year. | H23: 15000 | J23: - Farmer-Broker
B24: meeting expense for | J24: visit budget
B25: Root Sourcing department
E26: Total | H26: =SUM(H23:H25) -> 15000
B42: หมายเหตุ : กรณีไม่มีการเซ็นอนุมัติในแบบฟอร์ม ให้แนบเป็นอีเมลล์อนุมัติแทนได้

Sheet SK MAP -Oct 2026 _ 26.03.26
B1: Monthly Activities Plan
B3: SK plant : The Root Purchasing of October 2026 (Total Operation Day 31 days)
B4: Root rolling Forecast | C4: Plan Original LE0.2026 | D4: Latest View | E4: Root purchase forecasting | F4: Remarks
C5: (18/12/25) | D5: (11/2/2026) | E5: Most likely
B6: Root purchase expectation | E6: =F13 -> 34300 | M6: Number of Days | N6: 31
B7: Starch content forecasting | E7: =G13/100 -> 0.22995773 | M7: Volume Plan | N7: 34300
B8: Root price forecasting | E8: =H13 -> 2.955102 | M8: Farmer Daily supply | N8: 300
B9: PPDS. Forecasting | E9: =I13 -> 12.850632
B10: Expectation of root source purchasing. | E10: Farmer % of supply | F10: Volume/month | G10: Starch (%) | H10: Price(B./kg) | I10: PPDS (B./kg) | J10: Root expense amount (K baht)
B11: Farmer | E11: =F11/E6 -> 0.27113703 | F11: =N6*N8 -> 9300 | G11: 22.85 | H11: 2.7 | I11: =(H11/G11)*100 -> 11.816193 | J11: =H11*F11 -> 25110 | M11: F : 25% | N11: 2.8
B12: Broker | E12: =100%-E11 -> 0.72886297 | F12: =N7-F11 -> 25000 | G12: 23.05 | H12: 3.05 | I12: =(H12/G12)*100 -> 13.232104 | J12: =H12*F12 -> 76250 | M12: B : 25% | N12: 3.15
B13: Total | E13: =SUM(E11:E12) -> 1 | F13: =SUM(F11:F12) -> 34300 | G13: =SUMPRODUCT($E$11:$E$12,G11:G12) -> 22.995773 | H13: =SUMPRODUCT($E$11:$E$12,H11:H12) -> 2.955102 | I13: =(H13/G13)*100 -> 12.850632 | J13: =SUM(J11:J12) -> 101360
B15: Expectation of Co-products | E15: Portion to root grinding | F15: Volume (tons) | G15: Unit price (baht) | H15: Total revenue (baht)
B16: Wash skin | G16: 0.25
B17: Soil skin | G17: 0.03
B18: Pulp with 79% moisture content | G18: 0.352
G19: Total
B22: Activities | C22: Response | E22: Target | H22: Budget | J22: Remarks
E26: Total | H26: =SUM(H23:H25) -> 0
B42: หมายเหตุ : กรณีไม่มีการเซ็นอนุมัติในแบบฟอร์ม ให้แนบเป็นอีเมลล์อนุมัติแทนได้

Sheet SK MAP - Nov 26 (2)
B1: Monthly Activities Plan
B3: SK plant : The Root Purchasing of November 2026 (Total Operation Day 30 days)
B4: Root rolling Forecast | C4: Plan Original LE0.2026 | D4: Latest View | E4: Root purchase forecasting | F4: Remarks
C5: (18/12/25) | E5: Most likely
B6: Root purchase expectation | E6: =F13 -> 33150 | M6: Number of Days | N6: 30
B7: Starch content forecasting | E7: =G13/100 -> 0.25982127 | M7: Volume Plan | N7: ='LV02.04.2026 cost+ Act.'!L9 -> 33150
B8: Root price forecasting | E8: =H13 -> 3.0359729 | M8: Farmer Daily supply | N8: 300
B9: PPDS. Forecasting | E9: =I13 -> 11.684851
B10: Expectation of root source purchasing. | E10: Farmer % of supply | F10: Volume/month | G10: Starch (%) | H10: Price(B./kg) | I10: PPDS (B./kg) | J10: Root expense amount (K baht)
B11: Farmer | E11: =F11/E6 -> 0.27149321 | F11: =N6*N8 -> 9000 | G11: 25.8 | H11: 2.73 | I11: =(H11/G11)*100 -> 10.581395 | J11: =H11*F11 -> 24570 | M11: F : 25% | N11: 2.7 | P11: Corn vs Rice harvesting
B12: Broker | E12: =100%-E11 -> 0.72850679 | F12: =N7-F11 -> 24150 | G12: 26.05 | H12: 3.15 | I12: =(H12/G12)*100 -> 12.092131 | J12: =H12*F12 -> 76072.5 | M12: B : 25% | N12: 3.1
B13: Total | E13: =SUM(E11:E12) -> 1 | F13: =SUM(F11:F12) -> 33150 | G13: =SUMPRODUCT($E$11:$E$12,G11:G12) -> 25.982127 | H13: =SUMPRODUCT($E$11:$E$12,H11:H12) -> 3.0359729 | I13: =(H13/G13)*100 -> 11.684851 | J13: =SUM(J11:J12) -> 100642.5
B15: Expectation of Co-products | E15: Portion to root grinding | F15: Volume (tons) | G15: Unit price (baht) | H15: Total revenue (baht)
B16: Wash skin | E16: 0.02 | F16: =E6*E16 -> 663 | G16: 0.2 | H16: =G16*F16*1000 -> 132600
B17: Soil skin | E17: 0.061 | F17: =E6*E17 -> 2022.15 | G17: 0.03 | H17: =G17*F17*1000 -> 60664.5
B18: Pulp with 79% moisture content | E18: 0.2 | F18: =E6*E18 -> 6630 | G18: 0.282 | H18: =G18*F18*1000 -> 1869660
G19: Total
B22: Activities | C22: Response | E22: Target | H22: Budget | J22: Remarks
B23: Farmers-broker visit & | C23: Buyer | E23: Continuous root supply through year. | H23: 15000 | J23: - Farmer-Broker
B24: meeting expense for | J24: visit budget
B25: Root Sourcing department
E26: Total | H26: =SUM(H23:H25) -> 15000
B42: หมายเหตุ : กรณีไม่มีการเซ็นอนุมัติในแบบฟอร์ม ให้แนบเป็นอีเมลล์อนุมัติแทนได้

Sheet SK MAP -Nov 2026 _ 26.03.26
B1: Monthly Activities Plan
B3: SK plant : The Root Purchasing of November 2026 (Total Operation Day 30 days)
B4: Root rolling Forecast | C4: Plan Original LE0.2026 | D4: Latest View | E4: Root purchase forecasting | F4: Remarks
C5: (18/12/25) | D5: (11/2/2026) | E5: Most likely
B6: Root purchase expectation | E6: =F13 -> 33150 | M6: Number of Days | N6: 30
B7: Starch content forecasting | E7: =G13/100 -> 0.24 | M7: Volume Plan | N7: 33150
B8: Root price forecasting | E8: =H13 -> 3.0776018 | M8: Farmer Daily supply | N8: 200
B9: PPDS. Forecasting | E9: =I13 -> 12.823341
B10: Expectation of root source purchasing. | E10: Farmer % of supply | F10: Volume/month | G10: Starch (%) | H10: Price(B./kg) | I10: PPDS (B./kg) | J10: Root expense amount (K baht)
B11: Farmer | E11: =F11/E6 -> 0.18099548 | F11: =N6*N8 -> 6000 | G11: 24 | H11: 2.75 | I11: =(H11/G11)*100 -> 11.458333 | J11: =H11*F11 -> 16500 | M11: F : 25% | N11: 2.8
B12: Broker | E12: =100%-E11 -> 0.81900452 | F12: =N7-F11 -> 27150 | G12: 24 | H12: 3.15 | I12: =(H12/G12)*100 -> 13.125 | J12: =H12*F12 -> 85522.5 | M12: B : 25% | N12: 3.2
B13: Total | E13: =SUM(E11:E12) -> 1 | F13: =SUM(F11:F12) -> 33150 | G13: =SUMPRODUCT($E$11:$E$12,G11:G12) -> 24 | H13: =SUMPRODUCT($E$11:$E$12,H11:H12) -> 3.0776018 | I13: =(H13/G13)*100 -> 12.823341 | J13: =SUM(J11:J12) -> 102022.5
B15: Expectation of Co-products | E15: Portion to root grinding | F15: Volume (tons) | G15: Unit price (baht) | H15: Total revenue (baht)
B16: Wash skin | G16: 0.25
B17: Soil skin | G17: 0.03
B18: Pulp with 79% moisture content | G18: 0.352
G19: Total
B22: Activities | C22: Response | E22: Target | H22: Budget | J22: Remarks
E26: Total | H26: =SUM(H23:H25) -> 0
B42: หมายเหตุ : กรณีไม่มีการเซ็นอนุมัติในแบบฟอร์ม ให้แนบเป็นอีเมลล์อนุมัติแทนได้

Sheet SK MAP - Dec 26  (2)
B1: Monthly Activities Plan
B3: SK plant : The Root Purchasing of December 2026 (Total Operation Day 26 days)
B4: Root rolling Forecast | C4: Plan Original LE0.2026 | D4: Latest View | E4: Root purchase forecasting | F4: Remarks
C5: (18/12/25) | E5: Most likely
B6: Root purchase expectation | E6: =F13 -> 27600 | M6: Number of Days | N6: 26
B7: Starch content forecasting | E7: =G13/100 -> 0.26717391 | M7: Volume Plan | N7: ='LV02.04.2026 cost+ Act.'!M9 -> 27600
B8: Root price forecasting | E8: =H13 -> 3.0728261 | M8: Farmer Daily supply | N8: 300
B9: PPDS. Forecasting | E9: =I13 -> 11.501221
B10: Expectation of root source purchasing. | E10: Farmer % of supply | F10: Volume/month | G10: Starch (%) | H10: Price(B./kg) | I10: PPDS (B./kg) | J10: Root expense amount (K baht)
B11: Farmer | E11: =F11/E6 -> 0.2826087 | F11: =N6*N8 -> 7800 | G11: 26 | H11: 2.75 | I11: =(H11/G11)*100 -> 10.576923 | J11: =H11*F11 -> 21450 | M11: F : 25% | N11: 2.7
B12: Broker | E12: =100%-E11 -> 0.7173913 | F12: =N7-F11 -> 19800 | G12: 27 | H12: 3.2 | I12: =(H12/G12)*100 -> 11.851852 | J12: =H12*F12 -> 63360 | M12: B : 25% | N12: 3.1 | P12: Sugar cane
B13: Total | E13: =SUM(E11:E12) -> 1 | F13: =SUM(F11:F12) -> 27600 | G13: =SUMPRODUCT($E$11:$E$12,G11:G12) -> 26.717391 | H13: =SUMPRODUCT($E$11:$E$12,H11:H12) -> 3.0728261 | I13: =(H13/G13)*100 -> 11.501221 | J13: =SUM(J11:J12) -> 84810
B15: Expectation of Co-products | E15: Portion to root grinding | F15: Volume (tons) | G15: Unit price (baht) | H15: Total revenue (baht)
B16: Wash skin | E16: 0.02 | F16: =E6*E16 -> 552 | G16: 0.2 | H16: =G16*F16*1000 -> 110400
B17: Soil skin | E17: 0.061 | F17: =E6*E17 -> 1683.6 | G17: 0.03 | H17: =G17*F17*1000 -> 50508
B18: Pulp with 79% moisture content | E18: 0.2 | F18: =E6*E18 -> 5520 | G18: 0.282 | H18: =G18*F18*1000 -> 1556640
G19: Total
B22: Activities | C22: Response | E22: Target | H22: Budget | J22: Remarks
B23: Farmers-broker visit & | C23: Buyer | E23: Continuous root supply through year. | H23: 15000 | J23: - Farmer-Broker
B24: meeting expense for | J24: visit budget
B25: Root Sourcing department
E26: Total | H26: =SUM(H23:H25) -> 15000
B42: หมายเหตุ : กรณีไม่มีการเซ็นอนุมัติในแบบฟอร์ม ให้แนบเป็นอีเมลล์อนุมัติแทนได้

Sheet SK MAP -Dec 2026 _ 26.03.26 
B1: Monthly Activities Plan
B3: SK plant : The Root Purchasing of December 2026 (Total Operation Day 26 days)
B4: Root rolling Forecast | C4: Plan Original LE0.2026 | D4: Latest View | E4: Root purchase forecasting | F4: Remarks
C5: (18/12/25) | D5: (11/2/2026) | E5: Most likely
B6: Root purchase expectation | E6: =F13 -> 27600 | M6: Number of Days | N6: 26
B7: Starch content forecasting | E7: =G13/100 -> 0.25 | M7: Volume Plan | N7: 27600
B8: Root price forecasting | E8: =H13 -> 3.1746377 | M8: Farmer Daily supply | N8: 200
B9: PPDS. Forecasting | E9: =I13 -> 12.698551
B10: Expectation of root source purchasing. | E10: Farmer % of supply | F10: Volume/month | G10: Starch (%) | H10: Price(B./kg) | I10: PPDS (B./kg) | J10: Root expense amount (K baht)
B11: Farmer | E11: =F11/E6 -> 0.1884058 | F11: =N6*N8 -> 5200 | G11: 25 | H11: 2.85 | I11: =(H11/G11)*100 -> 11.4 | J11: =H11*F11 -> 14820 | M11: F : 25% | N11: 2.85
B12: Broker | E12: =100%-E11 -> 0.8115942 | F12: =N7-F11 -> 22400 | G12: 25 | H12: 3.25 | I12: =(H12/G12)*100 -> 13 | J12: =H12*F12 -> 72800 | M12: B : 25% | N12: 3.25
B13: Total | E13: =SUM(E11:E12) -> 1 | F13: =SUM(F11:F12) -> 27600 | G13: =SUMPRODUCT($E$11:$E$12,G11:G12) -> 25 | H13: =SUMPRODUCT($E$11:$E$12,H11:H12) -> 3.1746377 | I13: =(H13/G13)*100 -> 12.698551 | J13: =SUM(J11:J12) -> 87620
B15: Expectation of Co-products | E15: Portion to root grinding | F15: Volume (tons) | G15: Unit price (baht) | H15: Total revenue (baht)
B16: Wash skin | G16: 0.25
B17: Soil skin | G17: 0.03
B18: Pulp with 79% moisture content | G18: 0.352
G19: Total
B22: Activities | C22: Response | E22: Target | H22: Budget | J22: Remarks
E26: Total | H26: =SUM(H23:H25) -> 0
B42: หมายเหตุ : กรณีไม่มีการเซ็นอนุมัติในแบบฟอร์ม ให้แนบเป็นอีเมลล์อนุมัติแทนได้

Sheet KSN MAP - Mar 2026 (2)
B1: Monthly Activities Plan
B3: KSN plant : The Root Purchasing of March 2026 (Total Operation Day 31 days)
B4: Root rolling Forecast | C4: Plan Original LE0.2026 | D4: Latest View | E4: Root purchase forecasting | F4: Remarks
C5: (1/12/25) | D5: (16/01/26) | E5: Most likely
B6: Root purchase expectation | C6: 21700 | D6: =E6 -> 20150 | E6: =F13 -> 20150 | M6: Number of Days | N6: 31
B7: Starch content forecasting | C7: 0.265 | D7: =E7 -> 0.26184615 | E7: =G13/100 -> 0.26184615 | M7: Volume Plan/day | N7: 650
B8: Root price forecasting | C8: 2.63 | D8: =E8 -> 2.8946154 | E8: =H13 -> 2.8946154 | M8: Volume Plan/montn | N8: =N6*N7 -> 20150
B9: PPDS. Forecasting | C9: 9.92 | D9: =E9 -> 11.054642 | E9: =I13 -> 11.054642 | M9: Farmer Daily supply | N9: 300
B10: Expectation of root source purchasing. | E10: Farmer % of supply | F10: Volume/month | G10: Starch (%) | H10: Price(B./kg) | I10: PPDS (B./kg) | J10: Root expense amount (K baht)
B11: Farmer | E11: =F11/E6 -> 0.46153846 | F11: =N9*N6 -> 9300 | G11: 26.4 | H11: =2.78+0.05 -> 2.83 | I11: =(H11/G11)*100 -> 10.719697 | J11: =H11*F11 -> 26319 | M11: F : 25% | N11: 2.75
B12: Broker | E12: =100%-E11 -> 0.53846154 | F12: =N8-F11 -> 10850 | G12: 26 | H12: 2.95 | I12: =(H12/G12)*100 -> 11.346154 | J12: =H12*F12 -> 32007.5 | M12: B : 25% | N12: 2.9
B13: Total | E13: =SUM(E11:E12) -> 1 | F13: =SUM(F11:F12) -> 20150 | G13: =SUMPRODUCT($E$11:$E$12,G11:G12) -> 26.184615 | H13: =SUMPRODUCT($E$11:$E$12,H11:H12) -> 2.8946154 | I13: =(H13/G13)*100 -> 11.054642 | J13: =SUM(J11:J12) -> 58326.5
B15: Expectation of Co-products | E15: Portion to root grinding | F15: Volume (tons) | G15: Unit price (baht) | H15: Total revenue (baht)
B16: Wash skin | E16: 0.02 | F16: =E6*E16 -> 403 | G16: 0.12 | H16: =G16*F16*1000 -> 48360
B17: Soil skin | E17: 0.061 | F17: =E6*E17 -> 1229.15 | G17: 0.03 | H17: =G17*F17*1000 -> 36874.5
B18: Pulp | E18: 0.2 | F18: =E6*E18 -> 4030 | G18: 0.134 | H18: =G18*F18*1000 -> 540020
G19: Total
B22: Activities | C22: Response | E22: Target | H22: Budget | J22: Remarks
B23: Farmers-broker visit & | C23: Buyer | E23: Continuous root supply through year. | H23: - | J23: - Farmer-Broker
B24: meeting expense for | J24: visit budget
B25: Root Sourcing department
E26: Total | H26: =SUM(H23:H25) -> 0
B43: หมายเหตุ : กรณีไม่มีการเซ็นอนุมัติในแบบฟอร์ม ให้แนบเป็นอีเมลล์อนุมัติแทนได้

Sheet KSN MAP - Mar 2026 _ 22.02.2026
B1: Monthly Activities Plan
B3: KSN plant : The Root Purchasing of March 2026 (Total Operation Day 31 days)
B4: Root rolling Forecast | C4: Plan Original LE0.2026 | D4: Latest View | E4: Root purchase forecasting | F4: Remarks
C5: (1/12/25) | D5: (11/02/26) | E5: Most likely
B6: Root purchase expectation | C6: 21700 | D6: 20150 | E6: =F13 -> 20150 | F6: - There is high market competition, especially from nearby starch factories. | M6: Number of Days | N6: 31
B7: Starch content forecasting | C7: 0.265 | D7: 0.26184615 | E7: =G13/100 -> 0.265 | F7: - ASIA MODIFIED STARCH : 25% , Farmer 2.85 THB/kg and Broker 3.00 THB/kg | M7: Volume Plan/day | N7: 650
B8: Root price forecasting | C8: 2.63 | D8: 2.8946154 | E8: =H13 -> 2.8992308 | F8: (This report references the market price on 22 February 2026.) | M8: Volume Plan/montn | N8: =N6*N7 -> 20150
B9: PPDS. Forecasting | C9: 9.92 | D9: 11.054642 | E9: =I13 -> 10.940493 | F9: - Farmer Volume Plan 350 tons/day. | M9: Farmer Daily supply | N9: 350
B10: Expectation of root source purchasing. | E10: Farmer % of supply | F10: Volume/month | G10: Starch (%) | H10: Price(B./kg) | I10: PPDS (B./kg) | J10: Root expense amount (K baht)
B11: Farmer | E11: =F11/E6 -> 0.53846154 | F11: =N9*N6 -> 10850 | G11: 26.5 | H11: 2.875 | I11: =(H11/G11)*100 -> 10.849057 | J11: =H11*F11 -> 31193.75 | M11: F : 25% | N11: 2.8
B12: Broker | E12: =100%-E11 -> 0.46153846 | F12: =N8-F11 -> 9300 | G12: 26.5 | H12: 2.9275 | I12: =(H12/G12)*100 -> 11.04717 | J12: =H12*F12 -> 27225.75 | M12: B : 25% | N12: 2.85
B13: Total | E13: =SUM(E11:E12) -> 1 | F13: =SUM(F11:F12) -> 20150 | G13: =SUMPRODUCT($E$11:$E$12,G11:G12) -> 26.5 | H13: =SUMPRODUCT($E$11:$E$12,H11:H12) -> 2.8992308 | I13: =(H13/G13)*100 -> 10.940493 | J13: =SUM(J11:J12) -> 58419.5
B15: Expectation of Co-products | E15: Portion to root grinding | F15: Volume (tons) | G15: Unit price (baht) | H15: Total revenue (baht)
B16: Wash skin | E16: 0.02 | F16: =E6*E16 -> 403 | G16: 0.12 | H16: =G16*F16*1000 -> 48360
B17: Soil skin | E17: 0.061 | F17: =E6*E17 -> 1229.15 | G17: 0.03 | H17: =G17*F17*1000 -> 36874.5
B18: Pulp | E18: 0.2 | F18: =E6*E18 -> 4030 | G18: 0.134 | H18: =G18*F18*1000 -> 540020
G19: Total
B22: Activities | C22: Response | E22: Target | H22: Budget | J22: Remarks
B23: Farmers-broker visit & | C23: Buyer | E23: Continuous root supply through year. | H23: - | J23: - Farmer-Broker
B24: meeting expense for | J24: visit budget
B25: Root Sourcing department
E26: Total | H26: =SUM(H23:H25) -> 0
B43: หมายเหตุ : กรณีไม่มีการเซ็นอนุมัติในแบบฟอร์ม ให้แนบเป็นอีเมลล์อนุมัติแทนได้

Sheet KSN MAP - Apr 2026 (2)
B1: Monthly Activities Plan
B3: KSN plant : The Root Purchasing of April 2026 (Total Operation Day 24 days)
B4: Root rolling Forecast | C4: Plan Original LE0.2026 | D4: Latest View | E4: Root purchase forecasting | F4: Remarks
C5: (1/12/25) | E5: Most likely
B6: Root purchase expectation | E6: =F13 -> 16800 | M6: Number of Days | N6: 24
B7: Starch content forecasting | E7: =G13/100 -> 0.23807143 | M7: Volume Plan/day | N7: 700
B8: Root price forecasting | E8: =H13 -> 2.8442857 | M8: Volume Plan/montn | N8: =N6*N7 -> 16800
B9: PPDS. Forecasting | E9: =I13 -> 11.947195 | M9: Farmer Daily supply | N9: 200
B10: Expectation of root source purchasing. | E10: Farmer % of supply | F10: Volume/month | G10: Starch (%) | H10: Price(B./kg) | I10: PPDS (B./kg) | J10: Root expense amount (K baht)
B11: Farmer | E11: =F11/E6 -> 0.28571429 | F11: =N9*N6 -> 4800 | G11: 23.7 | H11: 2.73 | I11: =(H11/G11)*100 -> 11.518987 | J11: =H11*F11 -> 13104 | M11: F : 25% | N11: 2.8
B12: Broker | E12: =100%-E11 -> 0.71428571 | F12: =N8-F11 -> 12000 | G12: 23.85 | H12: 2.89 | I12: =(H12/G12)*100 -> 12.1174 | J12: =H12*F12 -> 34680 | M12: B : 25% | N12: 2.95
B13: Total | E13: =SUM(E11:E12) -> 1 | F13: =SUM(F11:F12) -> 16800 | G13: =SUMPRODUCT($E$11:$E$12,G11:G12) -> 23.807143 | H13: =SUMPRODUCT($E$11:$E$12,H11:H12) -> 2.8442857 | I13: =(H13/G13)*100 -> 11.947195 | J13: =SUM(J11:J12) -> 47784
B15: Expectation of Co-products | E15: Portion to root grinding | F15: Volume (tons) | G15: Unit price (baht) | H15: Total revenue (baht)
B16: Wash skin | E16: 0.02 | F16: =E6*E16 -> 336 | G16: 0.12 | H16: =G16*F16*1000 -> 40320
B17: Soil skin | E17: 0.061 | F17: =E6*E17 -> 1024.8 | G17: 0.03 | H17: =G17*F17*1000 -> 30744
B18: Pulp | E18: 0.2 | F18: =E6*E18 -> 3360 | G18: 0.134 | H18: =G18*F18*1000 -> 450240
G19: Total
B22: Activities | C22: Response | E22: Target | H22: Budget | J22: Remarks
B23: Farmers-broker visit & | C23: Buyer | E23: Continuous root supply through year. | H23: - | J23: - Farmer-Broker
B24: meeting expense for | J24: visit budget
B25: Root Sourcing department
E26: Total | H26: =SUM(H23:H25) -> 0
B43: หมายเหตุ : กรณีไม่มีการเซ็นอนุมัติในแบบฟอร์ม ให้แนบเป็นอีเมลล์อนุมัติแทนได้

Sheet KSN MAP - Apr 2026 _ 26.03.206
B1: Monthly Activities Plan
B3: KSN plant : The Root Purchasing of April 2026 (Total Operation Day 24 days)
B4: Root rolling Forecast | C4: Plan Original LE0.2026 | D4: Latest View | E4: Root purchase forecasting | F4: Remarks
C5: (18/12/25) | D5: (11/2/2026) | E5: Most likely
B6: Root purchase expectation | C6: 16800 | D6: 16800 | E6: =F13 -> 16800 | F6: - The estimated volume supply is approximately 700 tons per day, with farmers contributing about 120 tons per day. - According to this month’s projection reference, the industry is facing high competition from starch mills and cassava chip factories, limited root supply, low starch content, and a continuing fuel crisis. | M6: Number of Days | N6: 24
B7: Starch content forecasting | C7: 0.238 | D7: 0.23807143 | E7: =G13/100 -> 0.23 | M7: Volume Plan/day | N7: 700
B8: Root price forecasting | C8: 2.38 | D8: 2.8442857 | E8: =H13 -> 3.0485714 | M8: Volume Plan/montn | N8: =N6*N7 -> 16800
B9: PPDS. Forecasting | C9: 10 | D9: 11.947195 | E9: =I13 -> 13.254658 | M9: Farmer Daily supply | N9: 120
B10: Expectation of root source purchasing. | E10: Farmer % of supply | F10: Volume/month | G10: Starch (%) | H10: Price(B./kg) | I10: PPDS (B./kg) | J10: Root expense amount (K baht)
B11: Farmer | E11: =F11/E6 -> 0.17142857 | F11: =N9*N6 -> 2880 | G11: 23 | H11: 2.8 | I11: =(H11/G11)*100 -> 12.173913 | J11: =H11*F11 -> 8064 | M11: F : 25% | N11: 2.9
B12: Broker | E12: =100%-E11 -> 0.82857143 | F12: =N8-F11 -> 13920 | G12: 23 | H12: 3.1 | I12: =(H12/G12)*100 -> 13.478261 | J12: =H12*F12 -> 43152 | M12: B : 25% | N12: 3.2
B13: Total | E13: =SUM(E11:E12) -> 1 | F13: =SUM(F11:F12) -> 16800 | G13: =SUMPRODUCT($E$11:$E$12,G11:G12) -> 23 | H13: =SUMPRODUCT($E$11:$E$12,H11:H12) -> 3.0485714 | I13: =(H13/G13)*100 -> 13.254658 | J13: =SUM(J11:J12) -> 51216
B15: Expectation of Co-products | E15: Portion to root grinding | F15: Volume (tons) | G15: Unit price (baht) | H15: Total revenue (baht)
B16: Wash skin | G16: 0.12
B17: Soil skin | G17: 0.03
B18: Pulp | G18: 0.134
G19: Total
B22: Activities | C22: Response | E22: Target | H22: Budget | J22: Remarks
E26: Total | H26: =SUM(H23:H25) -> 0
B43: หมายเหตุ : กรณีไม่มีการเซ็นอนุมัติในแบบฟอร์ม ให้แนบเป็นอีเมลล์อนุมัติแทนได้

Sheet KSN MAP - Apr 2026 Rev1-2.04.26
B1: Monthly Activities Plan
B3: KSN plant : The Root Purchasing of April 2026 (Total Operation Day 24 days) Rev.:01
B4: Root rolling Forecast | C4: Plan Original LE0.2026 | D4: Latest View | E4: Root purchase forecasting | F4: Remarks
C5: (18/12/25) | D5: (11/2/2026) | E5: Most likely
B6: Root purchase expectation | C6: 16800 | D6: 16800 | E6: =F13 -> 16800 | F6: - The estimated volume supply is approximately 700 tons per day, with farmers contributing about 120 tons per day. - According to this month’s projection reference, the industry is facing high competition from starch mills and cassava chip factories, limited root supply, low starch content, and a continuing fuel crisis. | M6: Number of Days | N6: 24
B7: Starch content forecasting | C7: 0.238 | D7: 0.23807143 | E7: =G13/100 -> 0.23 | M7: Volume Plan/day | N7: 700
B8: Root price forecasting | C8: 2.38 | D8: 2.8442857 | E8: =H13 -> 3.0985714 | M8: Volume Plan/montn | N8: =N6*N7 -> 16800
B9: PPDS. Forecasting | C9: 10 | D9: 11.947195 | E9: =I13 -> 13.47205 | M9: Farmer Daily supply | N9: 120
B10: Expectation of root source purchasing. | E10: Farmer % of supply | F10: Volume/month | G10: Starch (%) | H10: Price(B./kg) | I10: PPDS (B./kg) | J10: Root expense amount (K baht)
B11: Farmer | E11: =F11/E6 -> 0.17142857 | F11: =N9*N6 -> 2880 | G11: 23 | H11: 2.85 | I11: =(H11/G11)*100 -> 12.391304 | J11: =H11*F11 -> 8208 | M11: F : 25% | N11: 2.95
B12: Broker | E12: =100%-E11 -> 0.82857143 | F12: =N8-F11 -> 13920 | G12: 23 | H12: 3.15 | I12: =(H12/G12)*100 -> 13.695652 | J12: =H12*F12 -> 43848 | M12: B : 25% | N12: 3.25
B13: Total | E13: =SUM(E11:E12) -> 1 | F13: =SUM(F11:F12) -> 16800 | G13: =SUMPRODUCT($E$11:$E$12,G11:G12) -> 23 | H13: =SUMPRODUCT($E$11:$E$12,H11:H12) -> 3.0985714 | I13: =(H13/G13)*100 -> 13.47205 | J13: =SUM(J11:J12) -> 52056
B15: Expectation of Co-products | E15: Portion to root grinding | F15: Volume (tons) | G15: Unit price (baht) | H15: Total revenue (baht)
B16: Wash skin | G16: 0.12
B17: Soil skin | G17: 0.03
B18: Pulp | G18: 0.134
G19: Total
B22: Activities | C22: Response | E22: Target | H22: Budget | J22: Remarks
E26: Total | H26: =SUM(H23:H25) -> 0
B43: หมายเหตุ : กรณีไม่มีการเซ็นอนุมัติในแบบฟอร์ม ให้แนบเป็นอีเมลล์อนุมัติแทนได้

Sheet KSN MAP - May 2026 (2)
B1: Monthly Activities Plan
B3: KSN plant : The Root Purchasing of May 2026 (Total Operation Day 31 days)
B4: Root rolling Forecast | C4: Plan Original LE0.2026 | D4: Latest View | E4: Root purchase forecasting | F4: Remarks
C5: (1/12/25) | E5: Most likely
B6: Root purchase expectation | E6: =F13 -> 21700 | M6: Number of Days | N6: 31
B7: Starch content forecasting | E7: =G13/100 -> 0.21551429 | M7: Volume Plan/day | N7: 700
B8: Root price forecasting | E8: =H13 -> 2.7264286 | M8: Volume Plan/montn | N8: =N6*N7 -> 21700
B9: PPDS. Forecasting | E9: =I13 -> 12.650802 | M9: Farmer Daily supply | N9: 250
B10: Expectation of root source purchasing. | E10: Farmer % of supply | F10: Volume/month | G10: Starch (%) | H10: Price(B./kg) | I10: PPDS (B./kg) | J10: Root expense amount (K baht)
B11: Farmer | E11: =F11/E6 -> 0.35714286 | F11: =N9*N6 -> 7750 | G11: 21.5 | H11: 2.63 | I11: =(H11/G11)*100 -> 12.232558 | J11: =H11*F11 -> 20382.5 | M11: F : 25% | N11: 2.8
B12: Broker | E12: =100%-E11 -> 0.64285714 | F12: =N8-F11 -> 13950 | G12: 21.58 | H12: 2.78 | I12: =(H12/G12)*100 -> 12.882298 | J12: =H12*F12 -> 38781 | M12: B : 25% | N12: 2.95
B13: Total | E13: =SUM(E11:E12) -> 1 | F13: =SUM(F11:F12) -> 21700 | G13: =SUMPRODUCT($E$11:$E$12,G11:G12) -> 21.551429 | H13: =SUMPRODUCT($E$11:$E$12,H11:H12) -> 2.7264286 | I13: =(H13/G13)*100 -> 12.650802 | J13: =SUM(J11:J12) -> 59163.5
B15: Expectation of Co-products | E15: Portion to root grinding | F15: Volume (tons) | G15: Unit price (baht) | H15: Total revenue (baht)
B16: Wash skin | E16: 0.02 | F16: =E6*E16 -> 434 | G16: 0.12 | H16: =G16*F16*1000 -> 52080
B17: Soil skin | E17: 0.061 | F17: =E6*E17 -> 1323.7 | G17: 0.03 | H17: =G17*F17*1000 -> 39711
B18: Pulp | E18: 0.2 | F18: =E6*E18 -> 4340 | G18: 0.134 | H18: =G18*F18*1000 -> 581560
G19: Total
B22: Activities | C22: Response | E22: Target | H22: Budget | J22: Remarks
B23: Farmers-broker visit & | C23: Buyer | E23: Continuous root supply through year. | H23: - | J23: - Farmer-Broker
B24: meeting expense for | J24: visit budget
B25: Root Sourcing department
E26: Total | H26: =SUM(H23:H25) -> 0
B43: หมายเหตุ : กรณีไม่มีการเซ็นอนุมัติในแบบฟอร์ม ให้แนบเป็นอีเมลล์อนุมัติแทนได้

Sheet KSN MAP - May 2026_02.04.26
B1: Monthly Activities Plan
B3: KSN plant : The Root Purchasing of May 2026 (Total Operation Day 31 days)
B4: Root rolling Forecast | C4: Plan Original LE0.2026 | D4: Latest View | E4: Root purchase forecasting | F4: Remarks
C5: (1/12/25) | E5: Most likely
B6: Root purchase expectation | E6: =F13 -> 21700 | M6: Number of Days | N6: 31
B7: Starch content forecasting | E7: =G13/100 -> 0.21551429 | M7: Volume Plan/day | N7: 700
B8: Root price forecasting | E8: =H13 -> 3.005 | M8: Volume Plan/montn | N8: =N6*N7 -> 21700
B9: PPDS. Forecasting | E9: =I13 -> 13.943391 | M9: Farmer Daily supply | N9: 250
B10: Expectation of root source purchasing. | E10: Farmer % of supply | F10: Volume/month | G10: Starch (%) | H10: Price(B./kg) | I10: PPDS (B./kg) | J10: Root expense amount (K baht)
B11: Farmer | E11: =F11/E6 -> 0.35714286 | F11: =N9*N6 -> 7750 | G11: 21.5 | H11: =2.63+0.15 -> 2.78 | I11: =(H11/G11)*100 -> 12.930233 | J11: =H11*F11 -> 21545 | M11: F : 25% | N11: 2.95
B12: Broker | E12: =100%-E11 -> 0.64285714 | F12: =N8-F11 -> 13950 | G12: 21.58 | H12: =2.78+0.35 -> 3.13 | I12: =(H12/G12)*100 -> 14.504171 | J12: =H12*F12 -> 43663.5 | M12: B : 25% | N12: 3.3
B13: Total | E13: =SUM(E11:E12) -> 1 | F13: =SUM(F11:F12) -> 21700 | G13: =SUMPRODUCT($E$11:$E$12,G11:G12) -> 21.551429 | H13: =SUMPRODUCT($E$11:$E$12,H11:H12) -> 3.005 | I13: =(H13/G13)*100 -> 13.943391 | J13: =SUM(J11:J12) -> 65208.5
B15: Expectation of Co-products | E15: Portion to root grinding | F15: Volume (tons) | G15: Unit price (baht) | H15: Total revenue (baht)
B16: Wash skin | E16: 0.02 | F16: =E6*E16 -> 434 | G16: 0.12 | H16: =G16*F16*1000 -> 52080
B17: Soil skin | E17: 0.061 | F17: =E6*E17 -> 1323.7 | G17: 0.03 | H17: =G17*F17*1000 -> 39711
B18: Pulp | E18: 0.2 | F18: =E6*E18 -> 4340 | G18: 0.134 | H18: =G18*F18*1000 -> 581560
G19: Total
B22: Activities | C22: Response | E22: Target | H22: Budget | J22: Remarks
B23: Farmers-broker visit & | C23: Buyer | E23: Continuous root supply through year. | H23: - | J23: - Farmer-Broker
B24: meeting expense for | J24: visit budget
B25: Root Sourcing department
E26: Total | H26: =SUM(H23:H25) -> 0
B43: หมายเหตุ : กรณีไม่มีการเซ็นอนุมัติในแบบฟอร์ม ให้แนบเป็นอีเมลล์อนุมัติแทนได้

Sheet KSN MAP - May 2026_24.04.26
B1: Monthly Activities Plan
B3: KSN plant : The Root Purchasing of May 2026 (Total Operation Day 31 days)
B4: Root rolling Forecast | C4: Plan Original LE0.2026 | D4: Latest View | E4: Root purchase forecasting | F4: Remarks
C5: (18/12/25) | D5: (2/4/26) | E5: Most likely
B6: Root purchase expectation | C6: 21700 | D6: 21700 | E6: =F13 -> 15500 | F6: - The estimated volume supply is approximately 500 tons/day, With farmers contributing about 60 tons /day. - According to this month’s projection reference, the industry is facing high competition from starch mills and cassava chip factories, limited root supply, low starch content. | M6: Number of Days | N6: 31
B7: Starch content forecasting | C7: 0.2155 | D7: 0.21551429 | E7: =G13/100 -> 0.2088 | M7: Volume Plan/day | N7: 500
B8: Root price forecasting | C8: 2.18 | D8: 3.005 | E8: =H13 -> 3.408 | M8: Volume Plan/montn | N8: =N6*N7 -> 15500
B9: PPDS. Forecasting | C9: 10.116009 | D9: 13.943391 | E9: =I13 -> 16.321839 | M9: Farmer Daily supply | N9: 60
B10: Expectation of root source purchasing. | E10: Farmer % of supply | F10: Volume/month | G10: Starch (%) | H10: Price(B./kg) | I10: PPDS (B./kg) | J10: Root expense amount (K baht)
B11: Farmer | E11: =F11/E6 -> 0.12 | F11: =N9*N6 -> 1860 | G11: 20 | H11: 3.1 | I11: =(H11/G11)*100 -> 15.5 | J11: =H11*F11 -> 5766 | M11: F : 25% | N11: 3.35
B12: Broker | E12: =100%-E11 -> 0.88 | F12: =N8-F11 -> 13640 | G12: 21 | H12: 3.45 | I12: =(H12/G12)*100 -> 16.428571 | J12: =H12*F12 -> 47058 | M12: B : 25% | N12: 3.65
B13: Total | E13: =SUM(E11:E12) -> 1 | F13: =SUM(F11:F12) -> 15500 | G13: =SUMPRODUCT($E$11:$E$12,G11:G12) -> 20.88 | H13: =SUMPRODUCT($E$11:$E$12,H11:H12) -> 3.408 | I13: =(H13/G13)*100 -> 16.321839 | J13: =SUM(J11:J12) -> 52824
B15: Expectation of Co-products | E15: Portion to root grinding | F15: Volume (tons) | G15: Unit price (baht) | H15: Total revenue (baht)
B16: Wash skin | G16: 0.12 | H16: =G16*F16*1000 -> 0 | N16: =I13*3% -> 0.48965517
B17: Soil skin | G17: 0.03 | H17: =G17*F17*1000 -> 0 | N17: =I13+N16 -> 16.811494
B18: Pulp | G18: 0.134 | H18: =G18*F18*1000 -> 0
G19: Total
B22: Activities | C22: Response | E22: Target | H22: Budget | J22: Remarks
B23: Farmers-broker visit & | C23: Buyer | E23: Continuous root supply through year. | H23: - | J23: - Farmer-Broker
B24: meeting expense for | J24: visit budget
B25: Root Sourcing department
E26: Total | H26: =SUM(H23:H25) -> 0
B43: หมายเหตุ : กรณีไม่มีการเซ็นอนุมัติในแบบฟอร์ม ให้แนบเป็นอีเมลล์อนุมัติแทนได้

Sheet KSN MAP - Jun 2026 (2)
B1: Monthly Activities Plan
B3: KSN plant : The Root Purchasing of June 2026 (Total Operation Day 30 days)
B4: Root rolling Forecast | C4: Plan Original LE0.2026 | D4: Latest View | E4: Root purchase forecasting | F4: Remarks
C5: (1/12/25) | E5: Most likely
B6: Root purchase expectation | E6: =F13 -> 21000 | M6: Number of Days | N6: 30
B7: Starch content forecasting | E7: =G13/100 -> 0.21496429 | M7: Volume Plan/day | N7: 700
B8: Root price forecasting | E8: =H13 -> 2.755 | M8: Volume Plan/montn | N8: =N6*N7 -> 21000
B9: PPDS. Forecasting | E9: =I13 -> 12.816082 | M9: Farmer Daily supply | N9: 250
B10: Expectation of root source purchasing. | E10: Farmer % of supply | F10: Volume/month | G10: Starch (%) | H10: Price(B./kg) | I10: PPDS (B./kg) | J10: Root expense amount (K baht)
B11: Farmer | E11: =F11/E6 -> 0.35714286 | F11: =N9*N6 -> 7500 | G11: 21.4 | H11: 2.62 | I11: =(H11/G11)*100 -> 12.242991 | J11: =H11*F11 -> 19650 | M11: F : 25% | N11: 2.8
B12: Broker | E12: =100%-E11 -> 0.64285714 | F12: =N8-F11 -> 13500 | G12: 21.55 | H12: 2.83 | I12: =(H12/G12)*100 -> 13.132251 | J12: =H12*F12 -> 38205 | M12: B : 25% | N12: 3
B13: Total | E13: =SUM(E11:E12) -> 1 | F13: =SUM(F11:F12) -> 21000 | G13: =SUMPRODUCT($E$11:$E$12,G11:G12) -> 21.496429 | H13: =SUMPRODUCT($E$11:$E$12,H11:H12) -> 2.755 | I13: =(H13/G13)*100 -> 12.816082 | J13: =SUM(J11:J12) -> 57855
B15: Expectation of Co-products | E15: Portion to root grinding | F15: Volume (tons) | G15: Unit price (baht) | H15: Total revenue (baht)
B16: Wash skin | E16: 0.02 | F16: =E6*E16 -> 420 | G16: 0.12 | H16: =G16*F16*1000 -> 50400
B17: Soil skin | E17: 0.061 | F17: =E6*E17 -> 1281 | G17: 0.03 | H17: =G17*F17*1000 -> 38430
B18: Pulp | E18: 0.2 | F18: =E6*E18 -> 4200 | G18: 0.134 | H18: =G18*F18*1000 -> 562800
G19: Total
B22: Activities | C22: Response | E22: Target | H22: Budget | J22: Remarks
B23: Farmers-broker visit & | C23: Buyer | E23: Continuous root supply through year. | H23: - | J23: - Farmer-Broker
B24: meeting expense for | J24: visit budget
B25: Root Sourcing department
E26: Total | H26: =SUM(H23:H25) -> 0
B43: หมายเหตุ : กรณีไม่มีการเซ็นอนุมัติในแบบฟอร์ม ให้แนบเป็นอีเมลล์อนุมัติแทนได้

Sheet KSN MAP - Jun 2026_02.04.26
B1: Monthly Activities Plan
B3: KSN plant : The Root Purchasing of June 2026 (Total Operation Day 30 days)
B4: Root rolling Forecast | C4: Plan Original LE0.2026 | D4: Latest View | E4: Root purchase forecasting | F4: Remarks
C5: (1/12/25) | E5: Most likely
B6: Root purchase expectation | E6: =F13 -> 21000 | M6: Number of Days | N6: 30
B7: Starch content forecasting | E7: =G13/100 -> 0.21496429 | M7: Volume Plan/day | N7: 700
B8: Root price forecasting | E8: =H13 -> 3.0014286 | M8: Volume Plan/montn | N8: =N6*N7 -> 21000
B9: PPDS. Forecasting | E9: =I13 -> 13.962452 | M9: Farmer Daily supply | N9: 250
B10: Expectation of root source purchasing. | E10: Farmer % of supply | F10: Volume/month | G10: Starch (%) | H10: Price(B./kg) | I10: PPDS (B./kg) | J10: Root expense amount (K baht)
B11: Farmer | E11: =F11/E6 -> 0.35714286 | F11: =N9*N6 -> 7500 | G11: 21.4 | H11: =2.62+0.15 -> 2.77 | I11: =(H11/G11)*100 -> 12.943925 | J11: =H11*F11 -> 20775 | M11: F : 25% | N11: 2.95
B12: Broker | E12: =100%-E11 -> 0.64285714 | F12: =N8-F11 -> 13500 | G12: 21.55 | H12: =2.83+0.3 -> 3.13 | I12: =(H12/G12)*100 -> 14.524362 | J12: =H12*F12 -> 42255 | M12: B : 25% | N12: 3.3
B13: Total | E13: =SUM(E11:E12) -> 1 | F13: =SUM(F11:F12) -> 21000 | G13: =SUMPRODUCT($E$11:$E$12,G11:G12) -> 21.496429 | H13: =SUMPRODUCT($E$11:$E$12,H11:H12) -> 3.0014286 | I13: =(H13/G13)*100 -> 13.962452 | J13: =SUM(J11:J12) -> 63030
B15: Expectation of Co-products | E15: Portion to root grinding | F15: Volume (tons) | G15: Unit price (baht) | H15: Total revenue (baht)
B16: Wash skin | E16: 0.02 | F16: =E6*E16 -> 420 | G16: 0.12 | H16: =G16*F16*1000 -> 50400
B17: Soil skin | E17: 0.061 | F17: =E6*E17 -> 1281 | G17: 0.03 | H17: =G17*F17*1000 -> 38430
B18: Pulp | E18: 0.2 | F18: =E6*E18 -> 4200 | G18: 0.134 | H18: =G18*F18*1000 -> 562800
G19: Total
B22: Activities | C22: Response | E22: Target | H22: Budget | J22: Remarks
